Workbook

Sheet METRICAS
A1: ALAN GALIANO DISTRIBUCIONES — PANEL DE CONTROL 2026
A2: Gas envasado a domicilio · 365 días al año · Santa Fe · 3425-331010
A4: RESUMEN DEL AÑO
A5: =B22 | D5: =C22 | G5: =IFERROR(C22/B22,0) | J5: =E22 | M5: 698 | P5: 492 | S5: $46,102
A6: FACTURADO AÑO | D6: GANANCIA AÑO | G6: % GANANCIA | J6: Nº VENTAS | M6: CLIENTES | P6: A REACTIVAR | S6: PROM. VENTA
A8: RESUMEN MENSUAL
A9: MES | B9: FACTURADO ($) | C9: GANANCIA ($) | D9: % GANANCIA | E9: Nº VENTAS | F9: 10 | G9: 15 | H9: 45 | I9: EFECTIVO ($) | J9: TRANSFER ($) | K9: PROM. VENTA ($) | M9: Mes | N9: Facturado | O9: Ganancia
A10: Enero | B10: =IFERROR(Enero!O11,0) | C10: =IFERROR(Enero!O12,0) | D10: =IFERROR(C10/B10,0) | E10: =IFERROR(Enero!O18,0) | F10: =IFERROR(Enero!O5,0) | G10: =IFERROR(Enero!O6,0) | H10: =IFERROR(Enero!O7,0) | I10: =IFERROR(Enero!O15,0) | J10: =IFERROR(Enero!O16,0) | K10: =IFERROR(B10/E10,0) | M10: Enero | N10: =IFERROR(Enero!O11,0) | O10: =IFERROR(Enero!O12,0)
A11: Febrero | B11: =IFERROR(Febrero!O11,0) | C11: =IFERROR(Febrero!O12,0) | D11: =IFERROR(C11/B11,0) | E11: =IFERROR(Febrero!O18,0) | F11: =IFERROR(Febrero!O5,0) | G11: =IFERROR(Febrero!O6,0) | H11: =IFERROR(Febrero!O7,0) | I11: =IFERROR(Febrero!O15,0) | J11: =IFERROR(Febrero!O16,0) | K11: =IFERROR(B11/E11,0) | M11: Febrero | N11: =IFERROR(Febrero!O11,0) | O11: =IFERROR(Febrero!O12,0)
A12: Marzo | B12: =IFERROR(Marzo!O11,0) | C12: =IFERROR(Marzo!O12,0) | D12: =IFERROR(C12/B12,0) | E12: =IFERROR(Marzo!O18,0) | F12: =IFERROR(Marzo!O5,0) | G12: =IFERROR(Marzo!O6,0) | H12: =IFERROR(Marzo!O7,0) | I12: =IFERROR(Marzo!O15,0) | J12: =IFERROR(Marzo!O16,0) | K12: =IFERROR(B12/E12,0) | M12: Marzo | N12: =IFERROR(Marzo!O11,0) | O12: =IFERROR(Marzo!O12,0)
A13: Abril | B13: =IFERROR(Abril!O11,0) | C13: =IFERROR(Abril!O12,0) | D13: =IFERROR(C13/B13,0) | E13: =IFERROR(Abril!O18,0) | F13: =IFERROR(Abril!O5,0) | G13: =IFERROR(Abril!O6,0) | H13: =IFERROR(Abril!O7,0) | I13: =IFERROR(Abril!O15,0) | J13: =IFERROR(Abril!O16,0) | K13: =IFERROR(B13/E13,0) | M13: Abril | N13: =IFERROR(Abril!O11,0) | O13: =IFERROR(Abril!O12,0)
A14: Mayo | B14: =IFERROR(Mayo!O11,0) | C14: =IFERROR(Mayo!O12,0) | D14: =IFERROR(C14/B14,0) | E14: =IFERROR(Mayo!O18,0) | F14: =IFERROR(Mayo!O5,0) | G14: =IFERROR(Mayo!O6,0) | H14: =IFERROR(Mayo!O7,0) | I14: =IFERROR(Mayo!O15,0) | J14: =IFERROR(Mayo!O16,0) | K14: =IFERROR(B14/E14,0) | M14: Mayo | N14: =IFERROR(Mayo!O11,0) | O14: =IFERROR(Mayo!O12,0)
A15: Junio | B15: =IFERROR(Junio!O11,0) | C15: =IFERROR(Junio!O12,0) | D15: =IFERROR(C15/B15,0) | E15: =IFERROR(Junio!O18,0) | F15: =IFERROR(Junio!O5,0) | G15: =IFERROR(Junio!O6,0) | H15: =IFERROR(Junio!O7,0) | I15: =IFERROR(Junio!O15,0) | J15: =IFERROR(Junio!O16,0) | K15: =IFERROR(B15/E15,0) | M15: Junio | N15: =IFERROR(Junio!O11,0) | O15: =IFERROR(Junio!O12,0)
A16: Julio | B16: =IFERROR(Julio!O11,0) | C16: =IFERROR(Julio!O12,0) | D16: =IFERROR(C16/B16,0) | E16: =IFERROR(Julio!O18,0) | F16: =IFERROR(Julio!O5,0) | G16: =IFERROR(Julio!O6,0) | H16: =IFERROR(Julio!O7,0) | I16: =IFERROR(Julio!O15,0) | J16: =IFERROR(Julio!O16,0) | K16: =IFERROR(B16/E16,0) | M16: Julio | N16: =IFERROR(Julio!O11,0) | O16: =IFERROR(Julio!O12,0)
A17: Agosto | B17: =IFERROR(Agosto!O11,0) | C17: =IFERROR(Agosto!O12,0) | D17: =IFERROR(C17/B17,0) | E17: =IFERROR(Agosto!O18,0) | F17: =IFERROR(Agosto!O5,0) | G17: =IFERROR(Agosto!O6,0) | H17: =IFERROR(Agosto!O7,0) | I17: =IFERROR(Agosto!O15,0) | J17: =IFERROR(Agosto!O16,0) | K17: =IFERROR(B17/E17,0) | M17: Agosto | N17: =IFERROR(Agosto!O11,0) | O17: =IFERROR(Agosto!O12,0)
A18: Septiembre | B18: =IFERROR(Septiembre!O11,0) | C18: =IFERROR(Septiembre!O12,0) | D18: =IFERROR(C18/B18,0) | E18: =IFERROR(Septiembre!O18,0) | F18: =IFERROR(Septiembre!O5,0) | G18: =IFERROR(Septiembre!O6,0) | H18: =IFERROR(Septiembre!O7,0) | I18: =IFERROR(Septiembre!O15,0) | J18: =IFERROR(Septiembre!O16,0) | K18: =IFERROR(B18/E18,0) | M18: Septiembre | N18: =IFERROR(Septiembre!O11,0) | O18: =IFERROR(Septiembre!O12,0)
A19: Octubre | B19: =IFERROR(Octubre!O11,0) | C19: =IFERROR(Octubre!O12,0) | D19: =IFERROR(C19/B19,0) | E19: =IFERROR(Octubre!O18,0) | F19: =IFERROR(Octubre!O5,0) | G19: =IFERROR(Octubre!O6,0) | H19: =IFERROR(Octubre!O7,0) | I19: =IFERROR(Octubre!O15,0) | J19: =IFERROR(Octubre!O16,0) | K19: =IFERROR(B19/E19,0) | M19: Octubre | N19: =IFERROR(Octubre!O11,0) | O19: =IFERROR(Octubre!O12,0)
A20: Noviembre | B20: =IFERROR(Noviembre!O11,0) | C20: =IFERROR(Noviembre!O12,0) | D20: =IFERROR(C20/B20,0) | E20: =IFERROR(Noviembre!O18,0) | F20: =IFERROR(Noviembre!O5,0) | G20: =IFERROR(Noviembre!O6,0) | H20: =IFERROR(Noviembre!O7,0) | I20: =IFERROR(Noviembre!O15,0) | J20: =IFERROR(Noviembre!O16,0) | K20: =IFERROR(B20/E20,0) | M20: Noviembre | N20: =IFERROR(Noviembre!O11,0) | O20: =IFERROR(Noviembre!O12,0)
A21: Diciembre | B21: =IFERROR(Diciembre!O11,0) | C21: =IFERROR(Diciembre!O12,0) | D21: =IFERROR(C21/B21,0) | E21: =IFERROR(Diciembre!O18,0) | F21: =IFERROR(Diciembre!O5,0) | G21: =IFERROR(Diciembre!O6,0) | H21: =IFERROR(Diciembre!O7,0) | I21: =IFERROR(Diciembre!O15,0) | J21: =IFERROR(Diciembre!O16,0) | K21: =IFERROR(B21/E21,0) | M21: Diciembre | N21: =IFERROR(Diciembre!O11,0) | O21: =IFERROR(Diciembre!O12,0)
A22: TOTAL AÑO | B22: =SUM(B10:B21) | C22: =SUM(C10:C21) | D22: =IFERROR(C22/B22,0) | E22: =SUM(E10:E21) | F22: =SUM(F10:F21) | G22: =SUM(G10:G21) | H22: =SUM(H10:H21) | I22: =SUM(I10:I21) | J22: =SUM(J10:J21) | K22: =IFERROR(B22/E22,0)
A24: FACTURADO VS GANANCIA POR MES ($)

Sheet COSTOS
A1: COSTOS — Actualizá aquí cuando cambien los precios
A2: ⚠ Cada vez que cambie un costo, agregá una fila nueva con la Fecha Desde. Las ganancias se calculan con el costo vigente a la fecha de cada venta.
A4: COSTOS VIGENTES ACTUALES
A5: PRODUCTO | B5: DESCRIPCION | C5: COSTO UNITARIO ($)
A6: Garrafa 10 | B6: Garrafa 10kg — Doméstico | C6: 15000
A7: Garrafa 15 | B7: Garrafa 15kg — Doméstico | C7: 22500
A8: Garrafa 45 | B8: Garrafa 45kg — Comercial | C8: 60000
A9: Yerba 500gr | B9: Yerba 500 gramos | C9: 2300
A10: Bidón | B10: Bidón de agua | C10: 850
A13: HISTORIAL DE COSTOS CON VIGENCIA — Agregá una fila nueva cada vez que cambien los precios
A14: PRODUCTO | B14: FECHA DESDE | C14: COSTO ($) | D14: NOTAS
A15: Garrafa 10 | B15: 46023 | C15: 10500 | D15: Enero-Febrero
A16: Garrafa 15 | B16: 46023 | C16: 15750 | D16: Enero-Febrero
A17: Garrafa 45 | B17: 46023 | C17: 47000 | D17: Enero-Febrero
A18: Yerba 500gr | B18: 46023 | C18: 2325 | D18: Enero-Febrero
A19: Bidón | B19: 46023 | C19: 800 | D19: Enero-Febrero
A20: Garrafa 10 | B20: 46082 | C20: 13500 | D20: Marzo 1-24
A21: Garrafa 15 | B21: 46082 | C21: 20250 | D21: Marzo 1-24
A22: Garrafa 45 | B22: 46082 | C22: 49000 | D22: Marzo 1-24
A23: Yerba 500gr | B23: 46082 | C23: 2300 | D23: Marzo 1-24
A24: Bidón | B24: 46082 | C24: 850 | D24: Marzo 1-24
A25: Garrafa 10 | B25: 46106 | C25: 15000 | D25: Marzo 25+
A26: Garrafa 15 | B26: 46106 | C26: 22500 | D26: Marzo 25+
... A29: Bidón | B29: 46106 | C29: 850 | D29: Marzo 25+

Sheet Enero
A1: VENTAS — ENERO 2026 | Q1: 🏆 RANKING ENERO
A2: ⚠ El nombre del cliente debe ser EXACTAMENTE igual siempre · La ganancia se calcula con el costo vigente a la fecha | Q2: # | R2: Cliente | S2: Facturado | T2: Ganancia | U2: Pedidos | V2: Últ. compra
Q3: 🥇 | R3: AZCUENAGA 5023 | S3: 551500 | T3: -26000 | U3: 9 | V3: 20/04/2026
A4: FECHA | B4: CLIENTE / DIRECCIÓN | C4: 10 | D4: 15 | E4: 45 | F4: YERBA | G4: AGUA | H4: VALOR ($) | I4: EFECTIVO ($) | J4: TRANSFER ($) | K4: ENVASE ($) | L4: GANANCIA ($) | N4: RESUMEN ENERO | Q4: 🥈 | R4: PANA GENESIO | S4: 520500 | T4: 70500 | U4: 7 | V4: 09/03/2026
A5: 46023 | B5: LOS PORKI | E5: 1 | H5: 69000 | J5: 69000 | L5: =IF(K5<>"",22000+K5,22000) | N5: TOTAL 10 | O5: =IFERROR(SUM(C5:C700),0) | Q5: 🥉 | R5: FILOMENA | S5: 468000 | T5: 78000 | U5: 16 | V5: 20/04/2026
B6: PANA GENESIO | C6: 1 | E6: 1 | H6: 88500 | J6: 88500 | L6: =IF(K6<>"",31000+K6,31000) | N6: TOTAL 15 | O6: =IFERROR(SUM(D5:D700),0) | Q6: 4 | R6: OTNIEL | S6: 423400 | T6: 105700 | U6: 10 | V6: 16/04/2026
B7: TACUARI 5717 | C7: 1 | H7: 19500 | J7: 19500 | L7: =IF(K7<>"",9000+K7,9000) | N7: TOTAL 45 | O7: =IFERROR(SUM(E5:E700),0) | Q7: 5 | R7: CAREN | S7: 414000 | T7: 54000 | U7: 6 | V7: 20/04/2026
A8: 46024 | B8: PANA VIEYTES | E8: 1 | H8: 65000 | I8: 65000 | L8: =IF(K8<>"",18000+K8,18000) | N8: TOTAL YERBA | O8: =IFERROR(SUM(F5:F700),0) | Q8: 6 | R8: EXE | S8: 414000 | T8: 54000 | U8: 6 | V8: 19/04/2026
B9: CAREN | E9: 1 | H9: 69000 | J9: 69000 | L9: =IF(K9<>"",22000+K9,22000) | N9: TOTAL AGUA | O9: =IFERROR(SUM(G5:G700),0) | Q9: 7 | R9: SABOREAR | S9: 329000 | T9: 51500 | U9: 8 | V9: 22/04/2026
B10: EXE | E10: 1 | H10: 69000 | J10: 69000 | L10: =IF(K10<>"",22000+K10,22000) | Q10: 8 | R10: LUCHO | S10: 316300 | T10: -7900 | U10: 13 | V10: 20/04/2026
B11: GARMENDIA 9250 | G11: 2 | H11: 9600 | J11: 9600 | L11: =IF(K11<>"",8000+K11,8000) | N11: FACTURACIÓN | O11: =IFERROR(SUM(H5:H700),0) | Q11: 9 | R11: GOLD BURGUER | S11: 316000 | T11: 76000 | U11: 2 | V11: 20/02/2026
B12: DUSSO 6638 | E12: 1 | H12: 65000 | I12: 65000 | L12: =IF(K12<>"",18000+K12,18000) | N12: GANANCIA | O12: =IFERROR(SUM(L5:L700),0) | Q12: 10 | R12: PANA ALBERTI | S12: 298000 | T12: 43000 | U12: 4 | V12: 22/04/2026
A13: 46025 | B13: FACU DONA | C13: 1 | H13: 13500 | I13: 13500 | L13: =IF(K13<>"",3000+K13,3000) | N13: % GANANCIA | O13: =IFERROR(SUM(L5:L700)/SUM(H5:H700),0) | Q13: 11 | R13: BRASERIA | S13: 282000 | T13: 42000 | U13: 4 | V13: 18/04/2026
B14: VICTO CAPE DRUGSTORE | C14: 1 | H14: 19500 | J14: 19500 | L14: =IF(K14<>"",9000+K14,9000) | Q14: 12 | R14: RIO NEGRO 6558 | S14: 270000 | T14: 210000 | U14: 1 | V14: 13/02/2026
B15: LUCHO | C15: 1 | H15: 13000 | I15: 13000 | L15: =IF(K15<>"",2500+K15,2500) | N15: EFECTIVO | O15: =IFERROR(SUM(I5:I700),0) | Q15: 13 | R15: GOLD COSTA ESTE | S15: 231000 | T15: 51000 | U15: 1 | V15: 06/01/2026
B16: BONEO 5315 | C16: 2 | H16: 41000 | J16: 41000 | L16: =IF(K16<>"",20000+K16,20000) | N16: TRANSFERENCIA | O16: =IFERROR(SUM(J5:J700),0) | Q16: 14 | R16: PANA VIEYTES 4500 | S16: 214000 | T16: 19000 | U16: 3 | V16: 16/04/2026
B17: OTNIEL | E17: 1 | H17: 69000 | J17: 69000 | L17: =IF(K17<>"",22000+K17,22000) | Q17: 15 | R17: 9 DE JULIO 1144 BAR | S17: 152000 | T17: 32000 | U17: 1 | V17: 20/01/2026
B18: ARISTOBULO 5879 | D18: 1 | H18: 34500 | I18: 34500 | L18: =IF(K18<>"",18750+K18,18750) | N18: Nº VENTAS | O18: =IFERROR(COUNTA(B5:B700),0) | Q18: 16 | R18: SANDRA | S18: 149000 | T18: 3950 | U18: 6 | V18: 16/04/2026
B19: SABOREAR | C19: 1 | H19: 18000 | J19: 18000 | L19: =IF(K19<>"",7500+K19,7500) | N19: DÍAS DEL MES | O19: 31 | Q19: 17 | R19: PAULO | S19: 146500 | T19: -11000 | U19: 4 | V19: 13/04/2026
B20: LUCIANDO LEIVA Y ALBERTI | C20: 1 | H20: 20500 | I20: 20500 | L20: =IF(K20<>"",10000+K20,10000) | Q20: 18 | R20: DOMINGO SILVA 4217 | S20: 146500 | T20: -3500 | U20: 2 | V20: 19/04/2026
B21: OTNIEL | G21: 2 | H21: 9600 | I21: 4800 | J21: 4800 | L21: =IF(K21<>"",8000+K21,8000) | N21: OBJETIVO ($) | Q21: 19 | R21: PANA GORRITI | S21: 144000 | T21: 24000 | U21: 2 | V21: 12/01/2026
B22: DIOGENES ANTILLES 675 | E22: 1 | H22: 76000 | J22: 76000 | L22: =IF(K22<>"",29000+K22,29000) | N22: DIFERENCIA | O22: =IFERROR(SUM(L5:L700)-N21,0) | Q22: 20 | R22: ALISOS 5837 | S22: 139500 | T22: 124500 | U22: 1 | V22: 04/01/2026
B23: GRAL PAZ 7826 | C23: 1 | H23: 22000 | I23: 22000 | L23: =IF(K23<>"",11500+K23,11500) | Q23: 21 | R23: PANA VIEYTES | S23: 135700 | T23: 13400 | U23: 5 | V23: 16/01/2026
B24: FILOMENA | C24: 2 | H24: 36000 | J24: 36000 | L24: =IF(K24<>"",15000+K24,15000) | N24: KG BUTANO | O24: =IFERROR((SUM(C5:C700)*10)+(SUM(D5:D700)*15),0) | Q24: 22 | R24: ROTI AGUADO | S24: 115000 | T24: 17500 | U24: 1 | V24: 17/04/2026
B25: SABOREARTE CARRO | C25: 1 | H25: 18000 | J25: 18000 | L25: =IF(K25<>"",7500+K25,7500) | N25: KG PROPANO | O25: =IFERROR(SUM(E5:E700)*45,0) | Q25: 23 | R25: NACHO CUEVA | S25: 115000 | T25: 17500 | U25: 3 | V25: 28/01/2026
B26: DRAXXO | C26: 1 | H26: 22000 | I26: 22000 | L26: =IF(K26<>"",11500+K26,11500) | N26: KG TOTAL | O26: =IFERROR(O24+O25,0) | Q26: 24 | R26: ROTI SAN LORENZO | S26: 107000 | T26: 24500 | U26: 3 | V26: 15/04/2026
B27: TACUARI 5717 | C27: 1 | H27: 19500 | J27: 19500 | L27: =IF(K27<>"",9000+K27,9000) | Q27: 25 | R27: CHICLANA 9671 | S27: 84000 | T27: 24000 | U27: 1 | V27: 03/01/2026
B28: NACHO CUEVA | C28: 2 | H28: 34000 | I28: 34000 | L28: =IF(K28<>"",13000+K28,13000) | N28: TICKET PROM. VENTA | O28: =IFERROR(SUM(H5:H700)/COUNTA(B5:B700),0) | Q28: 26 | R28: D SILVA 4217 | S28: 80500 | T28: -2000 | U28: 1 | V28: 11/04/2026
B29: CHICLANA 9671 | E29: 1 | H29: 84000 | J29: 84000 | L29: =IF(K29<>"",37000+K29,37000) | N29: TICKET PROM. GANANCIA | O29: =IFERROR(SUM(L5:L700)/COUNTA(B5:B700),0) | Q29: 27 | R29: ROTI VIEYTES | S29: 78000 | T29: -12000 | U29: 1 | V29: 17/04/2026
B30: BRASERIA | E30: 1 | H30: 69000 | J30: 69000 | L30: =IF(K30<>"",22000+K30,22000) | Q30: 28 | R30: TACUARI 5717 | S30: 78000 | T30: 18000 | U30: 3 | V30: 11/04/2026
A31: 46026 | B31: PARRILA BLAS PARERA | C31: 1 | H31: 16000 | J31: 16000 | L31: =IF(K31<>"",5500+K31,5500) | Q31: 29 | R31: BENTEVEOS DAMIAN | S31: 78000 | T31: 18000 | U31: 1 | V31: 11/01/2026
B32: ALISOS 5837 | C32: 1 | H32: 139500 | J32: 139500 | L32: =IF(K32<>"",129000+K32,129000) | Q32: 30 | R32: BONEO 5363 | S32: 78000 | T32: 18000 | U32: 1 | V32: 16/01/2026
B33: PANA ALBERTI | C33: 1 | E33: 1 | H33: 87000 | I33: 87000 | L33: =IF(K33<>"",29500+K33,29500) | Q33: 31 | R33: 9 DE JULIO 1144 | S33: 77000 | T33: 17000 | U33: 1 | V33: 06/03/2026
B34: C FUNES 4553 | E34: 1 | H34: 69000 | J34: 69000 | L34: =IF(K34<>"",22000+K34,22000) | Q34: 32 | R34: SAVEDRA 10125 | S34: 77000 | T34: 17000 | U34: 1 | V34: 09/04/2026
B35: J CIBILS 2519 | E35: 1 | H35: 72000 | J35: 72000 | L35: =IF(K35<>"",25000+K35,25000) | Q35: 33 | R35: GASTON AMARAL | S35: 77000 | T35: 17000 | U35: 1 | V35: 15/04/2026
B36: M ZAPATA 3304 | C36: 1 | H36: 22000 | J36: 22000 | L36: =IF(K36<>"",11500+K36,11500) | Q36: 34 | R36: NOGALES 2412 | S36: 77000 | T36: 17000 | U36: 1 | V36: 23/03/2026
B37: SABOREAR | D37: 1 | H37: 27000 | J37: 27000 | L37: =IF(K37<>"",11250+K37,11250) | Q37: 35 | R37: JOSE MONTEVERA | S37: 77000 | T37: 17000 | U37: 1 | V37: 18/03/2026
A38: 46027 | B38: PANA VIEYTES | C38: 1 | H38: 16000 | J38: 16000 | L38: =IF(K38<>"",5500+K38,5500) | Q38: 36 | R38: BAIGORRIA 9350 | S38: 77000 | T38: 17000 | U38: 1 | V38: 24/02/2026
B39: PAULO | C39: 2 | D39: 1 | H39: 45000 | I39: 45000 | L39: =IF(K39<>"",8250+K39,8250) | Q39: 37 | R39: LALO | S39: 77000 | T39: 17000 | U39: 1 | V39: 27/02/2026
B40: SANDRA | C40: 1 | G40: 1 | H40: 17000 | I40: 17000 | L40: =IF(K40<>"",5700+K40,5700) | Q40: 38 | R40: ESPORA 5335 | S40: 77000 | T40: 17000 | U40: 1 | V40: 07/01/2026
B41: LUCHO | C41: 2 | H41: 26000 | I41: 26000 | L41: =IF(K41<>"",5000+K41,5000) | Q41: 39 | R41: ALSINA 7981 | S41: 77000 | T41: 17000 | U41: 1 | V41: 17/01/2026
B42: CAREN | E42: 1 | H42: 69000 | J42: 69000 | L42: =IF(K42<>"",22000+K42,22000) | Q42: 40 | R42: MISIONES 5281 | S42: 77000 | T42: 17000 | U42: 1 | V42: 20/01/2026
B43: FILOMENA | C43: 2 | H43: 36000 | I43: 36000 | L43: =IF(K43<>"",15000+K43,15000) | Q43: 41 | R43: LOBOS ROCIO | S43: 77000 | T43: 17000 | U43: 1 | V43: 27/01/2026
B44: SAN MARTIN 1925 | C44: 1 | H44: 19500 | I44: 19500 | L44: =IF(K44<>"",9000+K44,9000) | Q44: 42 | R44: DIOGENES ANTILLES 675 | S44: 76000 | T44: 16000 | U44: 1 | V44: 03/01/2026
B45: LAVAISE 1074 | C45: 1 | G45: 2 | H45: 33600 | J45: 33600 | L45: =IF(K45<>"",21500+K45,21500) | Q45: 43 | R45: NAMUNCURA 4436 | S45: 75000 | T45: 15000 | U45: 1 | V45: 07/04/2026
B46: MAURITO | C46: 2 | H46: 26000 | J46: 26000 | L46: =IF(K46<>"",5000+K46,5000) | Q46: 44 | R46: LOBATO BARBARA | S46: 75000 | T46: 15000 | U46: 1 | V46: 09/01/2026
A47: 46028 | B47: GOLD COSTA ESTE | E47: 3 | H47: 231000 | J47: 231000 | L47: =IF(K47<>"",90000+K47,90000) | Q47: 45 | R47: PUBLICO 4746 | S47: 75000 | T47: 15000 | U47: 1 | V47: 10/01/2026
B48: ROTI DOMINGO SILVA | C48: 4 | H48: 52000 | I48: 52000 | L48: =IF(K48<>"",10000+K48,10000) | Q48: 46 | R48: PUBLICO 8821 | S48: 75000 | T48: 15000 | U48: 1 | V48: 13/01/2026
B49: LUCHO | G49: 1 | H49: 4800 | I49: 4800 | L49: =IF(K49<>"",4000+K49,4000) | Q49: 47 | R49: B IRIGOYEN 8383 | S49: 75000 | T49: 15000 | U49: 1 | V49: 18/01/2026
B50: AZCUENAGA 5023 | C50: 7 | H50: 91000 | J50: 91000 | L50: =IF(K50<>"",17500+K50,17500) | Q50: 48 | R50: FLORENCIO FERNANDEZ 6033 | S50: 75000 | T50: 15000 | U50: 1 | V50: 19/01/2026
B51: R GODOY 1614 | C51: 1 | H51: 19000 | I51: 19000 | L51: =IF(K51<>"",8500+K51,8500) | Q51: 49 | R51: MACHUCA RAMONA1 | S51: 75000 | T51: 15000 | U51: 1 | V51: 23/01/2026
B52: PJE MITRE 2409 | C52: 1 | H52: 19500 | I52: 19500 | L52: =IF(K52<>"",9000+K52,9000) | Q52: 50 | R52: ALVEAR 8278 | S52: 75000 | T52: 15000 | U52: 1 | V52: 26/01/2026
B53: CINDO | F53: 2 | H53: 6500 | J53: 6500 | L53: =IF(K53<>"",1850+K53,1850) | Q53: 51 | R53: BLAS PARERA 5224 | S53: 73500 | T53: 13500 | U53: 1 | V53: 09/04/2026
B54: 9 DE JULIO 1144 | E54: 1 | H54: 77000 | J54: 77000 | L54: =IF(K54<>"",30000+K54,30000) | Q54: 52 | R54: HERNANDARIAS 5150 | S54: 73000 | T54: 13000 | U54: 1 | V54: 12/01/2026
B55: SAVEDRA 6445 | E55: 1 | H55: 72000 | J55: 72000 | L55: =IF(K55<>"",25000+K55,25000) | Q55: 53 | R55: ALELIES 10358 | S55: 73000 | T55: 13000 | U55: 1 | V55: 23/01/2026
A56: 46029 | B56: ESPORA 5335 | E56: 1 | H56: 77000 | I56: 77000 | L56: =IF(K56<>"",30000+K56,30000) | Q56: 54 | R56: PANA GORRITI 4600 | S56: 72000 | T56: 12000 | U56: 1 | V56: 08/04/2026
B57: WILLIAN | D57: 1 | H57: 29500 | J57: 29500 | L57: =IF(K57<>"",13750+K57,13750) | Q57: 55 | R57: J CIBILS 2519 | S57: 72000 | T57: 12000 | U57: 1 | V57: 04/01/2026
B58: LUCHO | D58: 1 | H58: 21000 | I58: 21000 | L58: =IF(K58<>"",5250+K58,5250) | Q58: 56 | R58: SAVEDRA 6445 | S58: 72000 | T58: 12000 | U58: 1 | V58: 06/01/2026
B59: ROTI SAN LORENZO | D59: 1 | H59: 28000 | J59: 28000 | L59: =IF(K59<>"",12250+K59,12250) | Q59: 57 | R59: ALFEREZ MOREIRA 1845 | S59: 72000 | T59: 12000 | U59: 1 | V59: 23/01/2026
B60: PANA HNO FIGUERIOA | E60: 1 | H60: 65000 | J60: 65000 | L60: =IF(K60<>"",18000+K60,18000) | Q60: 58 | R60: GORRITI 6512 | S60: 72000 | T60: 12000 | U60: 1 | V60: 24/01/2026
A61: 46030 | B61: BLAS PARERA 6054 | E61: 1 | H61: 69000 | I61: 69000 | L61: =IF(K61<>"",22000+K61,22000) | Q61: 59 | R61: GORRITI 4600 | S61: 72000 | T61: 12000 | U61: 1 | V61: 31/01/2026
B62: OTNIEL | C62: 1 | E62: 1 | G62: 3 | H62: 101400 | J62: 101400 | L62: =IF(K62<>"",41500+K62,41500) | Q62: 60 | R62: CONDOMINIO 3728 | S62: 71000 | T62: 11000 | U62: 1 | V62: 24/01/2026
B63: JEMA BURGUER | G63: 3 | H63: 14400 | I63: 14400 | L63: =IF(K63<>"",12000+K63,12000) | Q63: 61 | R63: PANA VIEYTES 3800 | S63: 69000 | T63: 9000 | U63: 1 | V63: 08/04/2026
B64: GORRITI 4331 | D64: 1 | H64: 33000 | J64: 33000 | L64: =IF(K64<>"",17250+K64,17250) | Q64: 62 | R64: LOS PORKI | S64: 69000 | T64: 9000 | U64: 1 | V64: 23/03/2026
B65: FILOMENA | C65: 2 | H65: 36000 | I65: 36000 | L65: =IF(K65<>"",15000+K65,15000) | Q65: 63 | R65: C FUNES 4553 | S65: 69000 | T65: 9000 | U65: 1 | V65: 04/01/2026
B66: NACHI CUEVA | C66: 1 | D66: 1 | H66: 45000 | I66: 45000 | L66: =IF(K66<>"",18750+K66,18750) | Q66: 64 | R66: BLAS PARERA 6054 | S66: 69000 | T66: 9000 | U66: 1 | V66: 08/01/2026
B67: EXE | E67: 1 | H67: 69000 | J67: 69000 | L67: =IF(K67<>"",22000+K67,22000) | Q67: 65 | R67: PANA BERUTI 6400 | S67: 65000 | T67: 5000 | U67: 1 | V67: 22/04/2026
B68: PANA VIEYTES 3800 | E68: 1 | H68: 69000 | I68: 69000 | L68: =IF(K68<>"",22000+K68,22000) | Q68: 66 | R68: DUSSO 6638 | S68: 65000 | T68: 5000 | U68: 1 | V68: 02/01/2026
B69: PANA GENESIO | E69: 1 | H69: 69000 | I69: 69000 | L69: =IF(K69<>"",22000+K69,22000) | Q69: 67 | R69: PANA HNO FIGUERIOA | S69: 65000 | T69: 5000 | U69: 1 | V69: 07/01/2026
B70: PANA VIEYTES 4500 | E70: 1 | H70: 65000 | I70: 65000 | L70: =IF(K70<>"",18000+K70,18000) | Q70: 68 | R70: SABORERARTE | S70: 64000 | T70: 11500 | U70: 3 | V70: 26/02/2026
B71: POLLERIA. BLAS PAREA | C71: 1 | H71: 17000 | I71: 17000 | L71: =IF(K71<>"",6500+K71,6500) | Q71: 69 | R71: PANA VIEYTES GISELA | S71: 63100 | T71: 11200 | U71: 4 | V71: 16/04/2026
A72: 46031 | B72: FABIAN | C72: 1 | H72: 20000 | I72: 20000 | L72: =IF(K72<>"",9500+K72,9500) | Q72: 70 | R72: ESTELA PJE PARAGUAY | S72: 56000 | T72: -4000 | U72: 1 | V72: 18/01/2026
B73: PANA VIEYTES | C73: 1 | F73: 1 | H73: 19700 | J73: 19700 | L73: =IF(K73<>"",6875+K73,6875) | Q73: 71 | R73: BONEO 4054 | S73: 55000 | T73: 17500 | U73: 1 | V73: 11/04/2026
B74: OTNIEL | F74: 4 | H74: 14400 | I74: 14400 | L74: =IF(K74<>"",5100+K74,5100) | Q74: 72 | R74: SEGUI 1680 | S74: 54000 | T74: 16500 | U74: 2 | V74: 25/03/2026
B75: ROTI VIEYTES | D75: 4 | H75: 78000 | J75: 78000 | L75: =IF(K75<>"",15000+K75,15000) | Q75: 73 | R75: ROTI DOMINGO SILVA | S75: 52000 | T75: -8000 | U75: 1 | V75: 06/01/2026
B76: LOBATO BARBARA | E76: 1 | H76: 75000 | I76: 75000 | L76: =IF(K76<>"",28000+K76,28000) | Q76: 74 | R76: P CEBALLOS 8134 | S76: 49000 | T76: -3500 | U76: 1 | V76: 17/03/2026
B77: ANA ABDALA | C77: 1 | H77: 22000 | I77: 22000 | L77: =IF(K77<>"",11500+K77,11500) | Q77: 75 | R77: NACHI CUEVA | S77: 45000 | T77: 7500 | U77: 1 | V77: 08/01/2026
B78: JUJUY 3451 | C78: 1 | H78: 22000 | I78: 22000 | L78: =IF(K78<>"",11500+K78,11500) | Q78: 76 | R78: GENERAL PAZ 7826 | S78: 44000 | T78: 14000 | U78: 2 | V78: 13/02/2026
B79: SABOREAR | C79: 1 | E79: 1 | H79: 87000 | J79: 87000 | L79: =IF(K79<>"",29500+K79,29500) | Q79: 77 | R79: LAVADERO | S79: 43500 | T79: -1500 | U79: 3 | V79: 19/03/2026
A80: 46032 | B80: PANA GORRITI | E80: 1 | H80: 72000 | I80: 72000 | L80: =IF(K80<>"",25000+K80,25000) | Q80: 78 | R80: LAVAISE 3786 | S80: 42000 | T80: 12000 | U80: 1 | V80: 08/04/2026
B81: BERUTI 5520 | G81: 2 | H81: 10000 | J81: 10000 | L81: =IF(K81<>"",8400+K81,8400) | Q81: 79 | R81: BONEO 5315 | S81: 41000 | T81: 11000 | U81: 1 | V81: 19/04/2026
B82: AZOPARDO 7219 | C82: 1 | H82: 22000 | J82: 22000 | L82: =IF(K82<>"",11500+K82,11500) | Q82: 80 | R82: FORMOSOA 6058 | S82: 37900 | T82: 20350 | U82: 1 | V82: 30/01/2026
B83: FILOMENA | C83: 2 | H83: 36000 | I83: 36000 | L83: =IF(K83<>"",15000+K83,15000) | Q83: 81 | R83: HERNANDARIAS 5211 | S83: 36000 | T83: 13500 | U83: 1 | V83: 22/01/2026
B84: SAMDRA | C84: 1 | H84: 14500 | I84: 14500 | L84: =IF(K84<>"",4000+K84,4000) | Q84: 82 | R84: ARISTOBULO 5879 | S84: 34500 | T84: 12000 | U84: 1 | V84: 14/03/2026
B85: PUBLICO 4746 | E85: 1 | H85: 75000 | J85: 75000 | L85: =IF(K85<>"",28000+K85,28000) | Q85: 83 | R85: GARMENDIA 9249 | S85: 34000 | T85: 11500 | U85: 1 | V85: 08/04/2026
B86: ALSUNA 7980 | C86: 1 | H86: 22000 | I86: 22000 | L86: =IF(K86<>"",11500+K86,11500) | Q86: 84 | R86: JM ZUVIRIA 2143 | S86: 34000 | T86: 11500 | U86: 1 | V86: 12/01/2026
B87: BRASERIA | E87: 1 | H87: 69000 | J87: 69000 | L87: =IF(K87<>"",22000+K87,22000) | Q87: 85 | R87: LAVAISE 1074 | S87: 33600 | T87: 16900 | U87: 1 | V87: 05/03/2026
B88: GRAL PAZ 7989 | C88: 1 | H88: 22000 | I88: 22000 | L88: =IF(K88<>"",11500+K88,11500) | Q88: 86 | R88: TOFFO | S88: 33000 | T88: 10500 | U88: 1 | V88: 22/04/2026
A89: 46033 | B89: BENTEVEOS DAMIAN | E89: 1 | H89: 78000 | J89: 78000 | L89: =IF(K89<>"",31000+K89,31000) | Q89: 87 | R89: PAVON 2124 | S89: 33000 | T89: 10500 | U89: 1 | V89: 03/04/2026
B90: ALBERTI 4538 | D90: 1 | H90: 33000 | J90: 33000 | L90: =IF(K90<>"",17250+K90,17250) | Q90: 88 | R90: ALBERTI 4538 | S90: 33000 | T90: 10500 | U90: 1 | V90: 25/03/2026
B91: PANA ALBERTI | E91: 1 | H91: 69000 | I91: 69000 | L91: =IF(K91<>"",22000+K91,22000) | Q91: 89 | R91: GORRITI 4331 | S91: 33000 | T91: 10500 | U91: 1 | V91: 08/01/2026
B92: LUCHO | C92: 4 | H92: 58000 | I92: 58000 | L92: =IF(K92<>"",16000+K92,16000) | Q92: 90 | R92: CHICLANA 7565 | S92: 33000 | T92: 10500 | U92: 1 | V92: 17/01/2026
B93: M CANDIOTI 6281 | C93: 1 | H93: 22000 | J93: 22000 | L93: =IF(K93<>"",11500+K93,11500) | Q93: 91 | R93: AGUAYO 3617 | S93: 33000 | T93: 10500 | U93: 1 | V93: 25/01/2026
B94: GARMENDIA 9249 | D94: 1 | H94: 34000 | J94: 34000 | L94: =IF(K94<>"",18250+K94,18250) | Q94: 92 | R94: SAN LORENZO 5081 | S94: 33000 | T94: 10500 | U94: 1 | V94: 28/01/2026
B95: SABORERARTE | D95: 1 | H95: 28000 | I95: 12000 | J95: 28000 | L95: =IF(K95<>"",12250+K95,12250) | Q95: 93 | R95: HERNANDARIAS 5356 | S95: 32000 | T95: 9500 | U95: 1 | V95: 07/04/2026
B96: FILOMENA | C96: 1 | H96: 18000 | I96: 18000 | L96: =IF(K96<>"",7500+K96,7500) | Q96: 94 | R96: VICTOR CAPE | S96: 31500 | T96: 9000 | U96: 1 | V96: 02/03/2026
A97: 46034 | B97: PANA GORRITI | E97: 1 | H97: 72000 | I97: 72000 | L97: =IF(K97<>"",25000+K97,25000) | Q97: 95 | R97: PIRU | S97: 31000 | T97: 8500 | U97: 1 | V97: 04/03/2026
B98: OTNIEL | D98: 1 | H98: 28500 | J98: 28500 | L98: =IF(K98<>"",12750+K98,12750) | Q98: 96 | R98: WILLIAN | S98: 29500 | T98: 7000 | U98: 1 | V98: 07/01/2026
B99: AZCUENAGA 5023 | C99: 5 | H99: 72500 | J99: 72500 | L99: =IF(K99<>"",20000+K99,20000) | Q99: 97 | R99: MAURO | S99: 29000 | T99: -1000 | U99: 1 | V99: 13/01/2026
B100: HERNANDARIAS 5150 | E100: 1 | H100: 73000 | J100: 73000 | L100: =IF(K100<>"",26000+K100,26000) | Q100: 98 | R100: MAURITO | S100: 26000 | T100: -4000 | U100: 1 | V100: 05/01/2026
...

Sheet Febrero
A1: VENTAS — FEBRERO 2026 | Q1: 🏆 RANKING FEBRERO
A2: ⚠ El nombre del cliente debe ser EXACTAMENTE igual siempre · La ganancia se calcula con el costo vigente a la fecha | Q2: # | R2: Cliente | S2: Facturado | T2: Ganancia | U2: Pedidos | V2: Últ. compra
Q3: 🥇 | R3: OTNIEL | S3: 586000 | T3: 141650 | U3: 9 | V3: 16/04/2026
A4: FECHA | B4: CLIENTE / DIRECCIÓN | C4: 10 | D4: 15 | E4: 45 | F4: YERBA | G4: AGUA | H4: VALOR ($) | I4: EFECTIVO ($) | J4: TRANSFER ($) | K4: ENVASE ($) | L4: GANANCIA ($) | N4: RESUMEN FEBRERO | Q4: 🥈 | R4: PANA GENESIO | S4: 502000 | T4: 67000 | U4: 8 | V4: 09/03/2026
A5: 46054 | B5: GENERAL PAZ 7989 | C5: 1 | H5: 22000 | I5: 22000 | L5: =IF(K5<>"",11500+K5,11500) | N5: TOTAL 10 | O5: =IFERROR(SUM(C5:C700),0) | Q5: 🥉 | R5: CAREN | S5: 423000 | T5: 63000 | U5: 6 | V5: 20/04/2026
B6: POLLERIA BLAS PARERA | C6: 1 | H6: 17000 | I6: 17000 | L6: =IF(K6<>"",6500+K6,6500) | N6: TOTAL 15 | O6: =IFERROR(SUM(D5:D700),0) | Q6: 4 | R6: FILOMENA | S6: 403000 | T6: 73000 | U6: 15 | V6: 20/04/2026
B7: SAVEDRA 1683 | C7: 1 | H7: 22000 | I7: 22000 | L7: =IF(K7<>"",11500+K7,11500) | N7: TOTAL 45 | O7: =IFERROR(SUM(E5:E700),0) | Q7: 5 | R7: SABOREAR | S7: 388500 | T7: 73500 | U7: 10 | V7: 22/04/2026
B8: OTNIEL | C8: 1 | D8: 1 | E8: 1 | G8: 1 | H8: 123500 | I8: 120000 | J8: 3500 | L8: =IF(K8<>"",49450+K8,49450) | N8: TOTAL YERBA | O8: =IFERROR(SUM(F5:F700),0) | Q8: 6 | R8: LUCHO | S8: 370000 | T8: 7450 | U8: 14 | V8: 20/04/2026
B9: PARRI GABOTO | C9: 1 | H9: 19500 | J9: 19500 | L9: =IF(K9<>"",9000+K9,9000) | N9: TOTAL AGUA | O9: =IFERROR(SUM(G5:G700),0) | Q9: 7 | R9: EXE | S9: 351000 | T9: 51000 | U9: 5 | V9: 19/04/2026
B10: SABORERARTE | C10: 1 | E10: 1 | H10: 88000 | J10: 88000 | L10: =IF(K10<>"",30500+K10,30500) | Q10: 8 | R10: GOLD BURGUER | S10: 328000 | T10: 88000 | U10: 2 | V10: 20/02/2026
A11: 46055 | B11: FABIO PARISI | F11: 20 | H11: 67200 | I11: 67200 | L11: =IF(K11<>"",20700+K11,20700) | N11: FACTURACIÓN | O11: =IFERROR(SUM(H5:H700),0) | Q11: 9 | R11: AZCUENAGA 5023 | S11: 305000 | T11: -10000 | U11: 5 | V11: 20/04/2026
B12: SERBNADO BAY0 7165 | C12: 1 | H12: 20500 | I12: 20500 | L12: =IF(K12<>"",10000+K12,10000) | N12: GANANCIA | O12: =IFERROR(SUM(L5:L700),0) | Q12: 10 | R12: BRASERIA | S12: 289000 | T12: 49000 | U12: 4 | V12: 18/04/2026
B13: MAXI HERMANO | G13: 1 | H13: 5000 | J13: 5000 | L13: =IF(K13<>"",4200+K13,4200) | N13: % GANANCIA | O13: =IFERROR(SUM(L5:L700)/SUM(H5:H700),0) | Q13: 11 | R13: ROTI AGUADO | S13: 264500 | T13: 39500 | U13: 4 | V13: 17/04/2026
B14: PALLARES 8200 | C14: 2 | H14: 42000 | J14: 42000 | L14: =IF(K14<>"",21000+K14,21000) | Q14: 12 | R14: ROTI VIEYTES | S14: 222000 | T14: -3000 | U14: 5 | V14: 17/04/2026
B15: FILOMENA | C15: 2 | H15: 36000 | J15: 36000 | L15: =IF(K15<>"",15000+K15,15000) | N15: EFECTIVO | O15: =IFERROR(SUM(I5:I700),0) | Q15: 13 | R15: PANA VIEYTES 4500 | S15: 200000 | T15: 20000 | U15: 3 | V15: 16/04/2026
B16: LUCHO | C16: 1 | H16: 14500 | I16: 14500 | L16: =IF(K16<>"",4000+K16,4000) | N16: TRANSFERENCIA | O16: =IFERROR(SUM(J5:J700),0) | Q16: 14 | R16: SANDRA | S16: 199000 | T16: 5200 | U16: 8 | V16: 16/04/2026
B17: BRAILE 7173 | C17: 1 | H17: 21000 | I17: 21000 | L17: =IF(K17<>"",10500+K17,10500) | Q17: 15 | R17: PANA ALBERTI | S17: 191500 | T17: 34000 | U17: 4 | V17: 22/04/2026
B18: AZCUENAGA 5023 | C18: 1 | H18: 14500 | J18: 14500 | L18: =IF(K18<>"",4000+K18,4000) | N18: Nº VENTAS | O18: =IFERROR(COUNTA(B5:B700),0) | Q18: 16 | R18: COGORNO 5520 | S18: 190500 | T18: -4500 | U18: 3 | V18: 25/03/2026
A19: 46056 | B19: VICTOR CAPE | C19: 1 | H19: 20500 | J19: 20500 | L19: =IF(K19<>"",10000+K19,10000) | N19: DÍAS DEL MES | O19: 28 | Q19: 17 | R19: NACHO | S19: 174500 | T19: 32000 | U19: 8 | V19: 02/04/2026
B20: PANA VIEYTES GISELA | C20: 1 | H20: 17500 | J20: 17500 | L20: =IF(K20<>"",7000+K20,7000) | Q20: 18 | R20: ROTI SAN LORENZO | S20: 163000 | T20: 35500 | U20: 2 | V20: 15/04/2026
B21: RUPERTO GODOY 1278 | E21: 1 | H21: 72500 | I21: 72500 | L21: =IF(K21<>"",25500+K21,25500) | N21: OBJETIVO ($) | Q21: 19 | R21: 20 DE JUNIO Y 9 DE JULIO | S21: 156000 | T21: 36000 | U21: 1 | V21: 17/02/2026
B22: LUCHO | C22: 1 | H22: 14500 | I22: 14500 | L22: =IF(K22<>"",4000+K22,4000) | N22: DIFERENCIA | O22: =IFERROR(SUM(L5:L700)-N21,0) | Q22: 20 | R22: 9 DE JULIO 1144 | S22: 154000 | T22: 34000 | U22: 1 | V22: 06/03/2026
B23: BEATRIZ | G23: 1 | H23: 5000 | I23: 5000 | L23: =IF(K23<>"",4200+K23,4200) | Q23: 21 | R23: PANA GORRITI 4600 | S23: 148000 | T23: 28000 | U23: 2 | V23: 08/04/2026
B24: EX COMBATIENTES 5220 | C24: 2 | H24: 42000 | J24: 42000 | L24: =IF(K24<>"",21000+K24,21000) | N24: KG BUTANO | O24: =IFERROR((SUM(C5:C700)*10)+(SUM(D5:D700)*15),0) | Q24: 22 | R24: PAULO | S24: 145000 | T24: -5000 | U24: 4 | V24: 13/04/2026
B25: MOLINA FLORES 1 | E25: 1 | H25: 75000 | I25: 75000 | L25: =IF(K25<>"",28000+K25,28000) | N25: KG PROPANO | O25: =IFERROR(SUM(E5:E700)*45,0) | Q25: 23 | R25: PANA VIEYTES 3800 | S25: 143000 | T25: 23000 | U25: 2 | V25: 08/04/2026
B26: PANA VIEYTES 3800 | E26: 1 | H26: 71000 | J26: 71000 | L26: =IF(K26<>"",24000+K26,24000) | N26: KG TOTAL | O26: =IFERROR(O24+O25,0) | Q26: 24 | R26: PANA BERUTI 6400 | S26: 132000 | T26: 12000 | U26: 2 | V26: 22/04/2026
B27: LA SALLE 3151 | E27: 1 | H27: 73500 | I27: 73500 | L27: =IF(K27<>"",26500+K27,26500) | Q27: 25 | R27: MARTINEZ 3221 | S27: 119000 | T27: 29000 | U27: 1 | V27: 25/03/2026
B28: GENERAL PAZ 6050 | C28: 1 | H28: 22000 | J28: 22000 | L28: =IF(K28<>"",11500+K28,11500) | N28: TICKET PROM. VENTA | O28: =IFERROR(SUM(H5:H700)/COUNTA(B5:B700),0) | Q28: 26 | R28: GENERAL PAZ 7826 | S28: 118000 | T28: 28000 | U28: 2 | V28: 13/02/2026
B29: ESMERALDA 2376 | E29: 1 | H29: 75000 | J29: 75000 | L29: =IF(K29<>"",28000+K29,28000) | N29: TICKET PROM. GANANCIA | O29: =IFERROR(SUM(L5:L700)/COUNTA(B5:B700),0) | Q29: 27 | R29: SABORERARTE | S29: 107500 | T29: 17500 | U29: 2 | V29: 26/02/2026
B30: FABIAN BLAS PARERA | C30: 1 | D30: 1 | H30: 50000 | I30: 50000 | L30: =IF(K30<>"",23750+K30,23750) | Q30: 28 | R30: GRINGO ILGATO | S30: 99000 | T30: 24000 | U30: 1 | V30: 08/02/2026
B31: PANA VIEYTES 4500 | E31: 1 | H31: 66000 | I31: 66000 | L31: =IF(K31<>"",19000+K31,19000) | Q31: 29 | R31: MISIONES 6381 PANA | S31: 93000 | T31: 18000 | U31: 1 | V31: 12/02/2026
B32: SANDRA | C32: 2 | H32: 29000 | I32: 29000 | L32: =IF(K32<>"",8000+K32,8000) | Q32: 30 | R32: AZCUEJAGA 5023 | S32: 90000 | T32: 0 | U32: 1 | V32: 27/02/2026
B33: AYACUCHO 5370 | G33: 2 | H33: 10000 | J33: 10000 | L33: =IF(K33<>"",8400+K33,8400) | Q33: 31 | R33: PANA BONEO | S33: 82500 | T33: 7500 | U33: 1 | V33: 16/02/2026
B34: FILOMENA | C34: 1 | H34: 18000 | J34: 18000 | L34: =IF(K34<>"",7500+K34,7500) | Q34: 32 | R34: DOMINGO SIVLA 4217 | S34: 80500 | T34: -2000 | U34: 1 | V34: 09/03/2026
A35: 46057 | B35: COGORNO 5520 | C35: 5 | H35: 72500 | I35: 72500 | L35: =IF(K35<>"",20000+K35,20000) | Q35: 33 | R35: SAN JOSE 8494 | S35: 79000 | T35: 19000 | U35: 1 | V35: 08/02/2026
B36: OTNIEL | G36: 4 | H36: 20000 | I36: 20000 | L36: =IF(K36<>"",16800+K36,16800) | Q36: 34 | R36: ORREGO Y MENDIETA | S36: 79000 | T36: 19000 | U36: 1 | V36: 27/02/2026
B37: LAVADERO | D37: 1 | H37: 22000 | J37: 22000 | L37: =IF(K37<>"",6250+K37,6250) | Q37: 35 | R37: RIO NEGRO 6570 | S37: 79000 | T37: 19000 | U37: 1 | V37: 28/02/2026
B38: ALBERTI 5122 | E38: 1 | H38: 75000 | J38: 75000 | L38: =IF(K38<>"",28000+K38,28000) | Q38: 36 | R38: IL GATO PEPE | S38: 78000 | T38: 18000 | U38: 1 | V38: 17/02/2026
B39: NACHO | D39: 1 | H39: 27000 | J39: 27000 | L39: =IF(K39<>"",11250+K39,11250) | Q39: 37 | R39: RIO NEGRO 6558 | S39: 77000 | T39: 17000 | U39: 1 | V39: 13/02/2026
B40: ALBERTI 5303 | C40: 1 | H40: 21000 | I40: 21000 | L40: =IF(K40<>"",10500+K40,10500) | Q40: 38 | R40: ALSINA 9251 | S40: 77000 | T40: 17000 | U40: 1 | V40: 23/03/2026
B41: GENERAL PAZ 7826 | C41: 1 | H41: 22000 | I41: 22000 | L41: =IF(K41<>"",11500+K41,11500) | Q41: 39 | R41: BAIGORRIA 9350 | S41: 77000 | T41: 17000 | U41: 1 | V41: 24/02/2026
B42: PANA GENESIO | E42: 1 | H42: 69000 | I42: 69000 | L42: =IF(K42<>"",22000+K42,22000) | Q42: 40 | R42: MARCIAL CANDIOTI 8968 | S42: 77000 | T42: 17000 | U42: 1 | V42: 06/02/2026
B43: PANA ALBERTI | E43: 1 | H43: 71000 | I43: 71000 | L43: =IF(K43<>"",24000+K43,24000) | Q43: 41 | R43: HOTEL ROYAL | S43: 77000 | T43: 17000 | U43: 1 | V43: 13/02/2026
A44: 46058 | B44: DAMIANOVICH 6212 | E44: 1 | H44: 75000 | J44: 75000 | L44: =IF(K44<>"",28000+K44,28000) | Q44: 42 | R44: LALO | S44: 76000 | T44: 16000 | U44: 1 | V44: 27/02/2026
B45: OTNIEL | E45: 1 | H45: 71000 | J45: 71000 | L45: =IF(K45<>"",24000+K45,24000) | Q45: 43 | R45: ACASIAS 9788 | S45: 76000 | T45: 16000 | U45: 1 | V45: 17/02/2026
B46: ROTI AGUADO | D46: 2 | H46: 49000 | J46: 49000 | L46: =IF(K46<>"",17500+K46,17500) | Q46: 44 | R46: BERUTI 6400 CASA 88 | S46: 76000 | T46: 16000 | U46: 1 | V46: 17/02/2026
B47: PEDRO CEBALLOS 8134 | C47: 2 | H47: 29000 | I47: 29000 | L47: =IF(K47<>"",8000+K47,8000) | Q47: 45 | R47: RUPERTO GODOY 4484 | S47: 76000 | T47: 16000 | U47: 1 | V47: 21/02/2026
B48: ROTI VIEYTES | D48: 2 | H48: 44000 | J48: 44000 | L48: =IF(K48<>"",12500+K48,12500) | Q48: 46 | R48: NOGALES2651 | S48: 76000 | T48: 16000 | U48: 1 | V48: 21/02/2026
B49: PANA VIEYTES GISELA | C49: 1 | F49: 1 | H49: 21200 | J49: 21200 | L49: =IF(K49<>"",8375+K49,8375) | Q49: 47 | R49: RIVADAVIA 8280 | S49: 76000 | T49: 16000 | U49: 1 | V49: 21/02/2026
B50: FILOMENA | C50: 2 | H50: 36000 | J50: 36000 | L50: =IF(K50<>"",15000+K50,15000) | Q50: 48 | R50: EUROPA 9396 | S50: 76000 | T50: 16000 | U50: 1 | V50: 23/02/2026
B51: SABOREAR | D51: 1 | H51: 28000 | J51: 28000 | L51: =IF(K51<>"",12250+K51,12250) | Q51: 49 | R51: AYACUCHO 4057 | S51: 76000 | T51: 16000 | U51: 1 | V51: 25/02/2026
A52: 46059 | B52: MARCIAL CANDIOTI 8968 | E52: 1 | H52: 77000 | J52: 77000 | L52: =IF(K52<>"",30000+K52,30000) | Q52: 50 | R52: MOLINA FLORES 1 | S52: 75000 | T52: 15000 | U52: 1 | V52: 22/03/2026
B53: DAMIANOVICH 3190 | D53: 1 | H53: 31500 | I53: 31500 | L53: =IF(K53<>"",15750+K53,15750) | Q53: 51 | R53: ESMERALDA 2376 | S53: 75000 | T53: 15000 | U53: 1 | V53: 03/02/2026
B54: LUCIANO LEIVA Y ABLERTI | C54: 1 | H54: 20000 | I54: 20000 | L54: =IF(K54<>"",9500+K54,9500) | Q54: 52 | R54: ALBERTI 5122 | S54: 75000 | T54: 15000 | U54: 1 | V54: 04/02/2026
B55: ESTANISLAO ZEBALLOS 4560 | D55: 1 | H55: 33000 | I55: 33000 | L55: =IF(K55<>"",17250+K55,17250) | Q55: 53 | R55: DAMIANOVICH 6212 | S55: 75000 | T55: 15000 | U55: 1 | V55: 05/02/2026
B56: EUROPA 7251 | C56: 1 | H56: 22000 | J56: 22000 | L56: =IF(K56<>"",11500+K56,11500) | Q56: 54 | R56: SIR LAKI F5 | S56: 75000 | T56: 15000 | U56: 1 | V56: 06/02/2026
B57: AZCUENAGA 5023 | C57: 6 | H57: 87000 | J57: 87000 | L57: =IF(K57<>"",24000+K57,24000) | Q57: 55 | R57: ARISTOBULO 4471 | S57: 75000 | T57: 15000 | U57: 1 | V57: 18/02/2026
B58: SIR LAKI F5 | E58: 1 | H58: 75000 | I58: 75000 | L58: =IF(K58<>"",28000+K58,28000) | Q58: 56 | R58: PUBLICO 2550 | S58: 74000 | T58: 14000 | U58: 1 | V58: 24/03/2026
B59: LUCHO | G59: 1 | H59: 5000 | J59: 5000 | L59: =IF(K59<>"",4200+K59,4200) | Q59: 57 | R59: CASTAÑADUY 6687 | S59: 74000 | T59: 14000 | U59: 1 | V59: 26/02/2026
B60: LAVAISE 1074 | G60: 2 | H60: 11600 | J60: 11600 | L60: =IF(K60<>"",10000+K60,10000) | Q60: 58 | R60: LA SALLE 3151 | S60: 73500 | T60: 13500 | U60: 1 | V60: 03/02/2026
B61: FILOMENA | C61: 1 | H61: 18000 | J61: 18000 | L61: =IF(K61<>"",7500+K61,7500) | Q61: 59 | R61: LAVADERO | S61: 73000 | T61: -2000 | U61: 3 | V61: 19/03/2026
B62: BRASERIA | E62: 1 | H62: 72000 | J62: 72000 | L62: =IF(K62<>"",25000+K62,25000) | Q62: 60 | R62: CARCARAES 5820 | S62: 73000 | T62: 13000 | U62: 1 | V62: 27/02/2026
B63: CAREN | E63: 1 | H63: 69000 | J63: 69000 | L63: =IF(K63<>"",22000+K63,22000) | Q63: 61 | R63: CHICLANA 7325 | S63: 72500 | T63: -2500 | U63: 2 | V63: 22/04/2026
B64: ARGENTA PIZZAS | C64: 1 | H64: 21000 | J64: 21000 | L64: =IF(K64<>"",10500+K64,10500) | Q64: 62 | R64: RUPERTO GODOY 1278 | S64: 72500 | T64: 12500 | U64: 1 | V64: 03/02/2026
B65: PADRE GENESIO 4501 | C65: 1 | H65: 21000 | J65: 21000 | L65: =IF(K65<>"",10500+K65,10500) | Q65: 63 | R65: ALBERTI 5477 | S65: 72000 | T65: 12000 | U65: 1 | V65: 17/02/2026
B66: PORKIS | C66: 1 | H66: 18500 | J66: 18500 | L66: =IF(K66<>"",8000+K66,8000) | Q66: 64 | R66: MONTIEL 9165 | S66: 72000 | T66: 12000 | U66: 1 | V66: 18/02/2026
A67: 46060 | B67: AZCUENAGA 5023 | C67: 2 | H67: 29000 | J67: 29000 | L67: =IF(K67<>"",8000+K67,8000) | Q67: 65 | R67: PAVON 2612 | S67: 68000 | T67: 8000 | U67: 1 | V67: 21/02/2026
B68: SAVEDRA 2799 | C68: 1 | H68: 23000 | I68: 23000 | L68: =IF(K68<>"",12500+K68,12500) | Q68: 66 | R68: FABIO PARISI | S68: 67200 | T68: 21200 | U68: 1 | V68: 02/02/2026
B69: SABOREAR | C69: 2 | H69: 38000 | J69: 38000 | L69: =IF(K69<>"",17000+K69,17000) | Q69: 67 | R69: AYACUCHO 5370 | S69: 63500 | T69: 35900 | U69: 4 | V69: 16/04/2026
B70: 9 DE JULIO 1144 | E70: 2 | H70: 154000 | J70: 154000 | L70: =IF(K70<>"",60000+K70,60000) | Q70: 68 | R70: PEDRO CEBALLOS 8134 | S70: 58000 | T70: -2000 | U70: 2 | V70: 10/04/2026
B71: CASTELLI 4320 | C71: 1 | H71: 22000 | I71: 22000 | L71: =IF(K71<>"",11500+K71,11500) | Q71: 69 | R71: BEATRIZ | S71: 58000 | T71: 17100 | U71: 5 | V71: 16/04/2026
B72: ROTI AGUADO | D72: 1 | E72: 1 | H72: 96500 | J72: 96500 | L72: =IF(K72<>"",33750+K72,33750) | Q72: 70 | R72: PUBLICO 5727 | S72: 55000 | T72: 17500 | U72: 1 | V72: 20/04/2026
B73: FLORES 2 TORRE 8 | C73: 1 | H73: 22000 | I73: 22000 | L73: =IF(K73<>"",11500+K73,11500) | Q73: 71 | R73: SERBANDO BAYO 6840 | S73: 55000 | T73: 17500 | U73: 2 | V73: 26/02/2026
B74: EXE | E74: 1 | H74: 69000 | J74: 69000 | L74: =IF(K74<>"",22000+K74,22000) | Q74: 72 | R74: DOMINGO SILVA 4217 | S74: 51500 | T74: -1000 | U74: 1 | V74: 19/04/2026
B75: NACHO | C75: 1 | H75: 18000 | J75: 18000 | L75: =IF(K75<>"",7500+K75,7500) | Q75: 73 | R75: LAVAISE 3786 | S75: 51500 | T75: 14000 | U75: 1 | V75: 08/04/2026
B76: TACUARI | C76: 1 | H76: 20000 | J76: 20000 | L76: =IF(K76<>"",9500+K76,9500) | Q76: 74 | R76: DUSSOP 7678 | S76: 51500 | T76: -1000 | U76: 1 | V76: 25/02/2026
B77: FILOMENA | C77: 1 | H77: 18000 | J77: 18000 | L77: =IF(K77<>"",7500+K77,7500) | Q77: 75 | R77: FABIAN BLAS PARERA | S77: 50000 | T77: 12500 | U77: 1 | V77: 03/02/2026
B78: PANA GENESIO | E78: 1 | H78: 69000 | J78: 69000 | L78: =IF(K78<>"",22000+K78,22000) | Q78: 76 | R78: MARTIN ZAPATA 2101 | S78: 45000 | T78: 0 | U78: 1 | V78: 14/02/2026
B79: LUCHO | C79: 2 | H79: 29000 | I79: 29000 | L79: =IF(K79<>"",8000+K79,8000) | Q79: 77 | R79: ESTELA PALZA | S79: 45000 | T79: 0 | U79: 1 | V79: 21/02/2026
B80: ROTI VIEYTES | D80: 2 | H80: 44000 | J80: 44000 | L80: =IF(K80<>"",12500+K80,12500) | Q80: 78 | R80: D SILVA 4217 | S80: 43500 | T80: -1500 | U80: 1 | V80: 11/04/2026
A81: 46061 | B81: GENEIRO 8264 | D81: 1 | H81: 33000 | I81: 33000 | L81: =IF(K81<>"",17250+K81,17250) | Q81: 79 | R81: PALLARES 8200 | S81: 42000 | T81: 12000 | U81: 1 | V81: 02/02/2026
B82: SAN JOSE 8494 | E82: 1 | H82: 79000 | J82: 79000 | L82: =IF(K82<>"",32000+K82,32000) | Q82: 80 | R82: EX COMBATIENTES 5220 | S82: 42000 | T82: 12000 | U82: 1 | V82: 03/02/2026
B83: GRINGO ILGATO | C83: 1 | E83: 1 | H83: 99000 | I83: 99000 | L83: =IF(K83<>"",41500+K83,41500) | Q83: 81 | R83: ESTELA PARAGUAY | S83: 42000 | T83: -3000 | U83: 1 | V83: 15/02/2026
B84: OTNIEL | C84: 1 | G84: 1 | H84: 24000 | J84: 24000 | L84: =IF(K84<>"",12700+K84,12700) | Q84: 82 | R84: FORMOSA 6058 | S84: 41000 | T84: 23450 | U84: 1 | V84: 10/04/2026
B85: LUCHO | D85: 1 | H85: 22500 | I85: 22500 | L85: =IF(K85<>"",6750+K85,6750) | Q85: 83 | R85: GISE PANA | S85: 39800 | T85: 7500 | U85: 2 | V85: 26/02/2026
B86: ROQUE SAENZ PENA 7744 | C86: 1 | H86: 22000 | J86: 22000 | L86: =IF(K86<>"",11500+K86,11500) | Q86: 84 | R86: PANA VIEYTES GISELA | S86: 38700 | T86: 6400 | U86: 2 | V86: 16/04/2026
B87: SALTA 2709 | C87: 1 | H87: 22000 | I87: 22000 | L87: =IF(K87<>"",11500+K87,11500) | Q87: 85 | R87: PARRI GABOTO | S87: 38000 | T87: 8000 | U87: 2 | V87: 22/03/2026
B88: CLUB NACIONAL | C88: 1 | H88: 22000 | I88: 22000 | L88: =IF(K88<>"",11500+K88,11500) | Q88: 86 | R88: ARISTOBULO 5879 | S88: 34500 | T88: 12000 | U88: 1 | V88: 14/03/2026
B89: PAULO | C89: 2 | H89: 29000 | I89: 29000 | L89: =IF(K89<>"",8000+K89,8000) | Q89: 87 | R89: POLLERIA BLAS PARERA | S89: 34000 | T89: 4000 | U89: 2 | V89: 15/02/2026
A90: 46062 | B90: GOLD BURGUER | E90: 2 | H90: 164000 | I90: 164000 | L90: =IF(K90<>"",70000+K90,70000) | Q90: 88 | R90: ALBERTI 5298 | S90: 34000 | T90: 4000 | U90: 1 | V90: 24/02/2026
B91: ABUELA LUCAS | C91: 1 | H91: 22000 | I91: 22000 | L91: =IF(K91<>"",11500+K91,11500) | Q91: 89 | R91: BARRETO 9261 | S91: 33500 | T91: 11000 | U91: 1 | V91: 11/02/2026
B92: FILOMENA | C92: 1 | H92: 18000 | J92: 18000 | L92: =IF(K92<>"",7500+K92,7500) | Q92: 90 | R92: PUBLICO 5712 | S92: 33500 | T92: 11000 | U92: 1 | V92: 20/04/2026
B93: BEATRIZ | G93: 1 | H93: 5000 | I93: 5000 | L93: =IF(K93<>"",4200+K93,4200) | Q93: 91 | R93: ESTANISLAO ZEBALLOS 4560 | S93: 33000 | T93: 10500 | U93: 1 | V93: 06/02/2026
B94: MARTINEZ 3221 | C94: 2 | E94: 1 | H94: 119000 | J94: 119000 | L94: =IF(K94<>"",51000+K94,51000) | Q94: 92 | R94: GENEIRO 8264 | S94: 33000 | T94: 10500 | U94: 1 | V94: 08/02/2026
B95: SERBANDO BAYO 7250 | C95: 1 | H95: 21000 | I95: 21000 | L95: =IF(K95<>"",10500+K95,10500) | Q95: 93 | R95: 1 DE MAYO 1605 | S95: 33000 | T95: 10500 | U95: 1 | V95: 20/02/2026
B96: LAVAISE 3786 | C96: 1 | D96: 1 | H96: 51500 | I96: 51500 | L96: =IF(K96<>"",25250+K96,25250) | Q96: 94 | R96: GABOTO 7102 | S96: 33000 | T96: 10500 | U96: 1 | V96: 22/02/2026
B97: ALBERTI 4930 | G97: 2 | H97: 10000 | I97: 10000 | L97: =IF(K97<>"",8400+K97,8400) | Q97: 95 | R97: AGUADP 6970 | S97: 32000 | T97: 9500 | U97: 1 | V97: 10/03/2026
A98: 46063 | B98: ALE RUIZ | G98: 1 | H98: 5000 | I98: 5000 | L98: =IF(K98<>"",4200+K98,4200) | Q98: 96 | R98: DAMIANOVICH 3190 | S98: 31500 | T98: 9000 | U98: 1 | V98: 06/02/2026
B99: PANA GORRITI 4600 | E99: 1 | H99: 74000 | I99: 74000 | L99: =IF(K99<>"",27000+K99,27000) | Q99: 97 | R99: ALBERTI 5177 | S99: 31000 | T99: 8500 | U99: 1 | V99: 19/01/2026
B100: ARISTOBULO 5879 | D100: 1 | H100: 34500 | I100: 34500 | L100: =IF(K100<>"",18750+K100,18750) | Q100: 98 | R100: LARREA 3339 | S100: 30000 | T100: 0 | U100: 1 | V100: 23/03/2026
...

Sheet Marzo
A1: VENTAS — MARZO 2026 | Q1: 🏆 RANKING MARZO
A2: ⚠ El nombre del cliente debe ser EXACTAMENTE igual siempre · La ganancia se calcula con el costo vigente a la fecha | Q2: # | R2: Cliente | S2: Facturado | T2: Ganancia | U2: Pedidos | V2: Últ. compra
Q3: 🥇 | R3: OTNIEL | S3: 556000 | T3: 157500 | U3: 10 | V3: 16/04/2026
A4: FECHA | B4: CLIENTE / DIRECCIÓN | C4: 10 | D4: 15 | E4: 45 | F4: YERBA | G4: AGUA | H4: VALOR ($) | I4: EFECTIVO ($) | J4: TRANSFER ($) | K4: ENVASE ($) | L4: GANANCIA ($) | N4: RESUMEN MARZO | Q4: 🥈 | R4: AZCUENAGA 5023 | S4: 413000 | T4: 15500 | U4: 5 | V4: 20/04/2026
A5: 46082 | B5: JOSE CIBILS | E5: 1 | H5: 76000 | J5: 76000 | L5: =IF(K5<>"",27000+K5,27000) | N5: TOTAL 10 | O5: =IFERROR(SUM(C5:C700),0) | Q5: 🥉 | R5: FILOMENA | S5: 357000 | T5: 87000 | U5: 11 | V5: 20/04/2026
B6: ALSINA 6550 | D6: 1 | H6: 33000 | I6: 33000 | L6: =IF(K6<>"",12750+K6,12750) | N6: TOTAL 15 | O6: =IFERROR(SUM(D5:D700),0) | Q6: 4 | R6: EXE | S6: 342000 | T6: 72000 | U6: 4 | V6: 19/04/2026
B7: LAS HERAS Y GORRITI | E7: 1 | H7: 75000 | J7: 75000 | L7: =IF(K7<>"",26000+K7,26000) | N7: TOTAL 45 | O7: =IFERROR(SUM(E5:E700),0) | Q7: 5 | R7: CAREN | S7: 298000 | T7: 58000 | U7: 4 | V7: 20/04/2026
B8: RIVADAVIA 6330 | D8: 1 | H8: 33000 | J8: 33000 | L8: =IF(K8<>"",12750+K8,12750) | N8: TOTAL YERBA | O8: =IFERROR(SUM(F5:F700),0) | Q8: 6 | R8: SABOREAR | S8: 274000 | T8: 64000 | U8: 7 | V8: 22/04/2026
B9: BERUTI 4075 | E9: 2 | H9: 152000 | J9: 152000 | L9: =IF(K9<>"",54000+K9,54000) | N9: TOTAL AGUA | O9: =IFERROR(SUM(G5:G700),0) | Q9: 7 | R9: LUCHO | S9: 252500 | T9: 19150 | U9: 11 | V9: 20/04/2026
B10: 9 DE JULIO 2109 | C10: 1 | H10: 23000 | J10: 23000 | L10: =IF(K10<>"",9500+K10,9500) | Q10: 8 | R10: BRASERIA | S10: 229000 | T10: 49000 | U10: 3 | V10: 18/04/2026
B11: NACHO | C11: 1 | H11: 19000 | J11: 19000 | L11: =IF(K11<>"",5500+K11,5500) | N11: FACTURACIÓN | O11: =IFERROR(SUM(H5:H700),0) | Q11: 9 | R11: PANA ALBERTI | S11: 221000 | T11: 41000 | U11: 3 | V11: 22/04/2026
A12: 46083 | B12: IRMA INGENIEROS 5501 | C12: 1 | H12: 23000 | I12: 23000 | L12: =IF(K12<>"",9500+K12,9500) | N12: GANANCIA | O12: =IFERROR(SUM(L5:L700),0) | Q12: 10 | R12: MARIELA | S12: 219000 | T12: 53000 | U12: 1 | V12: 25/03/2026
B13: GENEIRO 8249 | C13: 1 | H13: 21000 | J13: 21000 | L13: =IF(K13<>"",7500+K13,7500) | N13: % GANANCIA | O13: =IFERROR(SUM(L5:L700)/SUM(H5:H700),0) | Q13: 11 | R13: PANA VIEYTES 4500 | S13: 214000 | T13: 34000 | U13: 3 | V13: 16/04/2026
B14: VIANDAS JORGE | C14: 1 | H14: 19000 | I14: 19000 | L14: =IF(K14<>"",5500+K14,5500) | Q14: 12 | R14: SANDRA | S14: 207000 | T14: 25300 | U14: 10 | V14: 16/04/2026
B15: 25 DE MAYO 8347 | C15: 1 | H15: 21000 | I15: 21000 | L15: =IF(K15<>"",7500+K15,7500) | N15: EFECTIVO | O15: =IFERROR(SUM(I5:I700),0) | Q15: 13 | R15: NACHO | S15: 179500 | T15: 22000 | U15: 7 | V15: 02/04/2026
B16: RICARDO ALDAO 3082 | C16: 1 | H16: 22000 | I16: 22000 | L16: =IF(K16<>"",8500+K16,8500) | N16: TRANSFERENCIA | O16: =IFERROR(SUM(J5:J700),0) | Q16: 14 | R16: DUSO 7678 | S16: 178500 | T16: 21000 | U16: 1 | V16: 22/03/2026
B17: B IRIGOYEN 6634 | C17: 1 | H17: 22000 | I17: 22000 | L17: =IF(K17<>"",8500+K17,8500) | Q17: 15 | R17: PANA GENESIO | S17: 176000 | T17: 26000 | U17: 4 | V17: 09/03/2026
B18: CAMELI 4860 | C18: 2 | H18: 42000 | J18: 42000 | L18: =IF(K18<>"",15000+K18,15000) | N18: Nº VENTAS | O18: =IFERROR(COUNTA(B5:B700),0) | Q18: 16 | R18: COGORNO 5520 | S18: 170000 | T18: 20000 | U18: 2 | V18: 25/03/2026
B19: VICTOR CAPE | D19: 1 | H19: 32000 | J19: 32000 | L19: =IF(K19<>"",11750+K19,11750) | N19: DÍAS DEL MES | O19: 31 | Q19: 17 | R19: J D SOLIS 10529 | S19: 166000 | T19: 46000 | U19: 1 | V19: 14/03/2026
B20: FILOMENA | C20: 2 | H20: 38000 | I20: 38000 | L20: =IF(K20<>"",11000+K20,11000) | Q20: 18 | R20: 9 DE JULIO 1144 | S20: 158000 | T20: 38000 | U20: 1 | V20: 06/03/2026
A21: 46084 | B21: OTNIEL | C21: 1 | D21: 1 | E21: 1 | G21: 1 | H21: 127500 | J21: 127500 | L21: =IF(K21<>"",43900+K21,43900) | N21: OBJETIVO ($) | Q21: 19 | R21: GRAL PAZ 7826 | S21: 156000 | T21: 36000 | U21: 1 | V21: 14/03/2026
B22: ALBERTI 5251 | C22: 1 | H22: 21000 | I22: 21000 | L22: =IF(K22<>"",7500+K22,7500) | N22: DIFERENCIA | O22: =IFERROR(SUM(L5:L700)-N21,0) | Q22: 20 | R22: PANA GORRITI 4600 | S22: 153000 | T22: 33000 | U22: 2 | V22: 08/04/2026
B23: LUCHO | C23: 1 | H23: 15000 | I23: 15000 | L23: =IF(K23<>"",1500+K23,1500) | Q23: 21 | R23: BERUTI 4075 | S23: 152000 | T23: 32000 | U23: 1 | V23: 01/03/2026
B24: PIEDRABUENA 4506 | E24: 1 | H24: 77000 | I24: 77000 | L24: =IF(K24<>"",28000+K24,28000) | N24: KG BUTANO | O24: =IFERROR((SUM(C5:C700)*10)+(SUM(D5:D700)*15),0) | Q24: 22 | R24: PANA VIEYTE 3800 | S24: 148000 | T24: 28000 | U24: 1 | V24: 05/03/2026
B25: EX COMBATIENTES 6532 | D25: 1 | H25: 32000 | I25: 32000 | L25: =IF(K25<>"",11750+K25,11750) | N25: KG PROPANO | O25: =IFERROR(SUM(E5:E700)*45,0) | Q25: 23 | R25: D SILVA 4217 | S25: 145500 | T25: 10500 | U25: 3 | V25: 11/04/2026
B26: AZOPARD0 10560 | C26: 1 | H26: 21000 | I26: 21000 | L26: =IF(K26<>"",7500+K26,7500) | N26: KG TOTAL | O26: =IFERROR(O24+O25,0) | Q26: 24 | R26: ROTI AGUADO | S26: 135000 | T26: 30000 | U26: 2 | V26: 17/04/2026
B27: PANA GENESIO | E27: 1 | H27: 69000 | J27: 69000 | L27: =IF(K27<>"",20000+K27,20000) | Q27: 25 | R27: MARCE DUSSO | S27: 132000 | T27: 12000 | U27: 1 | V27: 10/03/2026
B28: POLLERIA BLASPA | C28: 1 | H28: 18000 | I28: 18000 | L28: =IF(K28<>"",4500+K28,4500) | N28: TICKET PROM. VENTA | O28: =IFERROR(SUM(H5:H700)/COUNTA(B5:B700),0) | Q28: 26 | R28: MARTINEZ 3221 | S28: 108000 | T28: 33000 | U28: 1 | V28: 25/03/2026
B29: SANDRA | C29: 1 | H29: 15500 | I29: 15500 | L29: =IF(K29<>"",2000+K29,2000) | N29: TICKET PROM. GANANCIA | O29: =IFERROR(SUM(L5:L700)/COUNTA(B5:B700),0) | Q29: 27 | R29: GABOTO 7320 | S29: 105000 | T29: 30000 | U29: 1 | V29: 26/03/2026
B30: F5 GABOTO | C30: 1 | H30: 20000 | I30: 20000 | L30: =IF(K30<>"",6500+K30,6500) | Q30: 28 | R30: PUBLICO 2383 | S30: 104000 | T30: 29000 | U30: 1 | V30: 11/03/2026
B31: SARSOTI 6567 | D31: 1 | H31: 30000 | J31: 30000 | L31: =IF(K31<>"",9750+K31,9750) | Q31: 29 | R31: ALSINA 9251 | S31: 103000 | T31: 28000 | U31: 1 | V31: 23/03/2026
B32: ALBERTI 4930 | E32: 1 | G32: 1 | H32: 86000 | J32: 86000 | L32: =IF(K32<>"",36150+K32,36150) | Q32: 30 | R32: DOMINGO SILVA 4217 | S32: 102000 | T32: 12000 | U32: 2 | V32: 19/04/2026
B33: ROQUE S PENA 7668 | E33: 1 | H33: 73000 | J33: 73000 | L33: =IF(K33<>"",24000+K33,24000) | Q33: 31 | R33: P CEBALLOS 8134 | S33: 102000 | T33: 4500 | U33: 2 | V33: 17/03/2026
B34: CHICLANA 72325 | C34: 2 | H34: 29000 | I34: 29000 | L34: =IF(K34<>"",2000+K34,2000) | Q34: 32 | R34: ROTI SAN LORENZO | S34: 98000 | T34: 23000 | U34: 1 | V34: 15/04/2026
B35: ALMONACID 3637 | C35: 1 | H35: 21000 | I35: 21000 | L35: =IF(K35<>"",7500+K35,7500) | Q35: 33 | R35: FRENCH BIS 2000 GONZA TORRI | S35: 97000 | T35: 37000 | U35: 1 | V35: 07/03/2026
B36: PANA ALBERTI | E36: 1 | H36: 72000 | I36: 72000 | L36: =IF(K36<>"",23000+K36,23000) | Q36: 34 | R36: ROTI VIEYTES | S36: 95000 | T36: 5000 | U36: 2 | V36: 17/04/2026
B37: ALBERTI 5200 | C37: 1 | H37: 20000 | J37: 20000 | L37: =IF(K37<>"",6500+K37,6500) | Q37: 35 | R37: BERUTI 3850 | S37: 91500 | T37: 16500 | U37: 1 | V37: 26/03/2026
A38: 46085 | B38: PANA GORRITI 4600 | E38: 1 | H38: 74000 | I38: 74000 | L38: =IF(K38<>"",25000+K38,25000) | Q38: 36 | R38: ALBERTI 4930 | S38: 91000 | T38: 29300 | U38: 2 | V38: 24/03/2026
B39: SAVEDRA 10125 | E39: 1 | H39: 79000 | J39: 79000 | L39: =IF(K39<>"",30000+K39,30000) | Q39: 37 | R39: NOGALES 2412 | S39: 83000 | T39: 23000 | U39: 1 | V39: 23/03/2026
B40: ROTI ZEBALLOS | C40: 2 | H40: 38000 | I40: 38000 | L40: =IF(K40<>"",11000+K40,11000) | Q40: 38 | R40: JOSE MONTEVERA | S40: 83000 | T40: 23000 | U40: 1 | V40: 18/03/2026
B41: ESPORA 4874 | D41: 1 | H41: 32000 | J41: 32000 | L41: =IF(K41<>"",11750+K41,11750) | Q41: 39 | R41: LA SALLE 4625 | S41: 83000 | T41: 23000 | U41: 1 | V41: 16/03/2026
B42: D SILVA 4217 | C42: 3 | H42: 43500 | J42: 43500 | L42: =IF(K42<>"",3000+K42,3000) | Q42: 40 | R42: INGENIERO 8364 | S42: 83000 | T42: 23000 | U42: 1 | V42: 17/03/2026
B43: P CEBALLOS 8134 | C43: 3 | D43: 1 | H43: 68000 | J43: 68000 | L43: =IF(K43<>"",7250+K43,7250) | Q43: 41 | R43: TATU | S43: 83000 | T43: 23000 | U43: 1 | V43: 21/03/2026
B44: GENEIRO 8200 CASA 2 | C44: 1 | H44: 21000 | I44: 21000 | L44: =IF(K44<>"",7500+K44,7500) | Q44: 42 | R44: ALVEAR 5135 | S44: 83000 | T44: 23000 | U44: 1 | V44: 23/03/2026
B45: LUCHO | C45: 3 | H45: 45000 | I45: 45000 | L45: =IF(K45<>"",4500+K45,4500) | Q45: 43 | R45: RICARDO ALDAO 369 | S45: 83000 | T45: 23000 | U45: 1 | V45: 24/03/2026
B46: LEMAN 7856 | C46: 1 | H46: 20000 | I46: 20000 | L46: =IF(K46<>"",6500+K46,6500) | Q46: 44 | R46: P GENESIO 2128 | S46: 82000 | T46: 22000 | U46: 1 | V46: 15/03/2026
B47: CARRI FILOMENA | C47: 1 | H47: 19000 | J47: 19000 | L47: =IF(K47<>"",5500+K47,5500) | Q47: 45 | R47: PAULO | S47: 80500 | T47: 5500 | U47: 2 | V47: 13/04/2026
B48: PANA GENESIO | C48: 1 | H48: 19000 | J48: 19000 | L48: =IF(K48<>"",5500+K48,5500) | Q48: 46 | R48: MOLINA FLORES 1 | S48: 80000 | T48: 20000 | U48: 1 | V48: 22/03/2026
B49: J CAMPILLO 1637 | D49: 1 | H49: 33000 | I49: 33000 | L49: =IF(K49<>"",12750+K49,12750) | Q49: 47 | R49: BLAS PARERA 9777 | S49: 80000 | T49: 20000 | U49: 1 | V49: 14/03/2026
B50: EMIR | C50: 1 | H50: 22000 | J50: 22000 | L50: =IF(K50<>"",8500+K50,8500) | Q50: 48 | R50: FRANCIA 1872 | S50: 80000 | T50: 20000 | U50: 1 | V50: 15/03/2026
B51: AZCUENAGA 5023 | C51: 7 | D51: 2 | H51: 150000 | I51: 150000 | L51: =IF(K51<>"",15000+K51,15000) | Q51: 49 | R51: BONEO 2625 | S51: 80000 | T51: 20000 | U51: 1 | V51: 16/03/2026
B52: PIRU | D52: 1 | H52: 31500 | I52: 31500 | L52: =IF(K52<>"",11250+K52,11250) | Q52: 50 | R52: BERUTI 5199 | S52: 80000 | T52: 20000 | U52: 1 | V52: 18/03/2026
A53: 46086 | B53: FABIAN LUBRICENTRO | C53: 1 | H53: 21000 | I53: 21000 | L53: =IF(K53<>"",7500+K53,7500) | Q53: 51 | R53: LOPEZ Y PLANES 4630 | S53: 80000 | T53: 20000 | U53: 1 | V53: 19/03/2026
B54: CHICLANA 7325 | C54: 1 | H54: 14500 | I54: 14500 | L54: =IF(K54<>"",1000+K54,1000) | Q54: 52 | R54: NOGALES 2651 | S54: 80000 | T54: 20000 | U54: 1 | V54: 20/03/2026
B55: PARAGUAY 10333 | E55: 1 | H55: 75000 | I55: 75000 | L55: =IF(K55<>"",26000+K55,26000) | Q55: 53 | R55: LARGUIA 7824 | S55: 80000 | T55: 20000 | U55: 1 | V55: 23/03/2026
B56: GOROSTIAGA 4659 | E56: 1 | H56: 76000 | J56: 76000 | L56: =IF(K56<>"",27000+K56,27000) | Q56: 54 | R56: ECUADOR 4117 | S56: 80000 | T56: 20000 | U56: 1 | V56: 23/03/2026
B57: GUEMES 4421 | C57: 1 | H57: 21000 | J57: 21000 | L57: =IF(K57<>"",7500+K57,7500) | Q57: 55 | R57: PJE PUBLICO 2035 | S57: 80000 | T57: 20000 | U57: 1 | V57: 24/03/2026
B58: RIOJA 2934 | C58: 1 | H58: 23000 | J58: 23000 | L58: =IF(K58<>"",9500+K58,9500) | Q58: 56 | R58: ULRICO SCHMIT | S58: 80000 | T58: 20000 | U58: 1 | V58: 24/03/2026
B59: LARGUIA 6924 | C59: 1 | H59: 22500 | J59: 22500 | L59: =IF(K59<>"",9000+K59,9000) | Q59: 57 | R59: VIEYTES 5168 | S59: 80000 | T59: 20000 | U59: 1 | V59: 25/03/2026
B60: IGUALDAD | C60: 1 | H60: 20000 | I60: 20000 | L60: =IF(K60<>"",6500+K60,6500) | Q60: 58 | R60: LARGUIA 7186 | S60: 80000 | T60: 20000 | U60: 1 | V60: 25/03/2026
B61: SAN LORENZO 1987 | E61: 1 | H61: 75000 | I61: 75000 | L61: =IF(K61<>"",26000+K61,26000) | Q61: 59 | R61: GABOTO 7484 | S61: 79900 | T61: 19900 | U61: 1 | V61: 13/03/2026
B62: FILOMENA | C62: 1 | H62: 19000 | J62: 19000 | L62: =IF(K62<>"",5500+K62,5500) | Q62: 60 | R62: L Y PLANES 3884 | S62: 79900 | T62: 19900 | U62: 1 | V62: 13/03/2026
B63: BERUTI 4057 | E63: 1 | H63: 75000 | J63: 75000 | L63: =IF(K63<>"",26000+K63,26000) | Q63: 61 | R63: PJE LUIS BELTRAN 4362 | S63: 79900 | T63: 19900 | U63: 1 | V63: 14/03/2026
B64: LAVAISE 1074 | G64: 2 | H64: 12000 | J64: 12000 | L64: =IF(K64<>"",10300+K64,10300) | Q64: 62 | R64: LARREA 3164 | S64: 79900 | T64: 19900 | U64: 1 | V64: 15/03/2026
B65: PANA VOEYTES 4500 | E65: 1 | H65: 68000 | J65: 68000 | L65: =IF(K65<>"",19000+K65,19000) | Q65: 63 | R65: SAVEDRA 10125 | S65: 79000 | T65: 19000 | U65: 1 | V65: 09/04/2026
B66: EXE | E66: 1 | H66: 72000 | J66: 72000 | L66: =IF(K66<>"",23000+K66,23000) | Q66: 64 | R66: PUBLICO 2550 | S66: 79000 | T66: 19000 | U66: 1 | V66: 24/03/2026
B67: CAFERATA 9416 | D67: 1 | H67: 33000 | I67: 33000 | L67: =IF(K67<>"",12750+K67,12750) | Q67: 65 | R67: FRAY CAYETANO 3823 | S67: 79000 | T67: 19000 | U67: 1 | V67: 07/03/2026
B68: PANA VIEYTE 3800 | E68: 2 | H68: 148000 | J68: 148000 | L68: =IF(K68<>"",50000+K68,50000) | Q68: 66 | R68: LOBOS | S68: 79000 | T68: 19000 | U68: 1 | V68: 07/03/2026
B69: CAREN | E69: 1 | H69: 72000 | J69: 72000 | L69: =IF(K69<>"",23000+K69,23000) | Q69: 67 | R69: ARISTOBULO 8998 | S69: 79000 | T69: 19000 | U69: 1 | V69: 21/03/2026
B70: LAVADERO | C70: 1 | H70: 14500 | J70: 14500 | L70: =IF(K70<>"",1000+K70,1000) | Q70: 68 | R70: REIANARES 8257 | S70: 79000 | T70: 19000 | U70: 1 | V70: 22/03/2026
A71: 46087 | B71: PANA ALBERTI | E71: 1 | H71: 72000 | I71: 72000 | L71: =IF(K71<>"",23000+K71,23000) | Q71: 69 | R71: ANREALES 10512 | S71: 79000 | T71: 19000 | U71: 1 | V71: 24/03/2026
B72: ALE RUIZ | G72: 1 | H72: 5000 | I72: 5000 | L72: =IF(K72<>"",4150+K72,4150) | Q72: 70 | R72: BLAS PARERA 6372 | S72: 78000 | T72: 18000 | U72: 1 | V72: 15/03/2026
B73: CHICLANA 7325 | C73: 1 | H73: 14500 | I73: 14500 | L73: =IF(K73<>"",1000+K73,1000) | Q73: 71 | R73: TERCER PJE 4771 | S73: 78000 | T73: 18000 | U73: 1 | V73: 18/03/2026
B74: PANA GENESIO | E74: 1 | H74: 69000 | J74: 69000 | L74: =IF(K74<>"",20000+K74,20000) | Q74: 72 | R74: LOS PORKI | S74: 77000 | T74: 17000 | U74: 1 | V74: 23/03/2026
B75: AGUADO 8432 | C75: 1 | H75: 21000 | I75: 21000 | L75: =IF(K75<>"",7500+K75,7500) | Q75: 73 | R75: PIEDRABUENA 4506 | S75: 77000 | T75: 17000 | U75: 1 | V75: 03/03/2026
B76: SANDRA | C76: 1 | H76: 15000 | I76: 15000 | L76: =IF(K76<>"",1500+K76,1500) | Q76: 74 | R76: PJE ROCA 6371 | S76: 77000 | T76: 17000 | U76: 1 | V76: 14/03/2026
B77: SAVEDRA 7701 | E77: 1 | H77: 75000 | I77: 75000 | L77: =IF(K77<>"",26000+K77,26000) | Q77: 75 | R77: NAMUNCURA 4436 | S77: 76000 | T77: 16000 | U77: 1 | V77: 07/04/2026
B78: BEATRIZ | G78: 1 | H78: 5500 | J78: 5500 | L78: =IF(K78<>"",4650+K78,4650) | Q78: 76 | R78: JOSE CIBILS | S78: 76000 | T78: 16000 | U78: 1 | V78: 01/03/2026
B79: MANTOVANI 6537 | C79: 1 | H79: 21000 | I79: 21000 | L79: =IF(K79<>"",7500+K79,7500) | Q79: 77 | R79: GOROSTIAGA 4659 | S79: 76000 | T79: 16000 | U79: 1 | V79: 05/03/2026
B80: MATEU 3378 | C80: 1 | H80: 20000 | I80: 20000 | L80: =IF(K80<>"",6500+K80,6500) | Q80: 78 | R80: PUBLICO 1829 | S80: 76000 | T80: 16000 | U80: 1 | V80: 06/03/2026
B81: BRASERIA | E81: 1 | H81: 73000 | I81: 50000 | J81: 23000 | L81: =IF(K81<>"",24000+K81,24000) | Q81: 79 | R81: BRAZIL 4117 | S81: 76000 | T81: 16000 | U81: 1 | V81: 10/03/2026
B82: SABOREAR | C82: 2 | H82: 39000 | J82: 39000 | L82: =IF(K82<>"",12000+K82,12000) | Q82: 80 | R82: PIEDRABUENA 4599 | S82: 76000 | T82: 16000 | U82: 1 | V82: 10/03/2026
B83: FILOMENA | C83: 1 | H83: 19000 | J83: 19000 | L83: =IF(K83<>"",5500+K83,5500) | Q83: 81 | R83: LAS HERAS Y GORRITI | S83: 75000 | T83: 15000 | U83: 1 | V83: 01/03/2026
B84: OTNIEL | G84: 1 | H84: 5500 | J84: 5500 | L84: =IF(K84<>"",4650+K84,4650) | Q84: 82 | R84: PARAGUAY 10333 | S84: 75000 | T84: 15000 | U84: 1 | V84: 05/03/2026
B85: ABUELA MARGA | C85: 2 | H85: 39000 | I85: 39000 | L85: =IF(K85<>"",12000+K85,12000) | Q85: 83 | R85: SAN LORENZO 1987 | S85: 75000 | T85: 15000 | U85: 1 | V85: 05/03/2026
B86: NACHO | C86: 1 | H86: 19000 | J86: 19000 | L86: =IF(K86<>"",5500+K86,5500) | Q86: 84 | R86: BERUTI 4057 | S86: 75000 | T86: 15000 | U86: 1 | V86: 05/03/2026
B87: PUBLICO 1829 | E87: 1 | H87: 76000 | J87: 76000 | L87: =IF(K87<>"",27000+K87,27000) | Q87: 85 | R87: SAVEDRA 7701 | S87: 75000 | T87: 15000 | U87: 1 | V87: 06/03/2026
B88: M CANDIOTI 5759 | C88: 1 | H88: 23000 | I88: 23000 | L88: =IF(K88<>"",9500+K88,9500) | Q88: 86 | R88: CORDOBA 2753 | S88: 75000 | T88: 15000 | U88: 1 | V88: 10/03/2026
B89: 9 DE JULIO 1144 | E89: 2 | H89: 158000 | J89: 158000 | L89: =IF(K89<>"",60000+K89,60000) | Q89: 87 | R89: CASTELLI 5364 | S89: 75000 | T89: 15000 | U89: 1 | V89: 12/03/2026
A90: 46088 | B90: FRAY CAYETANO 3823 | E90: 1 | H90: 79000 | I90: 79000 | L90: =IF(K90<>"",30000+K90,30000) | Q90: 88 | R90: PENALOZA 7220 | S90: 74000 | T90: 14000 | U90: 1 | V90: 09/03/2026
B91: J P LOPEZ 1875 | D91: 1 | H91: 33000 | I91: 33000 | L91: =IF(K91<>"",12750+K91,12750) | Q91: 89 | R91: BERUTI 3850 PANA | S91: 74000 | T91: 14000 | U91: 1 | V91: 22/03/2026
B92: DANI TALLER | C92: 1 | H92: 17000 | I92: 17000 | L92: =IF(K92<>"",3500+K92,3500) | Q92: 90 | R92: ROQUE S PENA 7668 | S92: 73000 | T92: 13000 | U92: 1 | V92: 03/03/2026
B93: FRENCH BIS 2000 GONZA TORRI | E93: 1 | H93: 97000 | J93: 97000 | L93: =IF(K93<>"",48000+K93,48000) | Q93: 91 | R93: PANA BERUTI | S93: 73000 | T93: 13000 | U93: 1 | V93: 23/03/2026
B94: LAVADERO | C94: 1 | H94: 14500 | I94: 14500 | L94: =IF(K94<>"",1000+K94,1000) | Q94: 92 | R94: PANA HNO FIGUEROA | S94: 70000 | T94: 10000 | U94: 1 | V94: 13/03/2026
B95: R GODOY 1614 | C95: 1 | H95: 21000 | J95: 21000 | L95: =IF(K95<>"",7500+K95,7500) | Q95: 93 | R95: PANA FIGUEROA | S95: 70000 | T95: 10000 | U95: 1 | V95: 26/03/2026
B96: LOBOS | E96: 1 | H96: 79000 | I96: 79000 | L96: =IF(K96<>"",30000+K96,30000) | Q96: 94 | R96: DANA | S96: 68000 | T96: 8000 | U96: 1 | V96: 22/04/2026
B97: LUCHO | C97: 2 | H97: 30000 | J97: 30000 | L97: =IF(K97<>"",3000+K97,3000) | Q97: 95 | R97: PANA VOEYTES 4500 | S97: 68000 | T97: 8000 | U97: 1 | V97: 04/04/2026
B98: GABOTO 7445 | C98: 1 | H98: 20000 | I98: 20000 | L98: =IF(K98<>"",6500+K98,6500) | Q98: 96 | R98: LARREA 3339 | S98: 68000 | T98: 8000 | U98: 1 | V98: 23/03/2026
B99: AZCUENAGA 5023 | C99: 2 | D99: 1 | H99: 52500 | J99: 52500 | L99: =IF(K99<>"",5250+K99,5250) | Q99: 97 | R99: ANDRE | S99: 68000 | T99: 22000 | U99: 1 | V99: 16/03/2026
B100: HNO OTNIEL | G100: 1 | H100: 5500 | J100: 5500 | L100: =IF(K100<>"",4650+K100,4650) | Q100: 98 | R100: GORRITI 5019 | S100: 64000 | T100: 4000 | U100: 1 | V100: 24/03/2026
...

Sheet Abril
A1: VENTAS — ABRIL 2026 | Q1: 🏆 RANKING ABRIL
A2: ⚠ El nombre del cliente debe ser EXACTAMENTE igual siempre · La ganancia se calcula con el costo vigente a la fecha | Q2: # | R2: Cliente | S2: Facturado | T2: Ganancia | U2: Pedidos | V2: Últ. compra
Q3: 🥇 | R3: AZCUENAGA 5023 | S3: 475000 | T3: 100000 | U3: 4 | V3: 20/04/2026
A4: FECHA | B4: CLIENTE / DIRECCIÓN | C4: 10 | D4: 15 | E4: 45 | F4: YERBA | G4: AGUA | H4: VALOR ($) | I4: EFECTIVO ($) | J4: TRANSFER ($) | K4: ENVASE ($) | L4: GANANCIA ($) | N4: RESUMEN ABRIL | Q4: 🥈 | R4: FILOMENA | S4: 437000 | T4: 152000 | U4: 10 | V4: 20/04/2026
A5: 46113 | B5: DOMINGO SILVA 4217 | C5: 2 | D5: 1 | H5: 66500 | J5: 66500 | L5: =IF(K5<>"",14000+K5,14000) | N5: TOTAL 10 | O5: =IFERROR(SUM(C5:C700),0) | Q5: 🥉 | R5: OTNIEL | S5: 415300 | T5: 152650 | U5: 6 | V5: 16/04/2026
B6: MAMA NICO BUSTO | C6: 1 | F6: 10 | H6: 61000 | J6: 61000 | L6: =IF(K6<>"",23000+K6,23000) | N6: TOTAL 15 | O6: =IFERROR(SUM(D5:D700),0) | Q6: 4 | R6: LUCHO | S6: 411000 | T6: 94300 | U6: 10 | V6: 20/04/2026
B7: PANA VIEYTES 4500 | E7: 1 | H7: 78000 | J7: 78000 | L7: =IF(K7<>"",18000+K7,18000) | N7: TOTAL 45 | O7: =IFERROR(SUM(E5:E700),0) | Q7: 5 | R7: CAREN | S7: 328000 | T7: 88000 | U7: 4 | V7: 20/04/2026
B8: OTNIEL | G8: 3 | H8: 16500 | J8: 16500 | L8: =IF(K8<>"",13950+K8,13950) | N8: TOTAL YERBA | O8: =IFERROR(SUM(F5:F700),0) | Q8: 6 | R8: EXE | S8: 328000 | T8: 88000 | U8: 4 | V8: 19/04/2026
B9: M ZAPATA 2101 | C9: 2 | H9: 39000 | I9: 39000 | L9: =IF(K9<>"",9000+K9,9000) | N9: TOTAL AGUA | O9: =IFERROR(SUM(G5:G700),0) | Q9: 7 | R9: DANA | S9: 324000 | T9: 69000 | U9: 5 | V9: 22/04/2026
B10: LUCHO | C10: 1 | H10: 19000 | J10: 19000 | L10: =IF(K10<>"",4000+K10,4000) | Q10: 8 | R10: BRASERIA | S10: 249000 | T10: 69000 | U10: 3 | V10: 18/04/2026
B11: ALBERTI 5570 | E11: 2 | H11: 166000 | J11: 166000 | L11: =IF(K11<>"",46000+K11,46000) | N11: FACTURACIÓN | O11: =IFERROR(SUM(H5:H700),0) | Q11: 9 | R11: PANA ALBERTI | S11: 246000 | T11: 66000 | U11: 3 | V11: 22/04/2026
B12: ROTI SAN LORENZO | C12: 2 | D12: 1 | H12: 84000 | J12: 84000 | L12: =IF(K12<>"",31500+K12,31500) | N12: GANANCIA | O12: =IFERROR(SUM(L5:L700),0) | Q12: 10 | R12: PANA VIEYTES 4500 | S12: 234000 | T12: 54000 | U12: 3 | V12: 16/04/2026
B13: LUCHIO | G13: 1 | H13: 6000 | J13: 6000 | L13: =IF(K13<>"",5150+K13,5150) | N13: % GANANCIA | O13: =IFERROR(SUM(L5:L700)/SUM(H5:H700),0) | Q13: 11 | R13: ROTI SAN LORENZO | S13: 201000 | T13: 73500 | U13: 2 | V13: 15/04/2026
B14: GENEIRO 8200 | D14: 1 | H14: 39000 | I14: 39000 | L14: =IF(K14<>"",16500+K14,16500) | Q14: 12 | R14: SABOREAR | S14: 193500 | T14: 58500 | U14: 5 | V14: 22/04/2026
B15: FILOMENA | C15: 2 | H15: 46000 | J15: 46000 | L15: =IF(K15<>"",16000+K15,16000) | N15: EFECTIVO | O15: =IFERROR(SUM(I5:I700),0) | Q15: 13 | R15: ROTI VIEYTES | S15: 183000 | T15: 48000 | U15: 3 | V15: 17/04/2026
B16: SABOREAR | C16: 1 | H16: 22500 | J16: 22500 | L16: =IF(K16<>"",7500+K16,7500) | N16: TRANSFERENCIA | O16: =IFERROR(SUM(J5:J700),0) | Q16: 14 | R16: TERE | S16: 172000 | T16: 52000 | U16: 1 | V16: 02/04/2026
B17: MITRE 4930 | C17: 1 | H17: 27000 | I17: 27000 | L17: =IF(K17<>"",12000+K17,12000) | Q17: 15 | R17: ALBERTI 5570 | S17: 166000 | T17: 46000 | U17: 1 | V17: 01/04/2026
B18: POSTA EL TORO | C18: 2 | H18: 38000 | I18: 38000 | L18: =IF(K18<>"",8000+K18,8000) | N18: Nº VENTAS | O18: =IFERROR(COUNTA(B5:B700),0) | Q18: 16 | R18: PANA BERUTI 6400 | S18: 150000 | T18: 30000 | U18: 2 | V18: 22/04/2026
B19: LUCHO | C19: 1 | D19: 1 | H19: 47500 | J19: 47500 | L19: =IF(K19<>"",10000+K19,10000) | N19: DÍAS DEL MES | O19: 30 | Q19: 17 | R19: PANADERIA BAGUETE | S19: 150000 | T19: 30000 | U19: 2 | V19: 22/04/2026
B20: LA MADRID 7175 | D20: 1 | H20: 39000 | J20: 39000 | L20: =IF(K20<>"",16500+K20,16500) | Q20: 18 | R20: DOMINGO SILVA 4217 | S20: 142500 | T20: 30000 | U20: 2 | V20: 19/04/2026
B21: ROTI ARISTOBULO 5401 | D21: 1 | H21: 33500 | I21: 33500 | L21: =IF(K21<>"",11000+K21,11000) | N21: OBJETIVO ($) | Q21: 19 | R21: PANA BERUTI 3850 | S21: 142000 | T21: 37000 | U21: 1 | V21: 08/04/2026
A22: 46114 | B22: GABOTO 8168 | E22: 1 | H22: 83000 | J22: 83000 | L22: =IF(K22<>"",23000+K22,23000) | N22: DIFERENCIA | O22: =IFERROR(SUM(L5:L700)-N21,0) | Q22: 20 | R22: SANDRA | S22: 141000 | T22: 34300 | U22: 3 | V22: 16/04/2026
B23: AZCUENAGA 5023 | C23: 7 | H23: 133000 | J23: 133000 | L23: =IF(K23<>"",28000+K23,28000) | Q23: 21 | R23: DUSSO 7678 | S23: 133000 | T23: 28000 | U23: 1 | V23: 04/04/2026
B24: OTNIEL | C24: 1 | D24: 1 | H24: 57000 | J24: 57000 | L24: =IF(K24<>"",19500+K24,19500) | N24: KG BUTANO | O24: =IFERROR((SUM(C5:C700)*10)+(SUM(D5:D700)*15),0) | Q24: 22 | R24: LARGUIA 7287 | S24: 132000 | T24: 42000 | U24: 1 | V24: 20/04/2026
B25: LINIERS 3735 | C25: 1 | H25: 26000 | I25: 26000 | L25: =IF(K25<>"",11000+K25,11000) | N25: KG PROPANO | O25: =IFERROR(SUM(E5:E700)*45,0) | Q25: 23 | R25: ROTI AGUADO | S25: 115500 | T25: 33000 | U25: 2 | V25: 17/04/2026
B26: SIRLAKI | E26: 1 | H26: 80000 | J26: 80000 | L26: =IF(K26<>"",20000+K26,20000) | N26: KG TOTAL | O26: =IFERROR(O24+O25,0) | Q26: 24 | R26: GOLRD BURGER | S26: 115000 | T26: 40000 | U26: 1 | V26: 04/04/2026
B27: DANA | C27: 3 | H27: 57000 | I27: 57000 | L27: =IF(K27<>"",12000+K27,12000) | Q27: 25 | R27: COGORNP 5520 | S27: 114000 | T27: 24000 | U27: 1 | V27: 18/04/2026
B28: CASTELLI 2219 | C28: 1 | H28: 27000 | J28: 27000 | L28: =IF(K28<>"",12000+K28,12000) | N28: TICKET PROM. VENTA | O28: =IFERROR(SUM(H5:H700)/COUNTA(B5:B700),0) | Q28: 26 | R28: VIANDAS JORGE | S28: 110000 | T28: 35000 | U28: 5 | V28: 20/04/2026
B29: TERE | E29: 2 | H29: 172000 | I29: 86000 | J29: 86000 | L29: =IF(K29<>"",52000+K29,52000) | N29: TICKET PROM. GANANCIA | O29: =IFERROR(SUM(L5:L700)/COUNTA(B5:B700),0) | Q29: 27 | R29: DANTE | S29: 108000 | T29: 48000 | U29: 2 | V29: 12/04/2026
B30: TACUARI 5717 | C30: 1 | H30: 25000 | J30: 25000 | L30: =IF(K30<>"",10000+K30,10000) | Q30: 28 | R30: PORKIS | S30: 105000 | T30: 30000 | U30: 2 | V30: 19/04/2026
B31: BAIGORRIA 9351 | E31: 1 | H31: 90000 | I31: 90000 | L31: =IF(K31<>"",30000+K31,30000) | Q31: 29 | R31: CANCHA RIVADAVIA | S31: 105000 | T31: 30000 | U31: 1 | V31: 11/04/2026
B32: EXE | E32: 1 | H32: 82000 | J32: 82000 | L32: =IF(K32<>"",22000+K32,22000) | Q32: 30 | R32: GARMENDIA 9250 | S32: 102000 | T32: 40300 | U32: 2 | V32: 17/04/2026
B33: NACHO | C33: 1 | D33: 1 | H33: 56500 | I33: 56500 | L33: =IF(K33<>"",19000+K33,19000) | Q33: 31 | R33: POSTA COLASTINE | S33: 100000 | T33: 25000 | U33: 1 | V33: 04/04/2026
B34: GABOTO 7298 | D34: 1 | H34: 39000 | I34: 39000 | L34: =IF(K34<>"",16500+K34,16500) | Q34: 32 | R34: FREIRE 6181 | S34: 96000 | T34: 36000 | U34: 1 | V34: 06/04/2026
B35: GOROSTIAGA 4619 | E35: 1 | H35: 88000 | J35: 88000 | L35: =IF(K35<>"",28000+K35,28000) | Q35: 33 | R35: GASTON AMARAL | S35: 95000 | T35: 30400 | U35: 1 | V35: 15/04/2026
B36: LARGUIA 6924 | C36: 1 | H36: 25000 | I36: 25000 | L36: =IF(K36<>"",10000+K36,10000) | Q36: 34 | R36: ESTRADA 2198 | S36: 95000 | T36: 35000 | U36: 1 | V36: 10/04/2026
B37: BELNGRANO 3881 | C37: 2 | H37: 54000 | J37: 54000 | L37: =IF(K37<>"",24000+K37,24000) | Q37: 35 | R37: PAULO | S37: 94000 | T37: 19000 | U37: 2 | V37: 13/04/2026
A38: 46115 | B38: PAVON 2124 | D38: 1 | H38: 39000 | I38: 39000 | L38: =IF(K38<>"",16500+K38,16500) | Q38: 36 | R38: SAVEDRA 10125 | S38: 92000 | T38: 32000 | U38: 1 | V38: 09/04/2026
B39: D SILVA 4217 | C39: 2 | H39: 38000 | J39: 38000 | L39: =IF(K39<>"",8000+K39,8000) | Q39: 37 | R39: ILGATO | S39: 92000 | T39: 32000 | U39: 1 | V39: 12/04/2026
B40: ROTI ROCA 6371 | C40: 1 | H40: 25000 | J40: 25000 | L40: =IF(K40<>"",10000+K40,10000) | Q40: 38 | R40: EUROPA 9186 | S40: 90000 | T40: 30000 | U40: 1 | V40: 04/04/2026
B41: BLS PARERA 8380 | D41: 1 | H41: 39000 | I41: 39000 | L41: =IF(K41<>"",16500+K41,16500) | Q41: 39 | R41: TOFFO | S41: 90000 | T41: 30000 | U41: 1 | V41: 22/04/2026
B42: M CANDIOTI 6141 | C42: 1 | H42: 26000 | I42: 26000 | L42: =IF(K42<>"",11000+K42,11000) | Q42: 40 | R42: BAIGORRIA 9351 | S42: 90000 | T42: 30000 | U42: 1 | V42: 02/04/2026
B43: DANA | C43: 3 | D43: 1 | H43: 86000 | J43: 86000 | L43: =IF(K43<>"",18500+K43,18500) | Q43: 41 | R43: GORRITI 1418 | S43: 90000 | T43: 30000 | U43: 1 | V43: 05/02/2026
B44: SAN LORENZO 5949 | C44: 1 | H44: 25000 | I44: 25000 | L44: =IF(K44<>"",10000+K44,10000) | Q44: 42 | R44: LA PLATA 2834 | S44: 90000 | T44: 30000 | U44: 1 | V44: 05/02/2026
B45: SABORERAR | C45: 1 | H45: 22500 | J45: 22500 | L45: =IF(K45<>"",7500+K45,7500) | Q45: 43 | R45: MARIANA | S45: 90000 | T45: 30000 | U45: 1 | V45: 08/04/2026
B46: BLAS PARERA 9129 | C46: 1 | H46: 27000 | I46: 27000 | L46: =IF(K46<>"",12000+K46,12000) | Q46: 44 | R46: PEDRO VEGA 4343 | S46: 90000 | T46: 30000 | U46: 1 | V46: 09/04/2026
A47: 46116 | B47: CHICLANA 7325 | C47: 1 | H47: 19000 | J47: 19000 | L47: =IF(K47<>"",4000+K47,4000) | Q47: 45 | R47: ARISTOBULO 6897 | S47: 90000 | T47: 30000 | U47: 1 | V47: 11/04/2026
B48: DUSSO 7678 | C48: 4 | D48: 2 | H48: 133000 | I48: 60000 | J48: 73000 | L48: =IF(K48<>"",28000+K48,28000) | Q48: 46 | R48: FRAY CAYETANO 3813 | S48: 90000 | T48: 30000 | U48: 1 | V48: 19/04/2026
B49: FILOMENA | C49: 2 | H49: 46000 | J49: 46000 | L49: =IF(K49<>"",16000+K49,16000) | Q49: 47 | R49: S BAYO 7165 | S49: 89000 | T49: 29000 | U49: 1 | V49: 17/04/2026
B50: EUROPA 9186 | E50: 1 | H50: 90000 | J50: 90000 | L50: =IF(K50<>"",30000+K50,30000) | Q50: 48 | R50: GOROSTIAGA 4619 | S50: 88000 | T50: 28000 | U50: 1 | V50: 02/04/2026
B51: LAPACHOS 1840 | E51: 1 | H51: 86000 | J51: 86000 | L51: =IF(K51<>"",26000+K51,26000) | Q51: 49 | R51: PUBLICO 9118 | S51: 88000 | T51: 28000 | U51: 1 | V51: 15/04/2026
B52: BEATRIZ | G52: 1 | H52: 6000 | J52: 6000 | L52: =IF(K52<>"",5150+K52,5150) | Q52: 50 | R52: LAVAISE 2118 | S52: 87000 | T52: 27000 | U52: 1 | V52: 05/02/2026
B53: POSTA COLASTINE | C53: 5 | H53: 100000 | I53: 100000 | L53: =IF(K53<>"",25000+K53,25000) | Q53: 51 | R53: NAMUNCURA 4436 | S53: 86000 | T53: 26000 | U53: 1 | V53: 07/04/2026
B54: LARGUIA 7251 | C54: 1 | H54: 27000 | I54: 27000 | L54: =IF(K54<>"",12000+K54,12000) | Q54: 52 | R54: LAPACHOS 1840 | S54: 86000 | T54: 26000 | U54: 1 | V54: 04/04/2026
B55: PANA VOEYTES 4500 | E55: 1 | H55: 78000 | J55: 78000 | L55: =IF(K55<>"",18000+K55,18000) | Q55: 53 | R55: LOS PARAISOS 3422 | S55: 86000 | T55: 26000 | U55: 1 | V55: 05/02/2026
B56: GUANELA 4543 | C56: 1 | H56: 25000 | J56: 25000 | L56: =IF(K56<>"",10000+K56,10000) | Q56: 54 | R56: LA SALLE 6030 | S56: 86000 | T56: 26000 | U56: 1 | V56: 06/04/2026
B57: FRANCIA 1047 | C57: 1 | H57: 26000 | I57: 26000 | L57: =IF(K57<>"",11000+K57,11000) | Q57: 55 | R57: PIEDRABUENA 1927 | S57: 86000 | T57: 26000 | U57: 1 | V57: 09/04/2026
B58: ZAVALIA 779 | D58: 1 | H58: 39000 | I58: 39000 | L58: =IF(K58<>"",16500+K58,16500) | Q58: 56 | R58: BLAS PARERA 5224 | S58: 85000 | T58: 25000 | U58: 1 | V58: 09/04/2026
B59: ROTI VIEYTES | D59: 2 | H59: 61000 | J59: 61000 | L59: =IF(K59<>"",16000+K59,16000) | Q59: 57 | R59: F ZUVIRIA 7757 | S59: 85000 | T59: 25000 | U59: 1 | V59: 07/04/2026
B60: JOSE CIBILS 2467 | E60: 1 | H60: 84000 | J60: 84000 | L60: =IF(K60<>"",24000+K60,24000) | Q60: 58 | R60: EX COMBATIENTES 5433 | S60: 85000 | T60: 25000 | U60: 1 | V60: 07/04/2026
B61: FLORES 2 CAS A75 | C61: 1 | H61: 27000 | I61: 27000 | L61: =IF(K61<>"",12000+K61,12000) | Q61: 59 | R61: URQUIZA 2031 | S61: 85000 | T61: 25000 | U61: 1 | V61: 09/04/2026
B62: SAVEDRA 2799 | C62: 1 | H62: 27000 | I62: 27000 | L62: =IF(K62<>"",12000+K62,12000) | Q62: 60 | R62: CASTAÑADUY 7035 | S62: 85000 | T62: 25000 | U62: 1 | V62: 09/04/2026
B63: TERRAZAS | C63: 2 | H63: 54000 | I63: 54000 | L63: =IF(K63<>"",24000+K63,24000) | Q63: 61 | R63: LOBATO | S63: 85000 | T63: 25000 | U63: 1 | V63: 13/04/2026
B64: BRASERIA | E64: 1 | H64: 83000 | J64: 83000 | L64: =IF(K64<>"",23000+K64,23000) | Q64: 62 | R64: 1 DE MAYO 1959 BARSANTA | S64: 85000 | T64: 25000 | U64: 1 | V64: 17/04/2026
B65: LUCHO | C65: 1 | H65: 19000 | J65: 19000 | L65: =IF(K65<>"",4000+K65,4000) | Q65: 63 | R65: CALLEJON FUNES 1883 CARO | S65: 85000 | T65: 25000 | U65: 1 | V65: 17/04/2026
B66: GOLRD BURGER | C66: 5 | H66: 115000 | I66: 115000 | L66: =IF(K66<>"",40000+K66,40000) | Q66: 64 | R66: VIEYTES 5046 | S66: 85000 | T66: 25000 | U66: 1 | V66: 17/04/2026
B67: ALBERTI 5315 | E67: 1 | H67: 80000 | J67: 80000 | L67: =IF(K67<>"",20000+K67,20000) | Q67: 65 | R67: LLERENA 3746 | S67: 85000 | T67: 25000 | U67: 1 | V67: 20/04/2026
B68: LA SALLE Y PUBLICO | E68: 1 | H68: 84000 | J68: 84000 | L68: =IF(K68<>"",24000+K68,24000) | Q68: 66 | R68: JOSE CIBILS 2467 | S68: 84000 | T68: 24000 | U68: 1 | V68: 04/04/2026
B69: JAURETCHE 10100 | C69: 1 | H69: 25000 | I69: 20000 | J69: 5000 | L69: =IF(K69<>"",10000+K69,10000) | Q69: 67 | R69: LA SALLE Y PUBLICO | S69: 84000 | T69: 24000 | U69: 1 | V69: 04/04/2026
B70: CHICLANA 6668 | D70: 1 | H70: 34500 | J70: 34500 | L70: =IF(K70<>"",12000+K70,12000) | Q70: 68 | R70: PUBLICO 8193 | S70: 84000 | T70: 24000 | U70: 1 | V70: 07/04/2026
A71: 46058 | B71: CERVERA 4748 | C71: 1 | H71: 27000 | J71: 27000 | L71: =IF(K71<>"",16500+K71,16500) | Q71: 69 | R71: 9 DE JULIO 9244 | S71: 84000 | T71: 24000 | U71: 1 | V71: 12/04/2026
B72: CHACO 2843 | E72: 1 | H72: 83000 | I72: 83000 | L72: =IF(K72<>"",36000+K72,36000) | Q72: 70 | R72: FRANCIA 9250 | S72: 84000 | T72: 24000 | U72: 1 | V72: 13/04/2026
B73: LAS HERAS 5471 | C73: 2 | H73: 50000 | J73: 50000 | L73: =IF(K73<>"",29000+K73,29000) | Q73: 71 | R73: 7 JEFES 4525 | S73: 84000 | T73: 24000 | U73: 1 | V73: 17/04/2026
B74: VIEYTES 4587 | D74: 1 | H74: 39000 | I74: 39000 | L74: =IF(K74<>"",23250+K74,23250) | Q74: 72 | R74: PEDRO ESPINOSA 3169 | S74: 84000 | T74: 24000 | U74: 1 | V74: 17/04/2026
B75: GORRITI 1418 | E75: 1 | H75: 90000 | J75: 90000 | L75: =IF(K75<>"",43000+K75,43000) | Q75: 73 | R75: GABOTO 8168 | S75: 83000 | T75: 23000 | U75: 1 | V75: 02/04/2026
B76: BARRETO 9261 | D76: 1 | H76: 39000 | J76: 39000 | L76: =IF(K76<>"",23250+K76,23250) | Q76: 74 | R76: CHACO 2843 | S76: 83000 | T76: 23000 | U76: 1 | V76: 05/02/2026
B77: CERVERA 6885 | C77: 1 | H77: 27000 | I77: 27000 | L77: =IF(K77<>"",16500+K77,16500) | Q77: 75 | R77: CALLE 12 3856 | S77: 83000 | T77: 23000 | U77: 1 | V77: 08/04/2026
B78: PANA VIEYTES GISELA | C78: 1 | H78: 22000 | J78: 22000 | L78: =IF(K78<>"",11500+K78,11500) | Q78: 76 | R78: PANA GORRITI 4600 | S78: 82000 | T78: 22000 | U78: 1 | V78: 08/04/2026
B79: PARRI GABOTO | C79: 1 | H79: 23000 | J79: 23000 | L79: =IF(K79<>"",12500+K79,12500) | Q79: 77 | R79: PANA VIEYTES 3800 | S79: 82000 | T79: 22000 | U79: 1 | V79: 08/04/2026
B80: LA PLATA 2834 | E80: 1 | H80: 90000 | J80: 90000 | L80: =IF(K80<>"",43000+K80,43000) | Q80: 78 | R80: SIRLAKI | S80: 80000 | T80: 20000 | U80: 1 | V80: 02/04/2026
B81: LAVAISE 2118 | E81: 1 | H81: 87000 | J81: 87000 | L81: =IF(K81<>"",40000+K81,40000) | Q81: 79 | R81: ALBERTI 5315 | S81: 80000 | T81: 20000 | U81: 1 | V81: 04/04/2026
B82: LOS PARAISOS 3422 | E82: 1 | H82: 86000 | J82: 86000 | L82: =IF(K82<>"",39000+K82,39000) | Q82: 80 | R82: NECOCHEA 3933 | S82: 80000 | T82: 20000 | U82: 1 | V82: 12/04/2026
B83: MANTOVANI 6752 | C83: 1 | H83: 25000 | J83: 25000 | L83: =IF(K83<>"",14500+K83,14500) | Q83: 81 | R83: ALSINA 6601 | S83: 80000 | T83: 20000 | U83: 1 | V83: 22/04/2026
B84: PENALOZA 9757 | C84: 1 | H84: 25500 | J84: 25500 | L84: =IF(K84<>"",15000+K84,15000) | Q84: 82 | R84: PANA VOEYTES 4500 | S84: 78000 | T84: 18000 | U84: 1 | V84: 04/04/2026
B85: TACUARI 5717 | C85: 1 | H85: 25000 | J85: 25000 | L85: =IF(K85<>"",14500+K85,14500) | Q85: 83 | R85: PANA COLODRERO 1258 | S85: 78000 | T85: 18000 | U85: 1 | V85: 06/04/2026
B86: SANDRA | C86: 2 | H86: 38000 | I86: 10000 | J86: 28000 | L86: =IF(K86<>"",17000+K86,17000) | Q86: 84 | R86: PAVON 3435 | S86: 78000 | T86: 18000 | U86: 1 | V86: 13/04/2026
B87: PIRU | D87: 1 | H87: 35500 | J87: 35500 | L87: =IF(K87<>"",19750+K87,19750) | Q87: 85 | R87: AZCUENAGA 3972 | S87: 78000 | T87: 18000 | U87: 1 | V87: 16/04/2026
A88: 46118 | B88: FREIRE 6181 | E88: 1 | H88: 96000 | I88: 96000 | L88: =IF(K88<>"",36000+K88,36000) | Q88: 86 | R88: PANA BERUTI 6726 | S88: 78000 | T88: 18000 | U88: 1 | V88: 22/04/2026
B89: VIANDAS JORGE | C89: 1 | H89: 22000 | I89: 22000 | L89: =IF(K89<>"",7000+K89,7000) | Q89: 87 | R89: SANTA CRUZ 3051 | S89: 78000 | T89: 18000 | U89: 1 | V89: 22/04/2026
B90: HUERGO 2487 | C90: 1 | H90: 25000 | J90: 25000 | L90: =IF(K90<>"",10000+K90,10000) | Q90: 88 | R90: D SILVA 4217 | S90: 76000 | T90: 16000 | U90: 2 | V90: 11/04/2026
B91: PJE MANUE LEIVA 4230 | C91: 1 | H91: 26000 | I91: 26000 | L91: =IF(K91<>"",11000+K91,11000) | Q91: 89 | R91: CHICLANA 7325 | S91: 76000 | T91: 16000 | U91: 3 | V91: 22/04/2026
B92: OTNIEL | D92: 2 | H92: 68000 | J92: 68000 | L92: =IF(K92<>"",23000+K92,23000) | Q92: 90 | R92: TACUARI 5717 | S92: 75000 | T92: 30000 | U92: 3 | V92: 11/04/2026
B93: PJE GIMNASIA 5186 | C93: 1 | H93: 27000 | I93: 27000 | L93: =IF(K93<>"",12000+K93,12000) | Q93: 91 | R93: TROPPO | S93: 75000 | T93: 30000 | U93: 1 | V93: 08/04/2026
B94: LA SALLE 6030 | E94: 1 | H94: 86000 | I94: 86000 | L94: =IF(K94<>"",26000+K94,26000) | Q94: 92 | R94: ROTI ARISTOBULO | S94: 67000 | T94: 22000 | U94: 2 | V94: 18/04/2026
B95: NAMUNCURA 4439 | D95: 1 | H95: 36500 | I95: 36500 | L95: =IF(K95<>"",14000+K95,14000) | Q95: 93 | R95: BONEO 4054 | S95: 65000 | T95: 27500 | U95: 1 | V95: 11/04/2026
B96: PANA COLODRERO 1258 | E96: 1 | H96: 78000 | J96: 78000 | L96: =IF(K96<>"",18000+K96,18000) | Q96: 94 | R96: 4 DE ENERO 1342 | S96: 65000 | T96: 27500 | U96: 1 | V96: 21/04/2026
B97: CAREN | E97: 1 | H97: 82000 | J97: 82000 | L97: =IF(K97<>"",22000+K97,22000) | Q97: 95 | R97: PUBLICO 5727 | S97: 63000 | T97: 25500 | U97: 1 | V97: 20/04/2026
A98: 46119 | B98: PANA ALBERTI | E98: 1 | H98: 82000 | I98: 82000 | L98: =IF(K98<>"",22000+K98,22000) | Q98: 96 | R98: JAVIER DE LA ROSA 459 | S98: 61500 | T98: 24000 | U98: 1 | V98: 15/04/2026
B99: LUCHO | C99: 3 | H99: 57000 | I99: 57000 | L99: =IF(K99<>"",12000+K99,12000) | Q99: 97 | R99: MAMA NICO BUSTO | S99: 61000 | T99: 23000 | U99: 1 | V99: 01/04/2026
B100: AZCUENAGA 5023 | C100: 6 | H100: 114000 | J100: 114000 | L100: =IF(K100<>"",24000+K100,24000) | Q100: 98 | R100: ALBERTI Y GABOTO | S100: 57000 | T100: 12000 | U100: 1 | V100: 09/04/2026
...

Sheet Junio
A1: VENTAS — JUNIO 2026
A2: Datos cargados por Sistema Galiano
A4: FECHA | B4: CLIENTE | C4: 10 | D4: 15 | E4: 45 | F4: YERBA | G4: AGUA/BIDON | H4: VALOR ($) | I4: EFECTIVO ($) | J4: TRANSFER ($) | K4: ENVASE ($) | L4: GANANCIA ($)
A5: 2026-06-01 | B5: DALLAS 6761 | E5: 1 | H5: 98000 | J5: 98000 | L5: 29000
B6: CHICLANA 6630 | C6: 1 | H6: 26000 | J6: 26000 | L6: 9000
B7: BLAS PARERA 6372 | E7: 1 | H7: 93000 | J7: 93000 | L7: 24000
B8: PANA BERUTI 6700 | E8: 1 | H8: 88000 | I8: 88000 | L8: 19000
B9: SAN MARTIN 9308 | D9: 1 | H9: 41500 | I9: 41500 | L9: 16000
B10: LARGUIA 9355 | E10: 1 | H10: 96000 | J10: 96000 | L10: 27000
B11: PANA VIEYTES 4500 | C11: 1 | E11: 1 | H11: 113000 | J11: 113000 | L11: 27000
B12: MARCIAL CANDIOTI 5359 | C12: 1 | H12: 28000 | I12: 28000 | L12: 11000
B13: MATEU 4059 | D13: 1 | H13: 37000 | I13: 37000 | L13: 11500
B14: LAVAISE 3786 | C14: 1 | D14: 1 | H14: 69000 | J14: 69000 | L14: 26500
B15: CASANELLO 3463 | C15: 1 | H15: 28000 | J15: 28000 | L15: 11000
B16: LUCHO | D16: 1 | H16: 35000 | J16: 35000 | L16: 9500
B17: 9 DE JULIO 6810 | C17: 1 | H17: 27500 | I17: 27500 | L17: 10500
B18: FILOMENA | C18: 3 | H18: 79500 | J18: 79500 | L18: 28500
B19: PEDRO ESPINOSA 3169 | E19: 1 | H19: 92000 | I19: 92000 | L19: 23000
A20: 2026-06-02 | B20: ESTRADA 2815 | C20: 1 | H20: 28000 | I20: 28000 | L20: 11000
B21: PASAJE PARAGUAY 10333 | E21: 1 | H21: 96000 | J21: 96000 | L21: 27000
B22: CHICLANA 7325 | C22: 1 | H22: 22500 | J22: 22500 | L22: 5500
B23: MADAME CHEESE | D23: 1 | H23: 38500 | J23: 38500 | L23: 13000
B24: VIANDAS JORGE | C24: 1 | H24: 25000 | I24: 25000 | L24: 8000
B25: IGUALDAD | C25: 1 | H25: 27000 | J25: 27000 | L25: 10000
B26: ROTI ARISTOBULO | C26: 1 | D26: 1 | H26: 65000 | J26: 65000 | L26: 22500
B27: DAVID LEIVA Y ALBERTI | C27: 1 | H27: 27000 | I27: 27000 | L27: 10000
B28: PRIMERO DE MAYO 1605 | D28: 1 | H28: 42000 | I28: 42000 | L28: 16500
B29: PIEDRABUENA 6450 | E29: 1 | H29: 93000 | J29: 93000 | L29: 24000
B30: BRASIL 4871 | C30: 1 | H30: 28000 | I30: 28000 | L30: 11000
B31: SERVANDO BAYO 7250 | C31: 1 | H31: 27000 | I31: 27000 | L31: 10000
B32: ANGELA LAMADRID 7500 | C32: 1 | H32: 28000 | I32: 28000 | L32: 11000
B33: LAMADRID 1086 | C33: 1 | H33: 27000 | J33: 27000 | L33: 10000
B34: CALLE CONFUNE 5070 | E34: 1 | H34: 96000 | J34: 96000 | L34: 27000
B35: COLODRERO 1258 | E35: 1 | H35: 89000 | J35: 89000 | L35: 20000
B36: NOGALES 2426 | C36: 1 | H36: 28000 | J36: 28000 | L36: 11000
B37: BERUTI 6400 | E37: 1 | H37: 96000 | I37: 96000 | L37: 27000
B38: NAMUNCURA 4436 | E38: 1 | H38: 96000 | J38: 96000 | L38: 27000
B39: ALSINA 7980 | C39: 1 | H39: 28000 | I39: 28000 | L39: 11000
B40: GARMENDIA 9249 | D40: 1 | H40: 41500 | J40: 41500 | L40: 16000
B41: NACHO CUEVA | C41: 1 | H41: 25500 | I41: 25500 | L41: 8500
B42: SANDRA | C42: 3 | H42: 66000 | I42: 66000 | L42: 15000
B43: DANA | C43: 1 | D43: 1 | H43: 55000 | J43: 55000 | L43: 12500
A44: 2026-06-03 | B44: PADILLA 1453 | D44: 1 | H44: 42500 | J44: 42500 | L44: 17000
B45: URQUIZA 9396 | E45: 1 | H45: 96000 | J45: 96000 | L45: 27000
B46: VIANDAS JORGE | C46: 1 | H46: 25000 | I46: 25000 | L46: 8000
B47: CLIENTE PORTON | C47: 2 | H47: 46000 | J47: 46000 | L47: 12000
B48: PANA GISELA | F48: 1 | H48: 7500 | J48: 7500 | L48: 7500
B49: FRATERNIDAD GUANELIANA | C49: 1 | H49: 25000 | J49: 25000 | L49: 8000
B50: CASTELI 4320 | C50: 1 | H50: 28000 | I50: 28000 | L50: 11000
B51: CALLEJON FUNES 2965 | C51: 1 | H51: 28000 | J51: 28000 | L51: 11000
B52: PUBLICO 2550 | E52: 1 | H52: 96000 | J52: 96000 | L52: 27000
B53: QUIROGA 5244 | D53: 1 | H53: 41500 | J53: 41500 | L53: 16000
B54: CAFERATA 9416 | D54: 1 | H54: 41500 | J54: 41500 | L54: 16000
B55: BONEO 5363 | E55: 1 | H55: 98000 | J55: 98000 | L55: 29000
B56: NECOCHEA 6709 | D56: 1 | H56: 39500 | I56: 39500 | L56: 14000
B57: EXE | E57: 1 | H57: 93000 | J57: 93000 | L57: 24000
A58: 2026-06-04 | B58: BARRETO 9261 | D58: 1 | H58: 41500 | J58: 41500 | L58: 16000
B59: 4 DE ENERO 1935 | C59: 1 | H59: 131000 | J59: 131000 | K59: 65000 | L59: 49000
B60: RIO NEGRO 6558 | E60: 1 | H60: 98000 | I60: 98000 | L60: 29000
B61: SANDRA | C61: 2 | G61: 2 | H61: 54000 | I61: 54000 | L61: 18160
B62: FACUNDO ZUVIRIA 10235 | E62: 1 | H62: 98500 | I62: 98500 | L62: 29500
B63: PEDRO CEBALLOS 8134 | C63: 3 | H63: 66000 | I63: 66000 | L63: 15000
B64: PUBLICO 8170 | C64: 1 | H64: 28000 | J64: 28000 | L64: 11000
B65: SANTA BAR 1 MAYO 1959 | E65: 2 | H65: 190000 | J65: 190000 | L65: 52000
B66: ROTI SAN LORENZO | C66: 3 | D66: 2 | H66: 155000 | J66: 155000 | L66: 53000
B67: ALSINA 7035 | E67: 1 | H67: 96500 | J67: 96500 | L67: 27500
B68: ANA ABDALA | C68: 1 | H68: 28000 | J68: 28000 | L68: 11000
B69: LAS HERAS 7529 | D69: 1 | H69: 39500 | I69: 39500 | L69: 14000
B70: BRASERIA | E70: 1 | H70: 94000 | J70: 94000 | L70: 25000
B71: PUBLICO 56/20 | E71: 1 | H71: 98000 | J71: 98000 | L71: 29000
B72: SANDRA | C72: 1 | D72: 1 | H72: 55000 | I72: 55000 | L72: 12500
B73: VANE GORDILLO | E73: 1 | H73: 93000 | J73: 93000 | L73: 24000
B74: CAREN | E74: 1 | H74: 93000 | J74: 93000 | L74: 24000
A75: 2026-06-05 | B75: ANDRE | F75: 14 | H75: 95200 | I75: 95200 | L75: 95200
B76: BOULEVARD GALVEZ 2333 | C76: 1 | H76: 29000 | I76: 29000 | L76: 12000
B77: CHICLANA 7325 | C77: 1 | H77: 22500 | J77: 22500 | L77: 5500
B78: LUCHO | C78: 2 | G78: 2 | H78: 44000 | I78: 44000 | L78: 8160
B79: ALSINA 7981 | E79: 1 | H79: 98000 | J79: 98000 | L79: 29000
B80: CERVANTES 3754 | D80: 1 | H80: 41500 | I80: 41500 | L80: 16000
B81: ARENALES 7200 PASILLO | C81: 1 | H81: 27000 | J81: 27000 | L81: 10000
B82: 12 DE INFANTERIA 5210 | C82: 1 | H82: 28000 | I82: 28000 | L82: 11000
B83: VIEYTES 4361 | C83: 2 | H83: 57000 | I83: 57000 | L83: 23000
B84: FABIAN BLAS PARERA | C84: 1 | D84: 1 | H84: 65500 | I84: 65500 | L84: 23000
B85: JM ZUVIRIA 2143 | D85: 1 | H85: 43500 | I85: 43500 | L85: 18000
B86: SAN JERONIMO 5231 | C86: 1 | H86: 110000 | I86: 110000 | K86: 65000 | L86: 28000
B87: LAS HERAS 5471 | C87: 1 | H87: 28500 | J87: 28500 | L87: 11500
B88: SIRLAKI | C88: 1 | H88: 26000 | I88: 26000 | L88: 9000
B89: TACUARI 5717 | C89: 1 | H89: 28500 | J89: 28500 | L89: 11500
B90: FILOMENA | C90: 3 | H90: 79500 | J90: 79500 | L90: 28500
B91: GOBERNADOR FREIRE 6084 | E91: 1 | H91: 96000 | J91: 96000 | L91: 27000
B92: BERNARDO IRIGOYEN 6721 | C92: 1 | H92: 27000 | I92: 27000 | L92: 10000
B93: HUDSON 6047 | D93: 1 | H93: 39500 | J93: 39500 | L93: 14000
B94: LARGUIA 6924 | C94: 1 | H94: 27000 | I94: 27000 | L94: 10000
B95: PANA VIEYTES 3800 | E95: 1 | H95: 93000 | I95: 93000 | L95: 24000
B96: MITRE 6479 | C96: 1 | H96: 27500 | J96: 27500 | L96: 10500
B97: ALSINA 7981 DPTO | E97: 1 | H97: 98000 | J97: 98000 | L97: 29000
B98: NACHO CUEVA | C98: 1 | D98: 1 | H98: 62000 | I98: 62000 | L98: 19500
B99: LARREA 3164 | E99: 1 | H99: 98500 | J99: 98500 | L99: 29500
B100: CERVERA 7037 | D100: 1 | H100: 42500 | I100: 42500 | L100: 17000
B101: LUCHO | C101: 1 | H101: 22000 | I101: 22000 | L101: 5000
...

Sheet Mayo
A1: VENTAS — MAYO 2026
A2: ⚠ El nombre del cliente debe ser EXACTAMENTE igual siempre · La ganancia se calcula con el costo vigente a la fecha
A4: FECHA | B4: CLIENTE / DIRECCIÓN | C4: 10 | D4: 15 | E4: 45 | F4: YERBA | G4: AGUA | H4: VALOR ($) | I4: EFECTIVO ($) | J4: TRANSFER ($) | K4: ENVASE ($) | L4: GANANCIA ($) | N4: RESUMEN MAYO
A5: 46143 | B5: 5TO PASAJE 9681 | E5: 1 | H5: 95000 | J5: 95000 | L5: =IF(K5<>"",35000+K5,35000) | N5: TOTAL 10 | O5: =IFERROR(SUM(C5:C700),0)
B6: PIEDRABUENA 4506 | E6: 1 | H6: 91000 | J6: 91000 | L6: =IF(K6<>"",31000+K6,31000) | N6: TOTAL 15 | O6: =IFERROR(SUM(D5:D700),0)
B7: ALBERTI 5303 | C7: 1 | H7: 25000 | I7: 25000 | L7: =IF(K7<>"",10000+K7,10000) | N7: TOTAL 45 | O7: =IFERROR(SUM(E5:E700),0)
B8: LUCHO | C8: 1 | D8: 1 | H8: 47500 | I8: 47500 | L8: =IF(K8<>"",10000+K8,10000) | N8: TOTAL YERBA | O8: =IFERROR(SUM(F5:F700),0)
B9: CALLEJON ROCA 2622 | C9: 1 | H9: 27000 | I9: 27000 | L9: =IF(K9<>"",12000+K9,12000) | N9: TOTAL AGUA | O9: =IFERROR(SUM(G5:G700),0)
B10: 4 DE ENERO 6652 | C10: 1 | H10: 27000 | I10: 27000 | L10: =IF(K10<>"",12000+K10,12000)
B11: GUANELLA 4883 | D11: 1 | H11: 37500 | J11: 37500 | L11: =IF(K11<>"",15000+K11,15000) | N11: FACTURACIÓN | O11: =IFERROR(SUM(H5:H700),0)
B12: CARRANZA 8275 | C12: 1 | H12: 26000 | J12: 26000 | L12: =IF(K12<>"",11000+K12,11000) | N12: GANANCIA | O12: =IFERROR(SUM(L5:L700),0)
B13: GENEIRO 8249 | C13: 1 | H13: 26000 | J13: 26000 | L13: =IF(K13<>"",11000+K13,11000) | N13: % GANANCIA | O13: =IFERROR(SUM(L5:L700)/SUM(H5:H700),0)
B14: PANA ALBERTI | E14: 1 | H14: 82000 | I14: 82000 | L14: =IF(K14<>"",22000+K14,22000)
B15: BAGUETTE | E15: 1 | H15: 75000 | J15: 75000 | L15: =IF(K15<>"",15000+K15,15000) | N15: EFECTIVO | O15: =IFERROR(SUM(I5:I700),0)
B16: RIVADAVIA 8280 | E16: 1 | H16: 92000 | J16: 92000 | L16: =IF(K16<>"",32000+K16,32000) | N16: TRANSFERENCIA | O16: =IFERROR(SUM(J5:J700),0)
B17: LUCHO | C17: 1 | D17: 1 | H17: 47500 | J17: 47500 | L17: =IF(K17<>"",10000+K17,10000)
B18: MARCIAL CANDIOTI 6281 | D18: 1 | H18: 39000 | I18: 39000 | L18: =IF(K18<>"",16500+K18,16500) | N18: Nº VENTAS | O18: =IFERROR(COUNTA(B5:B700),0)
B19: BRASERIA | E19: 1 | H19: 83000 | J19: 83000 | L19: =IF(K19<>"",23000+K19,23000) | N19: DÍAS DEL MES | O19: 31
A20: 46144 | B20: RIVADAVIA JUNIORS | C20: 2 | H20: 52000 | I20: 52000 | L20: =IF(K20<>"",22000+K20,22000)
B21: URQUIZA 9309 | C21: 2 | D21: 1 | H21: 68500 | J21: 68500 | L21: =IF(K21<>"",16000+K21,16000) | N21: OBJETIVO ($)
B22: BEATRIZ | G22: 2 | H22: 12000 | J22: 12000 | L22: =IF(K22<>"",10300+K22,10300) | N22: DIFERENCIA | O22: =IFERROR(SUM(L5:L700)-N21,0)
B23: LAVALLE 4859 | C23: 1 | H23: 26000 | I23: 26000 | L23: =IF(K23<>"",11000+K23,11000)
B24: DOMINGO SILVA 4217 | C24: 1 | D24: 1 | H24: 47500 | J24: 47500 | L24: =IF(K24<>"",10000+K24,10000) | N24: KG BUTANO | O24: =IFERROR((SUM(C5:C700)*10)+(SUM(D5:D700)*15),0)
B25: ALSINA 7981 | E25: 1 | H25: 84000 | I25: 84000 | L25: =IF(K25<>"",24000+K25,24000) | N25: KG PROPANO | O25: =IFERROR(SUM(E5:E700)*45,0)
B26: ROTI SAN LORENZO | C26: 2 | D26: 1 | H26: 85000 | J26: 85000 | L26: =IF(K26<>"",32500+K26,32500) | N26: KG TOTAL | O26: =IFERROR(O24+O25,0)
B27: OTNIEL | D27: 1 | E27: 1 | H27: 115000 | I27: 115000 | L27: =IF(K27<>"",32500+K27,32500)
B28: MARCE DUSO | C28: 3 | H28: 57000 | I28: 57000 | L28: =IF(K28<>"",12000+K28,12000) | N28: TICKET PROM. VENTA | O28: =IFERROR(SUM(H5:H700)/COUNTA(B5:B700),0)
B29: VIÑAS 9420 | E29: 1 | H29: 92000 | J29: 92000 | L29: =IF(K29<>"",32000+K29,32000) | N29: TICKET PROM. GANANCIA | O29: =IFERROR(SUM(L5:L700)/COUNTA(B5:B700),0)
B30: VIANDAS JORGE | C30: 1 | H30: 22000 | I30: 22000 | L30: =IF(K30<>"",7000+K30,7000)
B31: JOSE CIBILS 6789 | E31: 1 | H31: 91000 | I31: 91000 | L31: =IF(K31<>"",31000+K31,31000)
B32: RICARDO ALDAO 3082 | C32: 1 | H32: 26000 | I32: 26000 | L32: =IF(K32<>"",11000+K32,11000)
B33: FLORENCIO FERNANDEZ 6196 | C33: 10 | H33: 185000 | J33: 185000 | L33: =IF(K33<>"",35000+K33,35000)
B34: FLORES 1 CANCHITA | C34: 1 | H34: 26000 | I34: 26000 | L34: =IF(K34<>"",11000+K34,11000)
B35: GORRITI 4661 | C35: 1 | H35: 26000 | J35: 26000 | L35: =IF(K35<>"",11000+K35,11000)
B36: AZOPARDO Y FLORENCIO SANCHEZ | D36: 1 | H36: 35500 | J36: 35500 | L36: =IF(K36<>"",13000+K36,13000)
B37: CALLE 14 3363 | E37: 1 | H37: 91000 | J37: 91000 | L37: =IF(K37<>"",31000+K37,31000)
B38: REMEDIO DE ESCALADA | E38: 2 | H38: 180000 | I38: 180000 | L38: =IF(K38<>"",60000+K38,60000)
B39: LUCHO | C39: 1 | D39: 1 | H39: 47500 | J39: 47500 | L39: =IF(K39<>"",10000+K39,10000)
B40: SAN JUAN 1963 | E40: 1 | H40: 91000 | J40: 91000 | L40: =IF(K40<>"",31000+K40,31000)
B41: URQUIZA 9309 | C41: 3 | D41: 1 | H41: 88000 | J41: 88000 | L41: =IF(K41<>"",20500+K41,20500)
B42: MISIONES 4693 | E42: 1 | H42: 91000 | J42: 91000 | L42: =IF(K42<>"",31000+K42,31000)
B43: FILOMENA | C43: 2 | H43: 46000 | J43: 46000 | L43: =IF(K43<>"",16000+K43,16000)
B44: PANA VIEYTES GISELA | C44: 2 | H44: 44000 | J44: 44000 | L44: =IF(K44<>"",14000+K44,14000)
B45: SABOREAR | C45: 1 | H45: 22500 | J45: 22500 | L45: =IF(K45<>"",7500+K45,7500)
B46: PAVON 4712 | C46: 1 | H46: 26000 | J46: 26000 | L46: =IF(K46<>"",11000+K46,11000)
B47: LAVADERO | C47: 2 | H47: 38000 | I47: 38000 | L47: =IF(K47<>"",8000+K47,8000)
A48: 46145 | B48: PEDRONI 6704 | E48: 1 | H48: 90000 | I48: 90000 | L48: =IF(K48<>"",(IF(H48="","",H48-(C48*COSTOS!$C$6+D48*COSTOS!$C$7+E48*COSTOS!$C$8+F48*COSTOS!$C$9+G48*COSTOS!$C$10)))+K48,IF(H48="","",H48-(C48*COSTOS!$C$6+D48*COSTOS!$C$7+E48*COSTOS!$C$8+F48*COSTOS!$C$9+G48*COSTOS!$C$10)))
B49: CÓRDOBA 2753 | E49: 1 | H49: 91000 | I49: 91000 | L49: =IF(K49<>"",(IF(H49="","",H49-(C49*COSTOS!$C$6+D49*COSTOS!$C$7+E49*COSTOS!$C$8+F49*COSTOS!$C$9+G49*COSTOS!$C$10)))+K49,IF(H49="","",H49-(C49*COSTOS!$C$6+D49*COSTOS!$C$7+E49*COSTOS!$C$8+F49*COSTOS!$C$9+G49*COSTOS!$C$10)))
B50: AYACUCHO 5644 | E50: 1 | H50: 91000 | J50: 91000 | L50: =IF(K50<>"",(IF(H50="","",H50-(C50*COSTOS!$C$6+D50*COSTOS!$C$7+E50*COSTOS!$C$8+F50*COSTOS!$C$9+G50*COSTOS!$C$10)))+K50,IF(H50="","",H50-(C50*COSTOS!$C$6+D50*COSTOS!$C$7+E50*COSTOS!$C$8+F50*COSTOS!$C$9+G50*COSTOS!$C$10)))
B51: DOMINGO SILVA 4217 | C51: 2 | H51: 38000 | I51: 38000 | L51: =IF(K51<>"",(IF(H51="","",H51-(C51*COSTOS!$C$6+D51*COSTOS!$C$7+E51*COSTOS!$C$8+F51*COSTOS!$C$9+G51*COSTOS!$C$10)))+K51,IF(H51="","",H51-(C51*COSTOS!$C$6+D51*COSTOS!$C$7+E51*COSTOS!$C$8+F51*COSTOS!$C$9+G51*COSTOS!$C$10)))
B52: JOSÉ 6529 | E52: 1 | H52: 95000 | J52: 95000 | L52: =IF(K52<>"",(IF(H52="","",H52-(C52*COSTOS!$C$6+D52*COSTOS!$C$7+E52*COSTOS!$C$8+F52*COSTOS!$C$9+G52*COSTOS!$C$10)))+K52,IF(H52="","",H52-(C52*COSTOS!$C$6+D52*COSTOS!$C$7+E52*COSTOS!$C$8+F52*COSTOS!$C$9+G52*COSTOS!$C$10)))
B53: PORKIS | C53: 1 | H53: 23000 | J53: 23000 | L53: =IF(K53<>"",(IF(H53="","",H53-(C53*COSTOS!$C$6+D53*COSTOS!$C$7+E53*COSTOS!$C$8+F53*COSTOS!$C$9+G53*COSTOS!$C$10)))+K53,IF(H53="","",H53-(C53*COSTOS!$C$6+D53*COSTOS!$C$7+E53*COSTOS!$C$8+F53*COSTOS!$C$9+G53*COSTOS!$C$10)))
B54: LUCHO | C54: 1 | D54: 1 | H54: 47500 | J54: 47500 | L54: =IF(K54<>"",(IF(H54="","",H54-(C54*COSTOS!$C$6+D54*COSTOS!$C$7+E54*COSTOS!$C$8+F54*COSTOS!$C$9+G54*COSTOS!$C$10)))+K54,IF(H54="","",H54-(C54*COSTOS!$C$6+D54*COSTOS!$C$7+E54*COSTOS!$C$8+F54*COSTOS!$C$9+G54*COSTOS!$C$10)))
B55: SERVANDO 6858 | E55: 1 | H55: 91000 | I55: 91000 | L55: =IF(K55<>"",(IF(H55="","",H55-(C55*COSTOS!$C$6+D55*COSTOS!$C$7+E55*COSTOS!$C$8+F55*COSTOS!$C$9+G55*COSTOS!$C$10)))+K55,IF(H55="","",H55-(C55*COSTOS!$C$6+D55*COSTOS!$C$7+E55*COSTOS!$C$8+F55*COSTOS!$C$9+G55*COSTOS!$C$10)))
B56: QUINTANA 1868 | C56: 1 | H56: 27000 | I56: 27000 | L56: =IF(K56<>"",(IF(H56="","",H56-(C56*COSTOS!$C$6+D56*COSTOS!$C$7+E56*COSTOS!$C$8+F56*COSTOS!$C$9+G56*COSTOS!$C$10)))+K56,IF(H56="","",H56-(C56*COSTOS!$C$6+D56*COSTOS!$C$7+E56*COSTOS!$C$8+F56*COSTOS!$C$9+G56*COSTOS!$C$10)))
B57: SANTA CRUZ 3051 | E57: 1 | H57: 78000 | I57: 78000 | L57: =IF(K57<>"",(IF(H57="","",H57-(C57*COSTOS!$C$6+D57*COSTOS!$C$7+E57*COSTOS!$C$8+F57*COSTOS!$C$9+G57*COSTOS!$C$10)))+K57,IF(H57="","",H57-(C57*COSTOS!$C$6+D57*COSTOS!$C$7+E57*COSTOS!$C$8+F57*COSTOS!$C$9+G57*COSTOS!$C$10)))
B58: GABOTO 8168 | E58: 1 | H58: 91000 | I58: 91000 | L58: =IF(K58<>"",(IF(H58="","",H58-(C58*COSTOS!$C$6+D58*COSTOS!$C$7+E58*COSTOS!$C$8+F58*COSTOS!$C$9+G58*COSTOS!$C$10)))+K58,IF(H58="","",H58-(C58*COSTOS!$C$6+D58*COSTOS!$C$7+E58*COSTOS!$C$8+F58*COSTOS!$C$9+G58*COSTOS!$C$10)))
B59: DUCHO | C59: 1 | H59: 19000 | J59: 19000 | L59: =IF(K59<>"",(IF(H59="","",H59-(C59*COSTOS!$C$6+D59*COSTOS!$C$7+E59*COSTOS!$C$8+F59*COSTOS!$C$9+G59*COSTOS!$C$10)))+K59,IF(H59="","",H59-(C59*COSTOS!$C$6+D59*COSTOS!$C$7+E59*COSTOS!$C$8+F59*COSTOS!$C$9+G59*COSTOS!$C$10)))
B60: 50 Y 23 | C60: 3 | H60: 57000 | I60: 57000 | L60: =IF(K60<>"",(IF(H60="","",H60-(C60*COSTOS!$C$6+D60*COSTOS!$C$7+E60*COSTOS!$C$8+F60*COSTOS!$C$9+G60*COSTOS!$C$10)))+K60,IF(H60="","",H60-(C60*COSTOS!$C$6+D60*COSTOS!$C$7+E60*COSTOS!$C$8+F60*COSTOS!$C$9+G60*COSTOS!$C$10)))
B61: 9 DE JULIO 1356 | C61: 1 | H61: 27000 | I61: 27000 | L61: =IF(K61<>"",(IF(H61="","",H61-(C61*COSTOS!$C$6+D61*COSTOS!$C$7+E61*COSTOS!$C$8+F61*COSTOS!$C$9+G61*COSTOS!$C$10)))+K61,IF(H61="","",H61-(C61*COSTOS!$C$6+D61*COSTOS!$C$7+E61*COSTOS!$C$8+F61*COSTOS!$C$9+G61*COSTOS!$C$10)))
B62: AVELLANEDA 4448 | E62: 1 | H62: 87000 | J62: 87000 | L62: =IF(K62<>"",(IF(H62="","",H62-(C62*COSTOS!$C$6+D62*COSTOS!$C$7+E62*COSTOS!$C$8+F62*COSTOS!$C$9+G62*COSTOS!$C$10)))+K62,IF(H62="","",H62-(C62*COSTOS!$C$6+D62*COSTOS!$C$7+E62*COSTOS!$C$8+F62*COSTOS!$C$9+G62*COSTOS!$C$10)))
B63: AZOPARDO 6965 | E63: 1 | H63: 91000 | J63: 91000 | L63: =IF(K63<>"",(IF(H63="","",H63-(C63*COSTOS!$C$6+D63*COSTOS!$C$7+E63*COSTOS!$C$8+F63*COSTOS!$C$9+G63*COSTOS!$C$10)))+K63,IF(H63="","",H63-(C63*COSTOS!$C$6+D63*COSTOS!$C$7+E63*COSTOS!$C$8+F63*COSTOS!$C$9+G63*COSTOS!$C$10)))
B64: EXE | E64: 1 | H64: 82000 | J64: 82000 | L64: =IF(K64<>"",(IF(H64="","",H64-(C64*COSTOS!$C$6+D64*COSTOS!$C$7+E64*COSTOS!$C$8+F64*COSTOS!$C$9+G64*COSTOS!$C$10)))+K64,IF(H64="","",H64-(C64*COSTOS!$C$6+D64*COSTOS!$C$7+E64*COSTOS!$C$8+F64*COSTOS!$C$9+G64*COSTOS!$C$10)))
B65: CAREN | E65: 1 | H65: 82000 | J65: 82000 | L65: =IF(K65<>"",(IF(H65="","",H65-(C65*COSTOS!$C$6+D65*COSTOS!$C$7+E65*COSTOS!$C$8+F65*COSTOS!$C$9+G65*COSTOS!$C$10)))+K65,IF(H65="","",H65-(C65*COSTOS!$C$6+D65*COSTOS!$C$7+E65*COSTOS!$C$8+F65*COSTOS!$C$9+G65*COSTOS!$C$10)))
B66: DANA | C66: 4 | H66: 76000 | J66: 76000 | L66: =IF(K66<>"",(IF(H66="","",H66-(C66*COSTOS!$C$6+D66*COSTOS!$C$7+E66*COSTOS!$C$8+F66*COSTOS!$C$9+G66*COSTOS!$C$10)))+K66,IF(H66="","",H66-(C66*COSTOS!$C$6+D66*COSTOS!$C$7+E66*COSTOS!$C$8+F66*COSTOS!$C$9+G66*COSTOS!$C$10)))
A67: 46146 | B67: JORGE VIANDAS | C67: 1 | H67: 22000 | J67: 22000 | L67: =IF(K67<>"",(IF(H67="","",H67-(C67*COSTOS!$C$6+D67*COSTOS!$C$7+E67*COSTOS!$C$8+F67*COSTOS!$C$9+G67*COSTOS!$C$10)))+K67,IF(H67="","",H67-(C67*COSTOS!$C$6+D67*COSTOS!$C$7+E67*COSTOS!$C$8+F67*COSTOS!$C$9+G67*COSTOS!$C$10)))
B68: OTNIEL | F68: 20 | H68: 69000 | I68: 69000 | L68: =IF(K68<>"",(IF(H68="","",H68-(C68*COSTOS!$C$6+D68*COSTOS!$C$7+E68*COSTOS!$C$8+F68*COSTOS!$C$9+G68*COSTOS!$C$10)))+K68,IF(H68="","",H68-(C68*COSTOS!$C$6+D68*COSTOS!$C$7+E68*COSTOS!$C$8+F68*COSTOS!$C$9+G68*COSTOS!$C$10)))
B69: FLORES 1 MOLINA | E69: 1 | H69: 91000 | I69: 91000 | L69: =IF(K69<>"",(IF(H69="","",H69-(C69*COSTOS!$C$6+D69*COSTOS!$C$7+E69*COSTOS!$C$8+F69*COSTOS!$C$9+G69*COSTOS!$C$10)))+K69,IF(H69="","",H69-(C69*COSTOS!$C$6+D69*COSTOS!$C$7+E69*COSTOS!$C$8+F69*COSTOS!$C$9+G69*COSTOS!$C$10)))
B70: BAGUETTE | E70: 1 | H70: 75000 | J70: 75000 | L70: =IF(K70<>"",(IF(H70="","",H70-(C70*COSTOS!$C$6+D70*COSTOS!$C$7+E70*COSTOS!$C$8+F70*COSTOS!$C$9+G70*COSTOS!$C$10)))+K70,IF(H70="","",H70-(C70*COSTOS!$C$6+D70*COSTOS!$C$7+E70*COSTOS!$C$8+F70*COSTOS!$C$9+G70*COSTOS!$C$10)))
B71: JM ZUVIRIA 3439 | C71: 1 | H71: 26000 | I71: 26000 | L71: =IF(K71<>"",(IF(H71="","",H71-(C71*COSTOS!$C$6+D71*COSTOS!$C$7+E71*COSTOS!$C$8+F71*COSTOS!$C$9+G71*COSTOS!$C$10)))+K71,IF(H71="","",H71-(C71*COSTOS!$C$6+D71*COSTOS!$C$7+E71*COSTOS!$C$8+F71*COSTOS!$C$9+G71*COSTOS!$C$10)))
B72: PEDRONI 6521 | C72: 2 | H72: 39000 | I72: 39000 | L72: =IF(K72<>"",(IF(H72="","",H72-(C72*COSTOS!$C$6+D72*COSTOS!$C$7+E72*COSTOS!$C$8+F72*COSTOS!$C$9+G72*COSTOS!$C$10)))+K72,IF(H72="","",H72-(C72*COSTOS!$C$6+D72*COSTOS!$C$7+E72*COSTOS!$C$8+F72*COSTOS!$C$9+G72*COSTOS!$C$10)))
B73: GUANELLA 4543 | C73: 1 | H73: 25000 | J73: 25000 | L73: =IF(K73<>"",(IF(H73="","",H73-(C73*COSTOS!$C$6+D73*COSTOS!$C$7+E73*COSTOS!$C$8+F73*COSTOS!$C$9+G73*COSTOS!$C$10)))+K73,IF(H73="","",H73-(C73*COSTOS!$C$6+D73*COSTOS!$C$7+E73*COSTOS!$C$8+F73*COSTOS!$C$9+G73*COSTOS!$C$10)))
B74: BERUTI 4075 | E74: 2 | H74: 182000 | J74: 182000 | L74: =IF(K74<>"",(IF(H74="","",H74-(C74*COSTOS!$C$6+D74*COSTOS!$C$7+E74*COSTOS!$C$8+F74*COSTOS!$C$9+G74*COSTOS!$C$10)))+K74,IF(H74="","",H74-(C74*COSTOS!$C$6+D74*COSTOS!$C$7+E74*COSTOS!$C$8+F74*COSTOS!$C$9+G74*COSTOS!$C$10)))
B75: ROTI VIEYTES | D75: 2 | H75: 61000 | J75: 61000 | L75: =IF(K75<>"",(IF(H75="","",H75-(C75*COSTOS!$C$6+D75*COSTOS!$C$7+E75*COSTOS!$C$8+F75*COSTOS!$C$9+G75*COSTOS!$C$10)))+K75,IF(H75="","",H75-(C75*COSTOS!$C$6+D75*COSTOS!$C$7+E75*COSTOS!$C$8+F75*COSTOS!$C$9+G75*COSTOS!$C$10)))
B76: DAVID LEIVA Y ALBERTO | C76: 1 | H76: 25000 | I76: 25000 | L76: =IF(K76<>"",(IF(H76="","",H76-(C76*COSTOS!$C$6+D76*COSTOS!$C$7+E76*COSTOS!$C$8+F76*COSTOS!$C$9+G76*COSTOS!$C$10)))+K76,IF(H76="","",H76-(C76*COSTOS!$C$6+D76*COSTOS!$C$7+E76*COSTOS!$C$8+F76*COSTOS!$C$9+G76*COSTOS!$C$10)))
B77: SAN MARTÍN 6376 | C77: 1 | H77: 26000 | J77: 26000 | L77: =IF(K77<>"",(IF(H77="","",H77-(C77*COSTOS!$C$6+D77*COSTOS!$C$7+E77*COSTOS!$C$8+F77*COSTOS!$C$9+G77*COSTOS!$C$10)))+K77,IF(H77="","",H77-(C77*COSTOS!$C$6+D77*COSTOS!$C$7+E77*COSTOS!$C$8+F77*COSTOS!$C$9+G77*COSTOS!$C$10)))
B78: DRUGSTORE LODENICO | C78: 3 | H78: 58500 | J78: 58500 | L78: =IF(K78<>"",(IF(H78="","",H78-(C78*COSTOS!$C$6+D78*COSTOS!$C$7+E78*COSTOS!$C$8+F78*COSTOS!$C$9+G78*COSTOS!$C$10)))+K78,IF(H78="","",H78-(C78*COSTOS!$C$6+D78*COSTOS!$C$7+E78*COSTOS!$C$8+F78*COSTOS!$C$9+G78*COSTOS!$C$10)))
B79: NECOCHEA 7314 | E79: 1 | H79: 91000 | J79: 91000 | L79: =IF(K79<>"",(IF(H79="","",H79-(C79*COSTOS!$C$6+D79*COSTOS!$C$7+E79*COSTOS!$C$8+F79*COSTOS!$C$9+G79*COSTOS!$C$10)))+K79,IF(H79="","",H79-(C79*COSTOS!$C$6+D79*COSTOS!$C$7+E79*COSTOS!$C$8+F79*COSTOS!$C$9+G79*COSTOS!$C$10)))
B80: EX COMBATIENTES 5500 | C80: 1 | H80: 27000 | I80: 27000 | L80: =IF(K80<>"",(IF(H80="","",H80-(C80*COSTOS!$C$6+D80*COSTOS!$C$7+E80*COSTOS!$C$8+F80*COSTOS!$C$9+G80*COSTOS!$C$10)))+K80,IF(H80="","",H80-(C80*COSTOS!$C$6+D80*COSTOS!$C$7+E80*COSTOS!$C$8+F80*COSTOS!$C$9+G80*COSTOS!$C$10)))
B81: FILOMENA | C81: 2 | H81: 46000 | J81: 46000 | L81: =IF(K81<>"",(IF(H81="","",H81-(C81*COSTOS!$C$6+D81*COSTOS!$C$7+E81*COSTOS!$C$8+F81*COSTOS!$C$9+G81*COSTOS!$C$10)))+K81,IF(H81="","",H81-(C81*COSTOS!$C$6+D81*COSTOS!$C$7+E81*COSTOS!$C$8+F81*COSTOS!$C$9+G81*COSTOS!$C$10)))
B82: EX COMBATIENTES 5400 | C82: 1 | H82: 25000 | J82: 25000 | L82: =IF(K82<>"",(IF(H82="","",H82-(C82*COSTOS!$C$6+D82*COSTOS!$C$7+E82*COSTOS!$C$8+F82*COSTOS!$C$9+G82*COSTOS!$C$10)))+K82,IF(H82="","",H82-(C82*COSTOS!$C$6+D82*COSTOS!$C$7+E82*COSTOS!$C$8+F82*COSTOS!$C$9+G82*COSTOS!$C$10)))
B83: ÁNGEL | D83: 1 | H83: 28500 | I83: 28500 | L83: =IF(K83<>"",(IF(H83="","",H83-(C83*COSTOS!$C$6+D83*COSTOS!$C$7+E83*COSTOS!$C$8+F83*COSTOS!$C$9+G83*COSTOS!$C$10)))+K83,IF(H83="","",H83-(C83*COSTOS!$C$6+D83*COSTOS!$C$7+E83*COSTOS!$C$8+F83*COSTOS!$C$9+G83*COSTOS!$C$10)))
B84: ALMONACID 4248 | C84: 1 | H84: 26000 | J84: 26000 | L84: =IF(K84<>"",(IF(H84="","",H84-(C84*COSTOS!$C$6+D84*COSTOS!$C$7+E84*COSTOS!$C$8+F84*COSTOS!$C$9+G84*COSTOS!$C$10)))+K84,IF(H84="","",H84-(C84*COSTOS!$C$6+D84*COSTOS!$C$7+E84*COSTOS!$C$8+F84*COSTOS!$C$9+G84*COSTOS!$C$10)))
B85: SANDRA | C85: 2 | H85: 38000 | I85: 38000 | L85: =IF(K85<>"",(IF(H85="","",H85-(C85*COSTOS!$C$6+D85*COSTOS!$C$7+E85*COSTOS!$C$8+F85*COSTOS!$C$9+G85*COSTOS!$C$10)))+K85,IF(H85="","",H85-(C85*COSTOS!$C$6+D85*COSTOS!$C$7+E85*COSTOS!$C$8+F85*COSTOS!$C$9+G85*COSTOS!$C$10)))
B86: JULIO ALBERTI | E86: 1 | H86: 95000 | I86: 95000 | L86: =IF(K86<>"",(IF(H86="","",H86-(C86*COSTOS!$C$6+D86*COSTOS!$C$7+E86*COSTOS!$C$8+F86*COSTOS!$C$9+G86*COSTOS!$C$10)))+K86,IF(H86="","",H86-(C86*COSTOS!$C$6+D86*COSTOS!$C$7+E86*COSTOS!$C$8+F86*COSTOS!$C$9+G86*COSTOS!$C$10)))
A87: 46147 | B87: LUCIANO TORRENT 2027 | C87: 1 | H87: 27000 | I87: 27000 | L87: =IF(K87<>"",(IF(H87="","",H87-(C87*COSTOS!$C$6+D87*COSTOS!$C$7+E87*COSTOS!$C$8+F87*COSTOS!$C$9+G87*COSTOS!$C$10)))+K87,IF(H87="","",H87-(C87*COSTOS!$C$6+D87*COSTOS!$C$7+E87*COSTOS!$C$8+F87*COSTOS!$C$9+G87*COSTOS!$C$10)))
B88: AVENIDA FREIRE 3151 | C88: 1 | H88: 27000 | I88: 27000 | L88: =IF(K88<>"",(IF(H88="","",H88-(C88*COSTOS!$C$6+D88*COSTOS!$C$7+E88*COSTOS!$C$8+F88*COSTOS!$C$9+G88*COSTOS!$C$10)))+K88,IF(H88="","",H88-(C88*COSTOS!$C$6+D88*COSTOS!$C$7+E88*COSTOS!$C$8+F88*COSTOS!$C$9+G88*COSTOS!$C$10)))
B89: NAMUNCURA 4436 | E89: 1 | H89: 89000 | J89: 89000 | L89: =IF(K89<>"",(IF(H89="","",H89-(C89*COSTOS!$C$6+D89*COSTOS!$C$7+E89*COSTOS!$C$8+F89*COSTOS!$C$9+G89*COSTOS!$C$10)))+K89,IF(H89="","",H89-(C89*COSTOS!$C$6+D89*COSTOS!$C$7+E89*COSTOS!$C$8+F89*COSTOS!$C$9+G89*COSTOS!$C$10)))
A90: 46148 | B90: SUPERCERATO | C90: 1 | H90: 25000 | J90: 25000 | L90: =IF(K90<>"",(IF(H90="","",H90-(C90*COSTOS!$C$6+D90*COSTOS!$C$7+E90*COSTOS!$C$8+F90*COSTOS!$C$9+G90*COSTOS!$C$10)))+K90,IF(H90="","",H90-(C90*COSTOS!$C$6+D90*COSTOS!$C$7+E90*COSTOS!$C$8+F90*COSTOS!$C$9+G90*COSTOS!$C$10)))
B91: ESPORA 4874 | D91: 1 | H91: 43000 | J91: 43000 | L91: =IF(K91<>"",(IF(H91="","",H91-(C91*COSTOS!$C$6+D91*COSTOS!$C$7+E91*COSTOS!$C$8+F91*COSTOS!$C$9+G91*COSTOS!$C$10)))+K91,IF(H91="","",H91-(C91*COSTOS!$C$6+D91*COSTOS!$C$7+E91*COSTOS!$C$8+F91*COSTOS!$C$9+G91*COSTOS!$C$10)))
B92: CHICLANA 7325 | C92: 1 | H92: 19000 | J92: 19000 | L92: =IF(K92<>"",(IF(H92="","",H92-(C92*COSTOS!$C$6+D92*COSTOS!$C$7+E92*COSTOS!$C$8+F92*COSTOS!$C$9+G92*COSTOS!$C$10)))+K92,IF(H92="","",H92-(C92*COSTOS!$C$6+D92*COSTOS!$C$7+E92*COSTOS!$C$8+F92*COSTOS!$C$9+G92*COSTOS!$C$10)))
B93: BAIGORRIA 9351 | E93: 1 | H93: 95000 | I93: 95000 | L93: =IF(K93<>"",(IF(H93="","",H93-(C93*COSTOS!$C$6+D93*COSTOS!$C$7+E93*COSTOS!$C$8+F93*COSTOS!$C$9+G93*COSTOS!$C$10)))+K93,IF(H93="","",H93-(C93*COSTOS!$C$6+D93*COSTOS!$C$7+E93*COSTOS!$C$8+F93*COSTOS!$C$9+G93*COSTOS!$C$10)))
B94: ZAVALLA 6577 | C94: 1 | H94: 26000 | I94: 26000 | L94: =IF(K94<>"",(IF(H94="","",H94-(C94*COSTOS!$C$6+D94*COSTOS!$C$7+E94*COSTOS!$C$8+F94*COSTOS!$C$9+G94*COSTOS!$C$10)))+K94,IF(H94="","",H94-(C94*COSTOS!$C$6+D94*COSTOS!$C$7+E94*COSTOS!$C$8+F94*COSTOS!$C$9+G94*COSTOS!$C$10)))
B95: ROTI ARISTÓBULO | D95: 1 | H95: 33500 | J95: 33500 | L95: =IF(K95<>"",(IF(H95="","",H95-(C95*COSTOS!$C$6+D95*COSTOS!$C$7+E95*COSTOS!$C$8+F95*COSTOS!$C$9+G95*COSTOS!$C$10)))+K95,IF(H95="","",H95-(C95*COSTOS!$C$6+D95*COSTOS!$C$7+E95*COSTOS!$C$8+F95*COSTOS!$C$9+G95*COSTOS!$C$10)))
B96: GENERAL PAZ 7826 | C96: 2 | H96: 52000 | I96: 52000 | L96: =IF(K96<>"",(IF(H96="","",H96-(C96*COSTOS!$C$6+D96*COSTOS!$C$7+E96*COSTOS!$C$8+F96*COSTOS!$C$9+G96*COSTOS!$C$10)))+K96,IF(H96="","",H96-(C96*COSTOS!$C$6+D96*COSTOS!$C$7+E96*COSTOS!$C$8+F96*COSTOS!$C$9+G96*COSTOS!$C$10)))
B97: LEMANN 7856 | C97: 1 | H97: 26000 | J97: 26000 | L97: =IF(K97<>"",(IF(H97="","",H97-(C97*COSTOS!$C$6+D97*COSTOS!$C$7+E97*COSTOS!$C$8+F97*COSTOS!$C$9+G97*COSTOS!$C$10)))+K97,IF(H97="","",H97-(C97*COSTOS!$C$6+D97*COSTOS!$C$7+E97*COSTOS!$C$8+F97*COSTOS!$C$9+G97*COSTOS!$C$10)))
B98: CASTAÑADUI 6601 | C98: 1 | H98: 26000 | I98: 26000 | L98: =IF(K98<>"",(IF(H98="","",H98-(C98*COSTOS!$C$6+D98*COSTOS!$C$7+E98*COSTOS!$C$8+F98*COSTOS!$C$9+G98*COSTOS!$C$10)))+K98,IF(H98="","",H98-(C98*COSTOS!$C$6+D98*COSTOS!$C$7+E98*COSTOS!$C$8+F98*COSTOS!$C$9+G98*COSTOS!$C$10)))
B99: LAS HERAS 6714 | C99: 1 | H99: 25000 | J99: 25000 | L99: =IF(K99<>"",(IF(H99="","",H99-(C99*COSTOS!$C$6+D99*COSTOS!$C$7+E99*COSTOS!$C$8+F99*COSTOS!$C$9+G99*COSTOS!$C$10)))+K99,IF(H99="","",H99-(C99*COSTOS!$C$6+D99*COSTOS!$C$7+E99*COSTOS!$C$8+F99*COSTOS!$C$9+G99*COSTOS!$C$10)))
B100: PANA VIEYTES 4500 | E100: 1 | H100: 78000 | I100: 78000 | L100: =IF(K100<>"",(IF(H100="","",H100-(C100*COSTOS!$C$6+D100*COSTOS!$C$7+E100*COSTOS!$C$8+F100*COSTOS!$C$9+G100*COSTOS!$C$10)))+K100,IF(H100="","",H100-(C100*COSTOS!$C$6+D100*COSTOS!$C$7+E100*COSTOS!$C$8+F100*COSTOS!$C$9+G100*COSTOS!$C$10)))
B101: ASCUÉNAGA 5023 | C101: 3 | D101: 1 | H101: 85500 | J101: 85500 | L101: =IF(K101<>"",(IF(H101="","",H101-(C101*COSTOS!$C$6+D101*COSTOS!$C$7+E101*COSTOS!$C$8+F101*COSTOS!$C$9+G101*COSTOS!$C$10)))+K101,IF(H101="","",H101-(C101*COSTOS!$C$6+D101*COSTOS!$C$7+E101*COSTOS!$C$8+F101*COSTOS!$C$9+G101*COSTOS!$C$10)))
...

Sheet Julio
A1: VENTAS — JULIO 2026
A2: ⚠ El nombre del cliente debe ser EXACTAMENTE igual siempre · La ganancia se calcula con el costo vigente a la fecha
A4: FECHA | B4: CLIENTE / DIRECCIÓN | C4: 10 | D4: 15 | E4: 45 | F4: YERBA | G4: AGUA | H4: VALOR ($) | I4: EFECTIVO ($) | J4: TRANSFER ($) | K4: ENVASE ($) | L4: GANANCIA ($) | N4: RESUMEN JULIO
L5: =IF(K5<>"",(IF(H5="","",H5-(C5*COSTOS!$C$6+D5*COSTOS!$C$7+E5*COSTOS!$C$8+F5*COSTOS!$C$9+G5*COSTOS!$C$10)))+K5,IF(H5="","",H5-(C5*COSTOS!$C$6+D5*COSTOS!$C$7+E5*COSTOS!$C$8+F5*COSTOS!$C$9+G5*COSTOS!$C$10))) | N5: TOTAL 10 | O5: =IFERROR(SUM(C5:C700),0)
L6: =IF(K6<>"",(IF(H6="","",H6-(C6*COSTOS!$C$6+D6*COSTOS!$C$7+E6*COSTOS!$C$8+F6*COSTOS!$C$9+G6*COSTOS!$C$10)))+K6,IF(H6="","",H6-(C6*COSTOS!$C$6+D6*COSTOS!$C$7+E6*COSTOS!$C$8+F6*COSTOS!$C$9+G6*COSTOS!$C$10))) | N6: TOTAL 15 | O6: =IFERROR(SUM(D5:D700),0)
L7: =IF(K7<>"",(IF(H7="","",H7-(C7*COSTOS!$C$6+D7*COSTOS!$C$7+E7*COSTOS!$C$8+F7*COSTOS!$C$9+G7*COSTOS!$C$10)))+K7,IF(H7="","",H7-(C7*COSTOS!$C$6+D7*COSTOS!$C$7+E7*COSTOS!$C$8+F7*COSTOS!$C$9+G7*COSTOS!$C$10))) | N7: TOTAL 45 | O7: =IFERROR(SUM(E5:E700),0)
L8: =IF(K8<>"",(IF(H8="","",H8-(C8*COSTOS!$C$6+D8*COSTOS!$C$7+E8*COSTOS!$C$8+F8*COSTOS!$C$9+G8*COSTOS!$C$10)))+K8,IF(H8="","",H8-(C8*COSTOS!$C$6+D8*COSTOS!$C$7+E8*COSTOS!$C$8+F8*COSTOS!$C$9+G8*COSTOS!$C$10))) | N8: TOTAL YERBA | O8: =IFERROR(SUM(F5:F700),0)
L9: =IF(K9<>"",(IF(H9="","",H9-(C9*COSTOS!$C$6+D9*COSTOS!$C$7+E9*COSTOS!$C$8+F9*COSTOS!$C$9+G9*COSTOS!$C$10)))+K9,IF(H9="","",H9-(C9*COSTOS!$C$6+D9*COSTOS!$C$7+E9*COSTOS!$C$8+F9*COSTOS!$C$9+G9*COSTOS!$C$10))) | N9: TOTAL AGUA | O9: =IFERROR(SUM(G5:G700),0)
L10: =IF(K10<>"",(IF(H10="","",H10-(C10*COSTOS!$C$6+D10*COSTOS!$C$7+E10*COSTOS!$C$8+F10*COSTOS!$C$9+G10*COSTOS!$C$10)))+K10,IF(H10="","",H10-(C10*COSTOS!$C$6+D10*COSTOS!$C$7+E10*COSTOS!$C$8+F10*COSTOS!$C$9+G10*COSTOS!$C$10)))
L11: =IF(K11<>"",(IF(H11="","",H11-(C11*COSTOS!$C$6+D11*COSTOS!$C$7+E11*COSTOS!$C$8+F11*COSTOS!$C$9+G11*COSTOS!$C$10)))+K11,IF(H11="","",H11-(C11*COSTOS!$C$6+D11*COSTOS!$C$7+E11*COSTOS!$C$8+F11*COSTOS!$C$9+G11*COSTOS!$C$10))) | N11: FACTURACIÓN | O11: =IFERROR(SUM(H5:H700),0)
L12: =IF(K12<>"",(IF(H12="","",H12-(C12*COSTOS!$C$6+D12*COSTOS!$C$7+E12*COSTOS!$C$8+F12*COSTOS!$C$9+G12*COSTOS!$C$10)))+K12,IF(H12="","",H12-(C12*COSTOS!$C$6+D12*COSTOS!$C$7+E12*COSTOS!$C$8+F12*COSTOS!$C$9+G12*COSTOS!$C$10))) | N12: GANANCIA | O12: =IFERROR(SUM(L5:L700),0)
L13: =IF(K13<>"",(IF(H13="","",H13-(C13*COSTOS!$C$6+D13*COSTOS!$C$7+E13*COSTOS!$C$8+F13*COSTOS!$C$9+G13*COSTOS!$C$10)))+K13,IF(H13="","",H13-(C13*COSTOS!$C$6+D13*COSTOS!$C$7+E13*COSTOS!$C$8+F13*COSTOS!$C$9+G13*COSTOS!$C$10))) | N13: % GANANCIA | O13: =IFERROR(SUM(L5:L700)/SUM(H5:H700),0)
L14: =IF(K14<>"",(IF(H14="","",H14-(C14*COSTOS!$C$6+D14*COSTOS!$C$7+E14*COSTOS!$C$8+F14*COSTOS!$C$9+G14*COSTOS!$C$10)))+K14,IF(H14="","",H14-(C14*COSTOS!$C$6+D14*COSTOS!$C$7+E14*COSTOS!$C$8+F14*COSTOS!$C$9+G14*COSTOS!$C$10)))
L15: =IF(K15<>"",(IF(H15="","",H15-(C15*COSTOS!$C$6+D15*COSTOS!$C$7+E15*COSTOS!$C$8+F15*COSTOS!$C$9+G15*COSTOS!$C$10)))+K15,IF(H15="","",H15-(C15*COSTOS!$C$6+D15*COSTOS!$C$7+E15*COSTOS!$C$8+F15*COSTOS!$C$9+G15*COSTOS!$C$10))) | N15: EFECTIVO | O15: =IFERROR(SUM(I5:I700),0)
L16: =IF(K16<>"",(IF(H16="","",H16-(C16*COSTOS!$C$6+D16*COSTOS!$C$7+E16*COSTOS!$C$8+F16*COSTOS!$C$9+G16*COSTOS!$C$10)))+K16,IF(H16="","",H16-(C16*COSTOS!$C$6+D16*COSTOS!$C$7+E16*COSTOS!$C$8+F16*COSTOS!$C$9+G16*COSTOS!$C$10))) | N16: TRANSFERENCIA | O16: =IFERROR(SUM(J5:J700),0)
L17: =IF(K17<>"",(IF(H17="","",H17-(C17*COSTOS!$C$6+D17*COSTOS!$C$7+E17*COSTOS!$C$8+F17*COSTOS!$C$9+G17*COSTOS!$C$10)))+K17,IF(H17="","",H17-(C17*COSTOS!$C$6+D17*COSTOS!$C$7+E17*COSTOS!$C$8+F17*COSTOS!$C$9+G17*COSTOS!$C$10)))
L18: =IF(K18<>"",(IF(H18="","",H18-(C18*COSTOS!$C$6+D18*COSTOS!$C$7+E18*COSTOS!$C$8+F18*COSTOS!$C$9+G18*COSTOS!$C$10)))+K18,IF(H18="","",H18-(C18*COSTOS!$C$6+D18*COSTOS!$C$7+E18*COSTOS!$C$8+F18*COSTOS!$C$9+G18*COSTOS!$C$10))) | N18: Nº VENTAS | O18: =IFERROR(COUNTA(B5:B700),0)
L19: =IF(K19<>"",(IF(H19="","",H19-(C19*COSTOS!$C$6+D19*COSTOS!$C$7+E19*COSTOS!$C$8+F19*COSTOS!$C$9+G19*COSTOS!$C$10)))+K19,IF(H19="","",H19-(C19*COSTOS!$C$6+D19*COSTOS!$C$7+E19*COSTOS!$C$8+F19*COSTOS!$C$9+G19*COSTOS!$C$10))) | N19: DÍAS DEL MES | O19: 31
L20: =IF(K20<>"",(IF(H20="","",H20-(C20*COSTOS!$C$6+D20*COSTOS!$C$7+E20*COSTOS!$C$8+F20*COSTOS!$C$9+G20*COSTOS!$C$10)))+K20,IF(H20="","",H20-(C20*COSTOS!$C$6+D20*COSTOS!$C$7+E20*COSTOS!$C$8+F20*COSTOS!$C$9+G20*COSTOS!$C$10)))
L21: =IF(K21<>"",(IF(H21="","",H21-(C21*COSTOS!$C$6+D21*COSTOS!$C$7+E21*COSTOS!$C$8+F21*COSTOS!$C$9+G21*COSTOS!$C$10)))+K21,IF(H21="","",H21-(C21*COSTOS!$C$6+D21*COSTOS!$C$7+E21*COSTOS!$C$8+F21*COSTOS!$C$9+G21*COSTOS!$C$10))) | N21: OBJETIVO ($)
L22: =IF(K22<>"",(IF(H22="","",H22-(C22*COSTOS!$C$6+D22*COSTOS!$C$7+E22*COSTOS!$C$8+F22*COSTOS!$C$9+G22*COSTOS!$C$10)))+K22,IF(H22="","",H22-(C22*COSTOS!$C$6+D22*COSTOS!$C$7+E22*COSTOS!$C$8+F22*COSTOS!$C$9+G22*COSTOS!$C$10))) | N22: DIFERENCIA | O22: =IFERROR(SUM(L5:L700)-N21,0)
L23: =IF(K23<>"",(IF(H23="","",H23-(C23*COSTOS!$C$6+D23*COSTOS!$C$7+E23*COSTOS!$C$8+F23*COSTOS!$C$9+G23*COSTOS!$C$10)))+K23,IF(H23="","",H23-(C23*COSTOS!$C$6+D23*COSTOS!$C$7+E23*COSTOS!$C$8+F23*COSTOS!$C$9+G23*COSTOS!$C$10)))
L24: =IF(K24<>"",(IF(H24="","",H24-(C24*COSTOS!$C$6+D24*COSTOS!$C$7+E24*COSTOS!$C$8+F24*COSTOS!$C$9+G24*COSTOS!$C$10)))+K24,IF(H24="","",H24-(C24*COSTOS!$C$6+D24*COSTOS!$C$7+E24*COSTOS!$C$8+F24*COSTOS!$C$9+G24*COSTOS!$C$10)))
L25: =IF(K25<>"",(IF(H25="","",H25-(C25*COSTOS!$C$6+D25*COSTOS!$C$7+E25*COSTOS!$C$8+F25*COSTOS!$C$9+G25*COSTOS!$C$10)))+K25,IF(H25="","",H25-(C25*COSTOS!$C$6+D25*COSTOS!$C$7+E25*COSTOS!$C$8+F25*COSTOS!$C$9+G25*COSTOS!$C$10)))
L26: =IF(K26<>"",(IF(H26="","",H26-(C26*COSTOS!$C$6+D26*COSTOS!$C$7+E26*COSTOS!$C$8+F26*COSTOS!$C$9+G26*COSTOS!$C$10)))+K26,IF(H26="","",H26-(C26*COSTOS!$C$6+D26*COSTOS!$C$7+E26*COSTOS!$C$8+F26*COSTOS!$C$9+G26*COSTOS!$C$10)))
L27: =IF(K27<>"",(IF(H27="","",H27-(C27*COSTOS!$C$6+D27*COSTOS!$C$7+E27*COSTOS!$C$8+F27*COSTOS!$C$9+G27*COSTOS!$C$10)))+K27,IF(H27="","",H27-(C27*COSTOS!$C$6+D27*COSTOS!$C$7+E27*COSTOS!$C$8+F27*COSTOS!$C$9+G27*COSTOS!$C$10)))
L28: =IF(K28<>"",(IF(H28="","",H28-(C28*COSTOS!$C$6+D28*COSTOS!$C$7+E28*COSTOS!$C$8+F28*COSTOS!$C$9+G28*COSTOS!$C$10)))+K28,IF(H28="","",H28-(C28*COSTOS!$C$6+D28*COSTOS!$C$7+E28*COSTOS!$C$8+F28*COSTOS!$C$9+G28*COSTOS!$C$10)))
L29: =IF(K29<>"",(IF(H29="","",H29-(C29*COSTOS!$C$6+D29*COSTOS!$C$7+E29*COSTOS!$C$8+F29*COSTOS!$C$9+G29*COSTOS!$C$10)))+K29,IF(H29="","",H29-(C29*COSTOS!$C$6+D29*COSTOS!$C$7+E29*COSTOS!$C$8+F29*COSTOS!$C$9+G29*COSTOS!$C$10))) | O29: =IFERROR(SUM(L5:L700)/COUNTA(B5:B700),0)
L30: =IF(K30<>"",(IF(H30="","",H30-(C30*COSTOS!$C$6+D30*COSTOS!$C$7+E30*COSTOS!$C$8+F30*COSTOS!$C$9+G30*COSTOS!$C$10)))+K30,IF(H30="","",H30-(C30*COSTOS!$C$6+D30*COSTOS!$C$7+E30*COSTOS!$C$8+F30*COSTOS!$C$9+G30*COSTOS!$C$10)))
L31: =IF(K31<>"",(IF(H31="","",H31-(C31*COSTOS!$C$6+D31*COSTOS!$C$7+E31*COSTOS!$C$8+F31*COSTOS!$C$9+G31*COSTOS!$C$10)))+K31,IF(H31="","",H31-(C31*COSTOS!$C$6+D31*COSTOS!$C$7+E31*COSTOS!$C$8+F31*COSTOS!$C$9+G31*COSTOS!$C$10)))
L32: =IF(K32<>"",(IF(H32="","",H32-(C32*COSTOS!$C$6+D32*COSTOS!$C$7+E32*COSTOS!$C$8+F32*COSTOS!$C$9+G32*COSTOS!$C$10)))+K32,IF(H32="","",H32-(C32*COSTOS!$C$6+D32*COSTOS!$C$7+E32*COSTOS!$C$8+F32*COSTOS!$C$9+G32*COSTOS!$C$10)))
L33: =IF(K33<>"",(IF(H33="","",H33-(C33*COSTOS!$C$6+D33*COSTOS!$C$7+E33*COSTOS!$C$8+F33*COSTOS!$C$9+G33*COSTOS!$C$10)))+K33,IF(H33="","",H33-(C33*COSTOS!$C$6+D33*COSTOS!$C$7+E33*COSTOS!$C$8+F33*COSTOS!$C$9+G33*COSTOS!$C$10)))
L34: =IF(K34<>"",(IF(H34="","",H34-(C34*COSTOS!$C$6+D34*COSTOS!$C$7+E34*COSTOS!$C$8+F34*COSTOS!$C$9+G34*COSTOS!$C$10)))+K34,IF(H34="","",H34-(C34*COSTOS!$C$6+D34*COSTOS!$C$7+E34*COSTOS!$C$8+F34*COSTOS!$C$9+G34*COSTOS!$C$10)))
L35: =IF(K35<>"",(IF(H35="","",H35-(C35*COSTOS!$C$6+D35*COSTOS!$C$7+E35*COSTOS!$C$8+F35*COSTOS!$C$9+G35*COSTOS!$C$10)))+K35,IF(H35="","",H35-(C35*COSTOS!$C$6+D35*COSTOS!$C$7+E35*COSTOS!$C$8+F35*COSTOS!$C$9+G35*COSTOS!$C$10)))
L36: =IF(K36<>"",(IF(H36="","",H36-(C36*COSTOS!$C$6+D36*COSTOS!$C$7+E36*COSTOS!$C$8+F36*COSTOS!$C$9+G36*COSTOS!$C$10)))+K36,IF(H36="","",H36-(C36*COSTOS!$C$6+D36*COSTOS!$C$7+E36*COSTOS!$C$8+F36*COSTOS!$C$9+G36*COSTOS!$C$10)))
L37: =IF(K37<>"",(IF(H37="","",H37-(C37*COSTOS!$C$6+D37*COSTOS!$C$7+E37*COSTOS!$C$8+F37*COSTOS!$C$9+G37*COSTOS!$C$10)))+K37,IF(H37="","",H37-(C37*COSTOS!$C$6+D37*COSTOS!$C$7+E37*COSTOS!$C$8+F37*COSTOS!$C$9+G37*COSTOS!$C$10)))
L38: =IF(K38<>"",(IF(H38="","",H38-(C38*COSTOS!$C$6+D38*COSTOS!$C$7+E38*COSTOS!$C$8+F38*COSTOS!$C$9+G38*COSTOS!$C$10)))+K38,IF(H38="","",H38-(C38*COSTOS!$C$6+D38*COSTOS!$C$7+E38*COSTOS!$C$8+F38*COSTOS!$C$9+G38*COSTOS!$C$10)))
L39: =IF(K39<>"",(IF(H39="","",H39-(C39*COSTOS!$C$6+D39*COSTOS!$C$7+E39*COSTOS!$C$8+F39*COSTOS!$C$9+G39*COSTOS!$C$10)))+K39,IF(H39="","",H39-(C39*COSTOS!$C$6+D39*COSTOS!$C$7+E39*COSTOS!$C$8+F39*COSTOS!$C$9+G39*COSTOS!$C$10)))
L40: =IF(K40<>"",(IF(H40="","",H40-(C40*COSTOS!$C$6+D40*COSTOS!$C$7+E40*COSTOS!$C$8+F40*COSTOS!$C$9+G40*COSTOS!$C$10)))+K40,IF(H40="","",H40-(C40*COSTOS!$C$6+D40*COSTOS!$C$7+E40*COSTOS!$C$8+F40*COSTOS!$C$9+G40*COSTOS!$C$10)))
L41: =IF(K41<>"",(IF(H41="","",H41-(C41*COSTOS!$C$6+D41*COSTOS!$C$7+E41*COSTOS!$C$8+F41*COSTOS!$C$9+G41*COSTOS!$C$10)))+K41,IF(H41="","",H41-(C41*COSTOS!$C$6+D41*COSTOS!$C$7+E41*COSTOS!$C$8+F41*COSTOS!$C$9+G41*COSTOS!$C$10)))
... L500: =IF(K500<>"",(IF(H500="","",H500-(C500*COSTOS!$C$6+D500*COSTOS!$C$7+E500*COSTOS!$C$8+F500*COSTOS!$C$9+G500*COSTOS!$C$10)))+K500,IF(H500="","",H500-(C500*COSTOS!$C$6+D500*COSTOS!$C$7+E500*COSTOS!$C$8+F500*COSTOS!$C$9+G500*COSTOS!$C$10)))
A501: TOTALES DEL MES | C501: =IFERROR(SUM(C5:C500),0) | D501: =IFERROR(SUM(D5:D500),0) | E501: =IFERROR(SUM(E5:E500),0) | F501: =IFERROR(SUM(F5:F500),0) | G501: =IFERROR(SUM(G5:G500),0)

Sheet Agosto
A1: VENTAS — AGOSTO 2026
A2: ⚠ El nombre del cliente debe ser EXACTAMENTE igual siempre · La ganancia se calcula con el costo vigente a la fecha
A4: FECHA | B4: CLIENTE / DIRECCIÓN | C4: 10 | D4: 15 | E4: 45 | F4: YERBA | G4: AGUA | H4: VALOR ($) | I4: EFECTIVO ($) | J4: TRANSFER ($) | K4: ENVASE ($) | L4: GANANCIA ($) | N4: RESUMEN AGOSTO
L5: =IF(K5<>"",(IF(H5="","",H5-(C5*COSTOS!$C$6+D5*COSTOS!$C$7+E5*COSTOS!$C$8+F5*COSTOS!$C$9+G5*COSTOS!$C$10)))+K5,IF(H5="","",H5-(C5*COSTOS!$C$6+D5*COSTOS!$C$7+E5*COSTOS!$C$8+F5*COSTOS!$C$9+G5*COSTOS!$C$10))) | N5: TOTAL 10 | O5: =IFERROR(SUM(C5:C700),0)
L6: =IF(K6<>"",(IF(H6="","",H6-(C6*COSTOS!$C$6+D6*COSTOS!$C$7+E6*COSTOS!$C$8+F6*COSTOS!$C$9+G6*COSTOS!$C$10)))+K6,IF(H6="","",H6-(C6*COSTOS!$C$6+D6*COSTOS!$C$7+E6*COSTOS!$C$8+F6*COSTOS!$C$9+G6*COSTOS!$C$10))) | N6: TOTAL 15 | O6: =IFERROR(SUM(D5:D700),0)
L7: =IF(K7<>"",(IF(H7="","",H7-(C7*COSTOS!$C$6+D7*COSTOS!$C$7+E7*COSTOS!$C$8+F7*COSTOS!$C$9+G7*COSTOS!$C$10)))+K7,IF(H7="","",H7-(C7*COSTOS!$C$6+D7*COSTOS!$C$7+E7*COSTOS!$C$8+F7*COSTOS!$C$9+G7*COSTOS!$C$10))) | N7: TOTAL 45 | O7: =IFERROR(SUM(E5:E700),0)
L8: =IF(K8<>"",(IF(H8="","",H8-(C8*COSTOS!$C$6+D8*COSTOS!$C$7+E8*COSTOS!$C$8+F8*COSTOS!$C$9+G8*COSTOS!$C$10)))+K8,IF(H8="","",H8-(C8*COSTOS!$C$6+D8*COSTOS!$C$7+E8*COSTOS!$C$8+F8*COSTOS!$C$9+G8*COSTOS!$C$10))) | N8: TOTAL YERBA | O8: =IFERROR(SUM(F5:F700),0)
L9: =IF(K9<>"",(IF(H9="","",H9-(C9*COSTOS!$C$6+D9*COSTOS!$C$7+E9*COSTOS!$C$8+F9*COSTOS!$C$9+G9*COSTOS!$C$10)))+K9,IF(H9="","",H9-(C9*COSTOS!$C$6+D9*COSTOS!$C$7+E9*COSTOS!$C$8+F9*COSTOS!$C$9+G9*COSTOS!$C$10))) | N9: TOTAL AGUA | O9: =IFERROR(SUM(G5:G700),0)
L10: =IF(K10<>"",(IF(H10="","",H10-(C10*COSTOS!$C$6+D10*COSTOS!$C$7+E10*COSTOS!$C$8+F10*COSTOS!$C$9+G10*COSTOS!$C$10)))+K10,IF(H10="","",H10-(C10*COSTOS!$C$6+D10*COSTOS!$C$7+E10*COSTOS!$C$8+F10*COSTOS!$C$9+G10*COSTOS!$C$10)))
L11: =IF(K11<>"",(IF(H11="","",H11-(C11*COSTOS!$C$6+D11*COSTOS!$C$7+E11*COSTOS!$C$8+F11*COSTOS!$C$9+G11*COSTOS!$C$10)))+K11,IF(H11="","",H11-(C11*COSTOS!$C$6+D11*COSTOS!$C$7+E11*COSTOS!$C$8+F11*COSTOS!$C$9+G11*COSTOS!$C$10))) | N11: FACTURACIÓN | O11: =IFERROR(SUM(H5:H700),0)
L12: =IF(K12<>"",(IF(H12="","",H12-(C12*COSTOS!$C$6+D12*COSTOS!$C$7+E12*COSTOS!$C$8+F12*COSTOS!$C$9+G12*COSTOS!$C$10)))+K12,IF(H12="","",H12-(C12*COSTOS!$C$6+D12*COSTOS!$C$7+E12*COSTOS!$C$8+F12*COSTOS!$C$9+G12*COSTOS!$C$10))) | N12: GANANCIA | O12: =IFERROR(SUM(L5:L700),0)
L13: =IF(K13<>"",(IF(H13="","",H13-(C13*COSTOS!$C$6+D13*COSTOS!$C$7+E13*COSTOS!$C$8+F13*COSTOS!$C$9+G13*COSTOS!$C$10)))+K13,IF(H13="","",H13-(C13*COSTOS!$C$6+D13*COSTOS!$C$7+E13*COSTOS!$C$8+F13*COSTOS!$C$9+G13*COSTOS!$C$10))) | N13: % GANANCIA | O13: =IFERROR(SUM(L5:L700)/SUM(H5:H700),0)
L14: =IF(K14<>"",(IF(H14="","",H14-(C14*COSTOS!$C$6+D14*COSTOS!$C$7+E14*COSTOS!$C$8+F14*COSTOS!$C$9+G14*COSTOS!$C$10)))+K14,IF(H14="","",H14-(C14*COSTOS!$C$6+D14*COSTOS!$C$7+E14*COSTOS!$C$8+F14*COSTOS!$C$9+G14*COSTOS!$C$10)))
L15: =IF(K15<>"",(IF(H15="","",H15-(C15*COSTOS!$C$6+D15*COSTOS!$C$7+E15*COSTOS!$C$8+F15*COSTOS!$C$9+G15*COSTOS!$C$10)))+K15,IF(H15="","",H15-(C15*COSTOS!$C$6+D15*COSTOS!$C$7+E15*COSTOS!$C$8+F15*COSTOS!$C$9+G15*COSTOS!$C$10))) | N15: EFECTIVO | O15: =IFERROR(SUM(I5:I700),0)
L16: =IF(K16<>"",(IF(H16="","",H16-(C16*COSTOS!$C$6+D16*COSTOS!$C$7+E16*COSTOS!$C$8+F16*COSTOS!$C$9+G16*COSTOS!$C$10)))+K16,IF(H16="","",H16-(C16*COSTOS!$C$6+D16*COSTOS!$C$7+E16*COSTOS!$C$8+F16*COSTOS!$C$9+G16*COSTOS!$C$10))) | N16: TRANSFERENCIA | O16: =IFERROR(SUM(J5:J700),0)
L17: =IF(K17<>"",(IF(H17="","",H17-(C17*COSTOS!$C$6+D17*COSTOS!$C$7+E17*COSTOS!$C$8+F17*COSTOS!$C$9+G17*COSTOS!$C$10)))+K17,IF(H17="","",H17-(C17*COSTOS!$C$6+D17*COSTOS!$C$7+E17*COSTOS!$C$8+F17*COSTOS!$C$9+G17*COSTOS!$C$10)))
L18: =IF(K18<>"",(IF(H18="","",H18-(C18*COSTOS!$C$6+D18*COSTOS!$C$7+E18*COSTOS!$C$8+F18*COSTOS!$C$9+G18*COSTOS!$C$10)))+K18,IF(H18="","",H18-(C18*COSTOS!$C$6+D18*COSTOS!$C$7+E18*COSTOS!$C$8+F18*COSTOS!$C$9+G18*COSTOS!$C$10))) | N18: Nº VENTAS | O18: =IFERROR(COUNTA(B5:B700),0)
L19: =IF(K19<>"",(IF(H19="","",H19-(C19*COSTOS!$C$6+D19*COSTOS!$C$7+E19*COSTOS!$C$8+F19*COSTOS!$C$9+G19*COSTOS!$C$10)))+K19,IF(H19="","",H19-(C19*COSTOS!$C$6+D19*COSTOS!$C$7+E19*COSTOS!$C$8+F19*COSTOS!$C$9+G19*COSTOS!$C$10))) | N19: DÍAS DEL MES | O19: 31
L20: =IF(K20<>"",(IF(H20="","",H20-(C20*COSTOS!$C$6+D20*COSTOS!$C$7+E20*COSTOS!$C$8+F20*COSTOS!$C$9+G20*COSTOS!$C$10)))+K20,IF(H20="","",H20-(C20*COSTOS!$C$6+D20*COSTOS!$C$7+E20*COSTOS!$C$8+F20*COSTOS!$C$9+G20*COSTOS!$C$10)))
L21: =IF(K21<>"",(IF(H21="","",H21-(C21*COSTOS!$C$6+D21*COSTOS!$C$7+E21*COSTOS!$C$8+F21*COSTOS!$C$9+G21*COSTOS!$C$10)))+K21,IF(H21="","",H21-(C21*COSTOS!$C$6+D21*COSTOS!$C$7+E21*COSTOS!$C$8+F21*COSTOS!$C$9+G21*COSTOS!$C$10))) | N21: OBJETIVO ($)
L22: =IF(K22<>"",(IF(H22="","",H22-(C22*COSTOS!$C$6+D22*COSTOS!$C$7+E22*COSTOS!$C$8+F22*COSTOS!$C$9+G22*COSTOS!$C$10)))+K22,IF(H22="","",H22-(C22*COSTOS!$C$6+D22*COSTOS!$C$7+E22*COSTOS!$C$8+F22*COSTOS!$C$9+G22*COSTOS!$C$10))) | N22: DIFERENCIA | O22: =IFERROR(SUM(L5:L700)-N21,0)
L23: =IF(K23<>"",(IF(H23="","",H23-(C23*COSTOS!$C$6+D23*COSTOS!$C$7+E23*COSTOS!$C$8+F23*COSTOS!$C$9+G23*COSTOS!$C$10)))+K23,IF(H23="","",H23-(C23*COSTOS!$C$6+D23*COSTOS!$C$7+E23*COSTOS!$C$8+F23*COSTOS!$C$9+G23*COSTOS!$C$10)))
L24: =IF(K24<>"",(IF(H24="","",H24-(C24*COSTOS!$C$6+D24*COSTOS!$C$7+E24*COSTOS!$C$8+F24*COSTOS!$C$9+G24*COSTOS!$C$10)))+K24,IF(H24="","",H24-(C24*COSTOS!$C$6+D24*COSTOS!$C$7+E24*COSTOS!$C$8+F24*COSTOS!$C$9+G24*COSTOS!$C$10)))
L25: =IF(K25<>"",(IF(H25="","",H25-(C25*COSTOS!$C$6+D25*COSTOS!$C$7+E25*COSTOS!$C$8+F25*COSTOS!$C$9+G25*COSTOS!$C$10)))+K25,IF(H25="","",H25-(C25*COSTOS!$C$6+D25*COSTOS!$C$7+E25*COSTOS!$C$8+F25*COSTOS!$C$9+G25*COSTOS!$C$10)))
L26: =IF(K26<>"",(IF(H26="","",H26-(C26*COSTOS!$C$6+D26*COSTOS!$C$7+E26*COSTOS!$C$8+F26*COSTOS!$C$9+G26*COSTOS!$C$10)))+K26,IF(H26="","",H26-(C26*COSTOS!$C$6+D26*COSTOS!$C$7+E26*COSTOS!$C$8+F26*COSTOS!$C$9+G26*COSTOS!$C$10)))
L27: =IF(K27<>"",(IF(H27="","",H27-(C27*COSTOS!$C$6+D27*COSTOS!$C$7+E27*COSTOS!$C$8+F27*COSTOS!$C$9+G27*COSTOS!$C$10)))+K27,IF(H27="","",H27-(C27*COSTOS!$C$6+D27*COSTOS!$C$7+E27*COSTOS!$C$8+F27*COSTOS!$C$9+G27*COSTOS!$C$10)))
L28: =IF(K28<>"",(IF(H28="","",H28-(C28*COSTOS!$C$6+D28*COSTOS!$C$7+E28*COSTOS!$C$8+F28*COSTOS!$C$9+G28*COSTOS!$C$10)))+K28,IF(H28="","",H28-(C28*COSTOS!$C$6+D28*COSTOS!$C$7+E28*COSTOS!$C$8+F28*COSTOS!$C$9+G28*COSTOS!$C$10)))
L29: =IF(K29<>"",(IF(H29="","",H29-(C29*COSTOS!$C$6+D29*COSTOS!$C$7+E29*COSTOS!$C$8+F29*COSTOS!$C$9+G29*COSTOS!$C$10)))+K29,IF(H29="","",H29-(C29*COSTOS!$C$6+D29*COSTOS!$C$7+E29*COSTOS!$C$8+F29*COSTOS!$C$9+G29*COSTOS!$C$10))) | O29: =IFERROR(SUM(L5:L700)/COUNTA(B5:B700),0)
L30: =IF(K30<>"",(IF(H30="","",H30-(C30*COSTOS!$C$6+D30*COSTOS!$C$7+E30*COSTOS!$C$8+F30*COSTOS!$C$9+G30*COSTOS!$C$10)))+K30,IF(H30="","",H30-(C30*COSTOS!$C$6+D30*COSTOS!$C$7+E30*COSTOS!$C$8+F30*COSTOS!$C$9+G30*COSTOS!$C$10)))
L31: =IF(K31<>"",(IF(H31="","",H31-(C31*COSTOS!$C$6+D31*COSTOS!$C$7+E31*COSTOS!$C$8+F31*COSTOS!$C$9+G31*COSTOS!$C$10)))+K31,IF(H31="","",H31-(C31*COSTOS!$C$6+D31*COSTOS!$C$7+E31*COSTOS!$C$8+F31*COSTOS!$C$9+G31*COSTOS!$C$10)))
L32: =IF(K32<>"",(IF(H32="","",H32-(C32*COSTOS!$C$6+D32*COSTOS!$C$7+E32*COSTOS!$C$8+F32*COSTOS!$C$9+G32*COSTOS!$C$10)))+K32,IF(H32="","",H32-(C32*COSTOS!$C$6+D32*COSTOS!$C$7+E32*COSTOS!$C$8+F32*COSTOS!$C$9+G32*COSTOS!$C$10)))
L33: =IF(K33<>"",(IF(H33="","",H33-(C33*COSTOS!$C$6+D33*COSTOS!$C$7+E33*COSTOS!$C$8+F33*COSTOS!$C$9+G33*COSTOS!$C$10)))+K33,IF(H33="","",H33-(C33*COSTOS!$C$6+D33*COSTOS!$C$7+E33*COSTOS!$C$8+F33*COSTOS!$C$9+G33*COSTOS!$C$10)))
L34: =IF(K34<>"",(IF(H34="","",H34-(C34*COSTOS!$C$6+D34*COSTOS!$C$7+E34*COSTOS!$C$8+F34*COSTOS!$C$9+G34*COSTOS!$C$10)))+K34,IF(H34="","",H34-(C34*COSTOS!$C$6+D34*COSTOS!$C$7+E34*COSTOS!$C$8+F34*COSTOS!$C$9+G34*COSTOS!$C$10)))
L35: =IF(K35<>"",(IF(H35="","",H35-(C35*COSTOS!$C$6+D35*COSTOS!$C$7+E35*COSTOS!$C$8+F35*COSTOS!$C$9+G35*COSTOS!$C$10)))+K35,IF(H35="","",H35-(C35*COSTOS!$C$6+D35*COSTOS!$C$7+E35*COSTOS!$C$8+F35*COSTOS!$C$9+G35*COSTOS!$C$10)))
L36: =IF(K36<>"",(IF(H36="","",H36-(C36*COSTOS!$C$6+D36*COSTOS!$C$7+E36*COSTOS!$C$8+F36*COSTOS!$C$9+G36*COSTOS!$C$10)))+K36,IF(H36="","",H36-(C36*COSTOS!$C$6+D36*COSTOS!$C$7+E36*COSTOS!$C$8+F36*COSTOS!$C$9+G36*COSTOS!$C$10)))
L37: =IF(K37<>"",(IF(H37="","",H37-(C37*COSTOS!$C$6+D37*COSTOS!$C$7+E37*COSTOS!$C$8+F37*COSTOS!$C$9+G37*COSTOS!$C$10)))+K37,IF(H37="","",H37-(C37*COSTOS!$C$6+D37*COSTOS!$C$7+E37*COSTOS!$C$8+F37*COSTOS!$C$9+G37*COSTOS!$C$10)))
L38: =IF(K38<>"",(IF(H38="","",H38-(C38*COSTOS!$C$6+D38*COSTOS!$C$7+E38*COSTOS!$C$8+F38*COSTOS!$C$9+G38*COSTOS!$C$10)))+K38,IF(H38="","",H38-(C38*COSTOS!$C$6+D38*COSTOS!$C$7+E38*COSTOS!$C$8+F38*COSTOS!$C$9+G38*COSTOS!$C$10)))
L39: =IF(K39<>"",(IF(H39="","",H39-(C39*COSTOS!$C$6+D39*COSTOS!$C$7+E39*COSTOS!$C$8+F39*COSTOS!$C$9+G39*COSTOS!$C$10)))+K39,IF(H39="","",H39-(C39*COSTOS!$C$6+D39*COSTOS!$C$7+E39*COSTOS!$C$8+F39*COSTOS!$C$9+G39*COSTOS!$C$10)))
L40: =IF(K40<>"",(IF(H40="","",H40-(C40*COSTOS!$C$6+D40*COSTOS!$C$7+E40*COSTOS!$C$8+F40*COSTOS!$C$9+G40*COSTOS!$C$10)))+K40,IF(H40="","",H40-(C40*COSTOS!$C$6+D40*COSTOS!$C$7+E40*COSTOS!$C$8+F40*COSTOS!$C$9+G40*COSTOS!$C$10)))
L41: =IF(K41<>"",(IF(H41="","",H41-(C41*COSTOS!$C$6+D41*COSTOS!$C$7+E41*COSTOS!$C$8+F41*COSTOS!$C$9+G41*COSTOS!$C$10)))+K41,IF(H41="","",H41-(C41*COSTOS!$C$6+D41*COSTOS!$C$7+E41*COSTOS!$C$8+F41*COSTOS!$C$9+G41*COSTOS!$C$10)))
... L500: =IF(K500<>"",(IF(H500="","",H500-(C500*COSTOS!$C$6+D500*COSTOS!$C$7+E500*COSTOS!$C$8+F500*COSTOS!$C$9+G500*COSTOS!$C$10)))+K500,IF(H500="","",H500-(C500*COSTOS!$C$6+D500*COSTOS!$C$7+E500*COSTOS!$C$8+F500*COSTOS!$C$9+G500*COSTOS!$C$10)))
A501: TOTALES DEL MES | C501: =IFERROR(SUM(C5:C500),0) | D501: =IFERROR(SUM(D5:D500),0) | E501: =IFERROR(SUM(E5:E500),0) | F501: =IFERROR(SUM(F5:F500),0) | G501: =IFERROR(SUM(G5:G500),0)

Sheet Septiembre
A1: VENTAS — SEPTIEMBRE 2026
A2: ⚠ El nombre del cliente debe ser EXACTAMENTE igual siempre · La ganancia se calcula con el costo vigente a la fecha
A4: FECHA | B4: CLIENTE / DIRECCIÓN | C4: 10 | D4: 15 | E4: 45 | F4: YERBA | G4: AGUA | H4: VALOR ($) | I4: EFECTIVO ($) | J4: TRANSFER ($) | K4: ENVASE ($) | L4: GANANCIA ($) | N4: RESUMEN SEPTIEMBRE
L5: =IF(K5<>"",(IF(H5="","",H5-(C5*COSTOS!$C$6+D5*COSTOS!$C$7+E5*COSTOS!$C$8+F5*COSTOS!$C$9+G5*COSTOS!$C$10)))+K5,IF(H5="","",H5-(C5*COSTOS!$C$6+D5*COSTOS!$C$7+E5*COSTOS!$C$8+F5*COSTOS!$C$9+G5*COSTOS!$C$10))) | N5: TOTAL 10 | O5: =IFERROR(SUM(C5:C700),0)
L6: =IF(K6<>"",(IF(H6="","",H6-(C6*COSTOS!$C$6+D6*COSTOS!$C$7+E6*COSTOS!$C$8+F6*COSTOS!$C$9+G6*COSTOS!$C$10)))+K6,IF(H6="","",H6-(C6*COSTOS!$C$6+D6*COSTOS!$C$7+E6*COSTOS!$C$8+F6*COSTOS!$C$9+G6*COSTOS!$C$10))) | N6: TOTAL 15 | O6: =IFERROR(SUM(D5:D700),0)
L7: =IF(K7<>"",(IF(H7="","",H7-(C7*COSTOS!$C$6+D7*COSTOS!$C$7+E7*COSTOS!$C$8+F7*COSTOS!$C$9+G7*COSTOS!$C$10)))+K7,IF(H7="","",H7-(C7*COSTOS!$C$6+D7*COSTOS!$C$7+E7*COSTOS!$C$8+F7*COSTOS!$C$9+G7*COSTOS!$C$10))) | N7: TOTAL 45 | O7: =IFERROR(SUM(E5:E700),0)
L8: =IF(K8<>"",(IF(H8="","",H8-(C8*COSTOS!$C$6+D8*COSTOS!$C$7+E8*COSTOS!$C$8+F8*COSTOS!$C$9+G8*COSTOS!$C$10)))+K8,IF(H8="","",H8-(C8*COSTOS!$C$6+D8*COSTOS!$C$7+E8*COSTOS!$C$8+F8*COSTOS!$C$9+G8*COSTOS!$C$10))) | N8: TOTAL YERBA | O8: =IFERROR(SUM(F5:F700),0)
L9: =IF(K9<>"",(IF(H9="","",H9-(C9*COSTOS!$C$6+D9*COSTOS!$C$7+E9*COSTOS!$C$8+F9*COSTOS!$C$9+G9*COSTOS!$C$10)))+K9,IF(H9="","",H9-(C9*COSTOS!$C$6+D9*COSTOS!$C$7+E9*COSTOS!$C$8+F9*COSTOS!$C$9+G9*COSTOS!$C$10))) | N9: TOTAL AGUA | O9: =IFERROR(SUM(G5:G700),0)
L10: =IF(K10<>"",(IF(H10="","",H10-(C10*COSTOS!$C$6+D10*COSTOS!$C$7+E10*COSTOS!$C$8+F10*COSTOS!$C$9+G10*COSTOS!$C$10)))+K10,IF(H10="","",H10-(C10*COSTOS!$C$6+D10*COSTOS!$C$7+E10*COSTOS!$C$8+F10*COSTOS!$C$9+G10*COSTOS!$C$10)))
L11: =IF(K11<>"",(IF(H11="","",H11-(C11*COSTOS!$C$6+D11*COSTOS!$C$7+E11*COSTOS!$C$8+F11*COSTOS!$C$9+G11*COSTOS!$C$10)))+K11,IF(H11="","",H11-(C11*COSTOS!$C$6+D11*COSTOS!$C$7+E11*COSTOS!$C$8+F11*COSTOS!$C$9+G11*COSTOS!$C$10))) | N11: FACTURACIÓN | O11: =IFERROR(SUM(H5:H700),0)
L12: =IF(K12<>"",(IF(H12="","",H12-(C12*COSTOS!$C$6+D12*COSTOS!$C$7+E12*COSTOS!$C$8+F12*COSTOS!$C$9+G12*COSTOS!$C$10)))+K12,IF(H12="","",H12-(C12*COSTOS!$C$6+D12*COSTOS!$C$7+E12*COSTOS!$C$8+F12*COSTOS!$C$9+G12*COSTOS!$C$10))) | N12: GANANCIA | O12: =IFERROR(SUM(L5:L700),0)
L13: =IF(K13<>"",(IF(H13="","",H13-(C13*COSTOS!$C$6+D13*COSTOS!$C$7+E13*COSTOS!$C$8+F13*COSTOS!$C$9+G13*COSTOS!$C$10)))+K13,IF(H13="","",H13-(C13*COSTOS!$C$6+D13*COSTOS!$C$7+E13*COSTOS!$C$8+F13*COSTOS!$C$9+G13*COSTOS!$C$10))) | N13: % GANANCIA | O13: =IFERROR(SUM(L5:L700)/SUM(H5:H700),0)
L14: =IF(K14<>"",(IF(H14="","",H14-(C14*COSTOS!$C$6+D14*COSTOS!$C$7+E14*COSTOS!$C$8+F14*COSTOS!$C$9+G14*COSTOS!$C$10)))+K14,IF(H14="","",H14-(C14*COSTOS!$C$6+D14*COSTOS!$C$7+E14*COSTOS!$C$8+F14*COSTOS!$C$9+G14*COSTOS!$C$10)))
L15: =IF(K15<>"",(IF(H15="","",H15-(C15*COSTOS!$C$6+D15*COSTOS!$C$7+E15*COSTOS!$C$8+F15*COSTOS!$C$9+G15*COSTOS!$C$10)))+K15,IF(H15="","",H15-(C15*COSTOS!$C$6+D15*COSTOS!$C$7+E15*COSTOS!$C$8+F15*COSTOS!$C$9+G15*COSTOS!$C$10))) | N15: EFECTIVO | O15: =IFERROR(SUM(I5:I700),0)
L16: =IF(K16<>"",(IF(H16="","",H16-(C16*COSTOS!$C$6+D16*COSTOS!$C$7+E16*COSTOS!$C$8+F16*COSTOS!$C$9+G16*COSTOS!$C$10)))+K16,IF(H16="","",H16-(C16*COSTOS!$C$6+D16*COSTOS!$C$7+E16*COSTOS!$C$8+F16*COSTOS!$C$9+G16*COSTOS!$C$10))) | N16: TRANSFERENCIA | O16: =IFERROR(SUM(J5:J700),0)
L17: =IF(K17<>"",(IF(H17="","",H17-(C17*COSTOS!$C$6+D17*COSTOS!$C$7+E17*COSTOS!$C$8+F17*COSTOS!$C$9+G17*COSTOS!$C$10)))+K17,IF(H17="","",H17-(C17*COSTOS!$C$6+D17*COSTOS!$C$7+E17*COSTOS!$C$8+F17*COSTOS!$C$9+G17*COSTOS!$C$10)))
L18: =IF(K18<>"",(IF(H18="","",H18-(C18*COSTOS!$C$6+D18*COSTOS!$C$7+E18*COSTOS!$C$8+F18*COSTOS!$C$9+G18*COSTOS!$C$10)))+K18,IF(H18="","",H18-(C18*COSTOS!$C$6+D18*COSTOS!$C$7+E18*COSTOS!$C$8+F18*COSTOS!$C$9+G18*COSTOS!$C$10))) | N18: Nº VENTAS | O18: =IFERROR(COUNTA(B5:B700),0)
L19: =IF(K19<>"",(IF(H19="","",H19-(C19*COSTOS!$C$6+D19*COSTOS!$C$7+E19*COSTOS!$C$8+F19*COSTOS!$C$9+G19*COSTOS!$C$10)))+K19,IF(H19="","",H19-(C19*COSTOS!$C$6+D19*COSTOS!$C$7+E19*COSTOS!$C$8+F19*COSTOS!$C$9+G19*COSTOS!$C$10))) | N19: DÍAS DEL MES | O19: 30
L20: =IF(K20<>"",(IF(H20="","",H20-(C20*COSTOS!$C$6+D20*COSTOS!$C$7+E20*COSTOS!$C$8+F20*COSTOS!$C$9+G20*COSTOS!$C$10)))+K20,IF(H20="","",H20-(C20*COSTOS!$C$6+D20*COSTOS!$C$7+E20*COSTOS!$C$8+F20*COSTOS!$C$9+G20*COSTOS!$C$10)))
L21: =IF(K21<>"",(IF(H21="","",H21-(C21*COSTOS!$C$6+D21*COSTOS!$C$7+E21*COSTOS!$C$8+F21*COSTOS!$C$9+G21*COSTOS!$C$10)))+K21,IF(H21="","",H21-(C21*COSTOS!$C$6+D21*COSTOS!$C$7+E21*COSTOS!$C$8+F21*COSTOS!$C$9+G21*COSTOS!$C$10))) | N21: OBJETIVO ($)
L22: =IF(K22<>"",(IF(H22="","",H22-(C22*COSTOS!$C$6+D22*COSTOS!$C$7+E22*COSTOS!$C$8+F22*COSTOS!$C$9+G22*COSTOS!$C$10)))+K22,IF(H22="","",H22-(C22*COSTOS!$C$6+D22*COSTOS!$C$7+E22*COSTOS!$C$8+F22*COSTOS!$C$9+G22*COSTOS!$C$10))) | N22: DIFERENCIA | O22: =IFERROR(SUM(L5:L700)-N21,0)
L23: =IF(K23<>"",(IF(H23="","",H23-(C23*COSTOS!$C$6+D23*COSTOS!$C$7+E23*COSTOS!$C$8+F23*COSTOS!$C$9+G23*COSTOS!$C$10)))+K23,IF(H23="","",H23-(C23*COSTOS!$C$6+D23*COSTOS!$C$7+E23*COSTOS!$C$8+F23*COSTOS!$C$9+G23*COSTOS!$C$10)))
L24: =IF(K24<>"",(IF(H24="","",H24-(C24*COSTOS!$C$6+D24*COSTOS!$C$7+E24*COSTOS!$C$8+F24*COSTOS!$C$9+G24*COSTOS!$C$10)))+K24,IF(H24="","",H24-(C24*COSTOS!$C$6+D24*COSTOS!$C$7+E24*COSTOS!$C$8+F24*COSTOS!$C$9+G24*COSTOS!$C$10)))
L25: =IF(K25<>"",(IF(H25="","",H25-(C25*COSTOS!$C$6+D25*COSTOS!$C$7+E25*COSTOS!$C$8+F25*COSTOS!$C$9+G25*COSTOS!$C$10)))+K25,IF(H25="","",H25-(C25*COSTOS!$C$6+D25*COSTOS!$C$7+E25*COSTOS!$C$8+F25*COSTOS!$C$9+G25*COSTOS!$C$10)))
L26: =IF(K26<>"",(IF(H26="","",H26-(C26*COSTOS!$C$6+D26*COSTOS!$C$7+E26*COSTOS!$C$8+F26*COSTOS!$C$9+G26*COSTOS!$C$10)))+K26,IF(H26="","",H26-(C26*COSTOS!$C$6+D26*COSTOS!$C$7+E26*COSTOS!$C$8+F26*COSTOS!$C$9+G26*COSTOS!$C$10)))
L27: =IF(K27<>"",(IF(H27="","",H27-(C27*COSTOS!$C$6+D27*COSTOS!$C$7+E27*COSTOS!$C$8+F27*COSTOS!$C$9+G27*COSTOS!$C$10)))+K27,IF(H27="","",H27-(C27*COSTOS!$C$6+D27*COSTOS!$C$7+E27*COSTOS!$C$8+F27*COSTOS!$C$9+G27*COSTOS!$C$10)))
L28: =IF(K28<>"",(IF(H28="","",H28-(C28*COSTOS!$C$6+D28*COSTOS!$C$7+E28*COSTOS!$C$8+F28*COSTOS!$C$9+G28*COSTOS!$C$10)))+K28,IF(H28="","",H28-(C28*COSTOS!$C$6+D28*COSTOS!$C$7+E28*COSTOS!$C$8+F28*COSTOS!$C$9+G28*COSTOS!$C$10)))
L29: =IF(K29<>"",(IF(H29="","",H29-(C29*COSTOS!$C$6+D29*COSTOS!$C$7+E29*COSTOS!$C$8+F29*COSTOS!$C$9+G29*COSTOS!$C$10)))+K29,IF(H29="","",H29-(C29*COSTOS!$C$6+D29*COSTOS!$C$7+E29*COSTOS!$C$8+F29*COSTOS!$C$9+G29*COSTOS!$C$10))) | O29: =IFERROR(SUM(L5:L700)/COUNTA(B5:B700),0)
L30: =IF(K30<>"",(IF(H30="","",H30-(C30*COSTOS!$C$6+D30*COSTOS!$C$7+E30*COSTOS!$C$8+F30*COSTOS!$C$9+G30*COSTOS!$C$10)))+K30,IF(H30="","",H30-(C30*COSTOS!$C$6+D30*COSTOS!$C$7+E30*COSTOS!$C$8+F30*COSTOS!$C$9+G30*COSTOS!$C$10)))
L31: =IF(K31<>"",(IF(H31="","",H31-(C31*COSTOS!$C$6+D31*COSTOS!$C$7+E31*COSTOS!$C$8+F31*COSTOS!$C$9+G31*COSTOS!$C$10)))+K31,IF(H31="","",H31-(C31*COSTOS!$C$6+D31*COSTOS!$C$7+E31*COSTOS!$C$8+F31*COSTOS!$C$9+G31*COSTOS!$C$10)))
L32: =IF(K32<>"",(IF(H32="","",H32-(C32*COSTOS!$C$6+D32*COSTOS!$C$7+E32*COSTOS!$C$8+F32*COSTOS!$C$9+G32*COSTOS!$C$10)))+K32,IF(H32="","",H32-(C32*COSTOS!$C$6+D32*COSTOS!$C$7+E32*COSTOS!$C$8+F32*COSTOS!$C$9+G32*COSTOS!$C$10)))
L33: =IF(K33<>"",(IF(H33="","",H33-(C33*COSTOS!$C$6+D33*COSTOS!$C$7+E33*COSTOS!$C$8+F33*COSTOS!$C$9+G33*COSTOS!$C$10)))+K33,IF(H33="","",H33-(C33*COSTOS!$C$6+D33*COSTOS!$C$7+E33*COSTOS!$C$8+F33*COSTOS!$C$9+G33*COSTOS!$C$10)))
L34: =IF(K34<>"",(IF(H34="","",H34-(C34*COSTOS!$C$6+D34*COSTOS!$C$7+E34*COSTOS!$C$8+F34*COSTOS!$C$9+G34*COSTOS!$C$10)))+K34,IF(H34="","",H34-(C34*COSTOS!$C$6+D34*COSTOS!$C$7+E34*COSTOS!$C$8+F34*COSTOS!$C$9+G34*COSTOS!$C$10)))
L35: =IF(K35<>"",(IF(H35="","",H35-(C35*COSTOS!$C$6+D35*COSTOS!$C$7+E35*COSTOS!$C$8+F35*COSTOS!$C$9+G35*COSTOS!$C$10)))+K35,IF(H35="","",H35-(C35*COSTOS!$C$6+D35*COSTOS!$C$7+E35*COSTOS!$C$8+F35*COSTOS!$C$9+G35*COSTOS!$C$10)))
L36: =IF(K36<>"",(IF(H36="","",H36-(C36*COSTOS!$C$6+D36*COSTOS!$C$7+E36*COSTOS!$C$8+F36*COSTOS!$C$9+G36*COSTOS!$C$10)))+K36,IF(H36="","",H36-(C36*COSTOS!$C$6+D36*COSTOS!$C$7+E36*COSTOS!$C$8+F36*COSTOS!$C$9+G36*COSTOS!$C$10)))
L37: =IF(K37<>"",(IF(H37="","",H37-(C37*COSTOS!$C$6+D37*COSTOS!$C$7+E37*COSTOS!$C$8+F37*COSTOS!$C$9+G37*COSTOS!$C$10)))+K37,IF(H37="","",H37-(C37*COSTOS!$C$6+D37*COSTOS!$C$7+E37*COSTOS!$C$8+F37*COSTOS!$C$9+G37*COSTOS!$C$10)))
L38: =IF(K38<>"",(IF(H38="","",H38-(C38*COSTOS!$C$6+D38*COSTOS!$C$7+E38*COSTOS!$C$8+F38*COSTOS!$C$9+G38*COSTOS!$C$10)))+K38,IF(H38="","",H38-(C38*COSTOS!$C$6+D38*COSTOS!$C$7+E38*COSTOS!$C$8+F38*COSTOS!$C$9+G38*COSTOS!$C$10)))
L39: =IF(K39<>"",(IF(H39="","",H39-(C39*COSTOS!$C$6+D39*COSTOS!$C$7+E39*COSTOS!$C$8+F39*COSTOS!$C$9+G39*COSTOS!$C$10)))+K39,IF(H39="","",H39-(C39*COSTOS!$C$6+D39*COSTOS!$C$7+E39*COSTOS!$C$8+F39*COSTOS!$C$9+G39*COSTOS!$C$10)))
L40: =IF(K40<>"",(IF(H40="","",H40-(C40*COSTOS!$C$6+D40*COSTOS!$C$7+E40*COSTOS!$C$8+F40*COSTOS!$C$9+G40*COSTOS!$C$10)))+K40,IF(H40="","",H40-(C40*COSTOS!$C$6+D40*COSTOS!$C$7+E40*COSTOS!$C$8+F40*COSTOS!$C$9+G40*COSTOS!$C$10)))
L41: =IF(K41<>"",(IF(H41="","",H41-(C41*COSTOS!$C$6+D41*COSTOS!$C$7+E41*COSTOS!$C$8+F41*COSTOS!$C$9+G41*COSTOS!$C$10)))+K41,IF(H41="","",H41-(C41*COSTOS!$C$6+D41*COSTOS!$C$7+E41*COSTOS!$C$8+F41*COSTOS!$C$9+G41*COSTOS!$C$10)))
... L500: =IF(K500<>"",(IF(H500="","",H500-(C500*COSTOS!$C$6+D500*COSTOS!$C$7+E500*COSTOS!$C$8+F500*COSTOS!$C$9+G500*COSTOS!$C$10)))+K500,IF(H500="","",H500-(C500*COSTOS!$C$6+D500*COSTOS!$C$7+E500*COSTOS!$C$8+F500*COSTOS!$C$9+G500*COSTOS!$C$10)))
A501: TOTALES DEL MES | C501: =IFERROR(SUM(C5:C500),0) | D501: =IFERROR(SUM(D5:D500),0) | E501: =IFERROR(SUM(E5:E500),0) | F501: =IFERROR(SUM(F5:F500),0) | G501: =IFERROR(SUM(G5:G500),0)

Sheet Octubre
A1: VENTAS — OCTUBRE 2026
A2: ⚠ El nombre del cliente debe ser EXACTAMENTE igual siempre · La ganancia se calcula con el costo vigente a la fecha
A4: FECHA | B4: CLIENTE / DIRECCIÓN | C4: 10 | D4: 15 | E4: 45 | F4: YERBA | G4: AGUA | H4: VALOR ($) | I4: EFECTIVO ($) | J4: TRANSFER ($) | K4: ENVASE ($) | L4: GANANCIA ($) | N4: RESUMEN OCTUBRE
L5: =IF(K5<>"",(IF(H5="","",H5-(C5*COSTOS!$C$6+D5*COSTOS!$C$7+E5*COSTOS!$C$8+F5*COSTOS!$C$9+G5*COSTOS!$C$10)))+K5,IF(H5="","",H5-(C5*COSTOS!$C$6+D5*COSTOS!$C$7+E5*COSTOS!$C$8+F5*COSTOS!$C$9+G5*COSTOS!$C$10))) | N5: TOTAL 10 | O5: =IFERROR(SUM(C5:C700),0)
L6: =IF(K6<>"",(IF(H6="","",H6-(C6*COSTOS!$C$6+D6*COSTOS!$C$7+E6*COSTOS!$C$8+F6*COSTOS!$C$9+G6*COSTOS!$C$10)))+K6,IF(H6="","",H6-(C6*COSTOS!$C$6+D6*COSTOS!$C$7+E6*COSTOS!$C$8+F6*COSTOS!$C$9+G6*COSTOS!$C$10))) | N6: TOTAL 15 | O6: =IFERROR(SUM(D5:D700),0)
L7: =IF(K7<>"",(IF(H7="","",H7-(C7*COSTOS!$C$6+D7*COSTOS!$C$7+E7*COSTOS!$C$8+F7*COSTOS!$C$9+G7*COSTOS!$C$10)))+K7,IF(H7="","",H7-(C7*COSTOS!$C$6+D7*COSTOS!$C$7+E7*COSTOS!$C$8+F7*COSTOS!$C$9+G7*COSTOS!$C$10))) | N7: TOTAL 45 | O7: =IFERROR(SUM(E5:E700),0)
L8: =IF(K8<>"",(IF(H8="","",H8-(C8*COSTOS!$C$6+D8*COSTOS!$C$7+E8*COSTOS!$C$8+F8*COSTOS!$C$9+G8*COSTOS!$C$10)))+K8,IF(H8="","",H8-(C8*COSTOS!$C$6+D8*COSTOS!$C$7+E8*COSTOS!$C$8+F8*COSTOS!$C$9+G8*COSTOS!$C$10))) | N8: TOTAL YERBA | O8: =IFERROR(SUM(F5:F700),0)
L9: =IF(K9<>"",(IF(H9="","",H9-(C9*COSTOS!$C$6+D9*COSTOS!$C$7+E9*COSTOS!$C$8+F9*COSTOS!$C$9+G9*COSTOS!$C$10)))+K9,IF(H9="","",H9-(C9*COSTOS!$C$6+D9*COSTOS!$C$7+E9*COSTOS!$C$8+F9*COSTOS!$C$9+G9*COSTOS!$C$10))) | N9: TOTAL AGUA | O9: =IFERROR(SUM(G5:G700),0)
L10: =IF(K10<>"",(IF(H10="","",H10-(C10*COSTOS!$C$6+D10*COSTOS!$C$7+E10*COSTOS!$C$8+F10*COSTOS!$C$9+G10*COSTOS!$C$10)))+K10,IF(H10="","",H10-(C10*COSTOS!$C$6+D10*COSTOS!$C$7+E10*COSTOS!$C$8+F10*COSTOS!$C$9+G10*COSTOS!$C$10)))
L11: =IF(K11<>"",(IF(H11="","",H11-(C11*COSTOS!$C$6+D11*COSTOS!$C$7+E11*COSTOS!$C$8+F11*COSTOS!$C$9+G11*COSTOS!$C$10)))+K11,IF(H11="","",H11-(C11*COSTOS!$C$6+D11*COSTOS!$C$7+E11*COSTOS!$C$8+F11*COSTOS!$C$9+G11*COSTOS!$C$10))) | N11: FACTURACIÓN | O11: =IFERROR(SUM(H5:H700),0)
L12: =IF(K12<>"",(IF(H12="","",H12-(C12*COSTOS!$C$6+D12*COSTOS!$C$7+E12*COSTOS!$C$8+F12*COSTOS!$C$9+G12*COSTOS!$C$10)))+K12,IF(H12="","",H12-(C12*COSTOS!$C$6+D12*COSTOS!$C$7+E12*COSTOS!$C$8+F12*COSTOS!$C$9+G12*COSTOS!$C$10))) | N12: GANANCIA | O12: =IFERROR(SUM(L5:L700),0)
L13: =IF(K13<>"",(IF(H13="","",H13-(C13*COSTOS!$C$6+D13*COSTOS!$C$7+E13*COSTOS!$C$8+F13*COSTOS!$C$9+G13*COSTOS!$C$10)))+K13,IF(H13="","",H13-(C13*COSTOS!$C$6+D13*COSTOS!$C$7+E13*COSTOS!$C$8+F13*COSTOS!$C$9+G13*COSTOS!$C$10))) | N13: % GANANCIA | O13: =IFERROR(SUM(L5:L700)/SUM(H5:H700),0)
L14: =IF(K14<>"",(IF(H14="","",H14-(C14*COSTOS!$C$6+D14*COSTOS!$C$7+E14*COSTOS!$C$8+F14*COSTOS!$C$9+G14*COSTOS!$C$10)))+K14,IF(H14="","",H14-(C14*COSTOS!$C$6+D14*COSTOS!$C$7+E14*COSTOS!$C$8+F14*COSTOS!$C$9+G14*COSTOS!$C$10)))
L15: =IF(K15<>"",(IF(H15="","",H15-(C15*COSTOS!$C$6+D15*COSTOS!$C$7+E15*COSTOS!$C$8+F15*COSTOS!$C$9+G15*COSTOS!$C$10)))+K15,IF(H15="","",H15-(C15*COSTOS!$C$6+D15*COSTOS!$C$7+E15*COSTOS!$C$8+F15*COSTOS!$C$9+G15*COSTOS!$C$10))) | N15: EFECTIVO | O15: =IFERROR(SUM(I5:I700),0)
L16: =IF(K16<>"",(IF(H16="","",H16-(C16*COSTOS!$C$6+D16*COSTOS!$C$7+E16*COSTOS!$C$8+F16*COSTOS!$C$9+G16*COSTOS!$C$10)))+K16,IF(H16="","",H16-(C16*COSTOS!$C$6+D16*COSTOS!$C$7+E16*COSTOS!$C$8+F16*COSTOS!$C$9+G16*COSTOS!$C$10))) | N16: TRANSFERENCIA | O16: =IFERROR(SUM(J5:J700),0)
L17: =IF(K17<>"",(IF(H17="","",H17-(C17*COSTOS!$C$6+D17*COSTOS!$C$7+E17*COSTOS!$C$8+F17*COSTOS!$C$9+G17*COSTOS!$C$10)))+K17,IF(H17="","",H17-(C17*COSTOS!$C$6+D17*COSTOS!$C$7+E17*COSTOS!$C$8+F17*COSTOS!$C$9+G17*COSTOS!$C$10)))
L18: =IF(K18<>"",(IF(H18="","",H18-(C18*COSTOS!$C$6+D18*COSTOS!$C$7+E18*COSTOS!$C$8+F18*COSTOS!$C$9+G18*COSTOS!$C$10)))+K18,IF(H18="","",H18-(C18*COSTOS!$C$6+D18*COSTOS!$C$7+E18*COSTOS!$C$8+F18*COSTOS!$C$9+G18*COSTOS!$C$10))) | N18: Nº VENTAS | O18: =IFERROR(COUNTA(B5:B700),0)
L19: =IF(K19<>"",(IF(H19="","",H19-(C19*COSTOS!$C$6+D19*COSTOS!$C$7+E19*COSTOS!$C$8+F19*COSTOS!$C$9+G19*COSTOS!$C$10)))+K19,IF(H19="","",H19-(C19*COSTOS!$C$6+D19*COSTOS!$C$7+E19*COSTOS!$C$8+F19*COSTOS!$C$9+G19*COSTOS!$C$10))) | N19: DÍAS DEL MES | O19: 31
L20: =IF(K20<>"",(IF(H20="","",H20-(C20*COSTOS!$C$6+D20*COSTOS!$C$7+E20*COSTOS!$C$8+F20*COSTOS!$C$9+G20*COSTOS!$C$10)))+K20,IF(H20="","",H20-(C20*COSTOS!$C$6+D20*COSTOS!$C$7+E20*COSTOS!$C$8+F20*COSTOS!$C$9+G20*COSTOS!$C$10)))
L21: =IF(K21<>"",(IF(H21="","",H21-(C21*COSTOS!$C$6+D21*COSTOS!$C$7+E21*COSTOS!$C$8+F21*COSTOS!$C$9+G21*COSTOS!$C$10)))+K21,IF(H21="","",H21-(C21*COSTOS!$C$6+D21*COSTOS!$C$7+E21*COSTOS!$C$8+F21*COSTOS!$C$9+G21*COSTOS!$C$10))) | N21: OBJETIVO ($)
L22: =IF(K22<>"",(IF(H22="","",H22-(C22*COSTOS!$C$6+D22*COSTOS!$C$7+E22*COSTOS!$C$8+F22*COSTOS!$C$9+G22*COSTOS!$C$10)))+K22,IF(H22="","",H22-(C22*COSTOS!$C$6+D22*COSTOS!$C$7+E22*COSTOS!$C$8+F22*COSTOS!$C$9+G22*COSTOS!$C$10))) | N22: DIFERENCIA | O22: =IFERROR(SUM(L5:L700)-N21,0)
L23: =IF(K23<>"",(IF(H23="","",H23-(C23*COSTOS!$C$6+D23*COSTOS!$C$7+E23*COSTOS!$C$8+F23*COSTOS!$C$9+G23*COSTOS!$C$10)))+K23,IF(H23="","",H23-(C23*COSTOS!$C$6+D23*COSTOS!$C$7+E23*COSTOS!$C$8+F23*COSTOS!$C$9+G23*COSTOS!$C$10)))
L24: =IF(K24<>"",(IF(H24="","",H24-(C24*COSTOS!$C$6+D24*COSTOS!$C$7+E24*COSTOS!$C$8+F24*COSTOS!$C$9+G24*COSTOS!$C$10)))+K24,IF(H24="","",H24-(C24*COSTOS!$C$6+D24*COSTOS!$C$7+E24*COSTOS!$C$8+F24*COSTOS!$C$9+G24*COSTOS!$C$10)))
L25: =IF(K25<>"",(IF(H25="","",H25-(C25*COSTOS!$C$6+D25*COSTOS!$C$7+E25*COSTOS!$C$8+F25*COSTOS!$C$9+G25*COSTOS!$C$10)))+K25,IF(H25="","",H25-(C25*COSTOS!$C$6+D25*COSTOS!$C$7+E25*COSTOS!$C$8+F25*COSTOS!$C$9+G25*COSTOS!$C$10)))
L26: =IF(K26<>"",(IF(H26="","",H26-(C26*COSTOS!$C$6+D26*COSTOS!$C$7+E26*COSTOS!$C$8+F26*COSTOS!$C$9+G26*COSTOS!$C$10)))+K26,IF(H26="","",H26-(C26*COSTOS!$C$6+D26*COSTOS!$C$7+E26*COSTOS!$C$8+F26*COSTOS!$C$9+G26*COSTOS!$C$10)))
L27: =IF(K27<>"",(IF(H27="","",H27-(C27*COSTOS!$C$6+D27*COSTOS!$C$7+E27*COSTOS!$C$8+F27*COSTOS!$C$9+G27*COSTOS!$C$10)))+K27,IF(H27="","",H27-(C27*COSTOS!$C$6+D27*COSTOS!$C$7+E27*COSTOS!$C$8+F27*COSTOS!$C$9+G27*COSTOS!$C$10)))
L28: =IF(K28<>"",(IF(H28="","",H28-(C28*COSTOS!$C$6+D28*COSTOS!$C$7+E28*COSTOS!$C$8+F28*COSTOS!$C$9+G28*COSTOS!$C$10)))+K28,IF(H28="","",H28-(C28*COSTOS!$C$6+D28*COSTOS!$C$7+E28*COSTOS!$C$8+F28*COSTOS!$C$9+G28*COSTOS!$C$10)))
L29: =IF(K29<>"",(IF(H29="","",H29-(C29*COSTOS!$C$6+D29*COSTOS!$C$7+E29*COSTOS!$C$8+F29*COSTOS!$C$9+G29*COSTOS!$C$10)))+K29,IF(H29="","",H29-(C29*COSTOS!$C$6+D29*COSTOS!$C$7+E29*COSTOS!$C$8+F29*COSTOS!$C$9+G29*COSTOS!$C$10))) | O29: =IFERROR(SUM(L5:L700)/COUNTA(B5:B700),0)
L30: =IF(K30<>"",(IF(H30="","",H30-(C30*COSTOS!$C$6+D30*COSTOS!$C$7+E30*COSTOS!$C$8+F30*COSTOS!$C$9+G30*COSTOS!$C$10)))+K30,IF(H30="","",H30-(C30*COSTOS!$C$6+D30*COSTOS!$C$7+E30*COSTOS!$C$8+F30*COSTOS!$C$9+G30*COSTOS!$C$10)))
L31: =IF(K31<>"",(IF(H31="","",H31-(C31*COSTOS!$C$6+D31*COSTOS!$C$7+E31*COSTOS!$C$8+F31*COSTOS!$C$9+G31*COSTOS!$C$10)))+K31,IF(H31="","",H31-(C31*COSTOS!$C$6+D31*COSTOS!$C$7+E31*COSTOS!$C$8+F31*COSTOS!$C$9+G31*COSTOS!$C$10)))
L32: =IF(K32<>"",(IF(H32="","",H32-(C32*COSTOS!$C$6+D32*COSTOS!$C$7+E32*COSTOS!$C$8+F32*COSTOS!$C$9+G32*COSTOS!$C$10)))+K32,IF(H32="","",H32-(C32*COSTOS!$C$6+D32*COSTOS!$C$7+E32*COSTOS!$C$8+F32*COSTOS!$C$9+G32*COSTOS!$C$10)))
L33: =IF(K33<>"",(IF(H33="","",H33-(C33*COSTOS!$C$6+D33*COSTOS!$C$7+E33*COSTOS!$C$8+F33*COSTOS!$C$9+G33*COSTOS!$C$10)))+K33,IF(H33="","",H33-(C33*COSTOS!$C$6+D33*COSTOS!$C$7+E33*COSTOS!$C$8+F33*COSTOS!$C$9+G33*COSTOS!$C$10)))
L34: =IF(K34<>"",(IF(H34="","",H34-(C34*COSTOS!$C$6+D34*COSTOS!$C$7+E34*COSTOS!$C$8+F34*COSTOS!$C$9+G34*COSTOS!$C$10)))+K34,IF(H34="","",H34-(C34*COSTOS!$C$6+D34*COSTOS!$C$7+E34*COSTOS!$C$8+F34*COSTOS!$C$9+G34*COSTOS!$C$10)))
L35: =IF(K35<>"",(IF(H35="","",H35-(C35*COSTOS!$C$6+D35*COSTOS!$C$7+E35*COSTOS!$C$8+F35*COSTOS!$C$9+G35*COSTOS!$C$10)))+K35,IF(H35="","",H35-(C35*COSTOS!$C$6+D35*COSTOS!$C$7+E35*COSTOS!$C$8+F35*COSTOS!$C$9+G35*COSTOS!$C$10)))
L36: =IF(K36<>"",(IF(H36="","",H36-(C36*COSTOS!$C$6+D36*COSTOS!$C$7+E36*COSTOS!$C$8+F36*COSTOS!$C$9+G36*COSTOS!$C$10)))+K36,IF(H36="","",H36-(C36*COSTOS!$C$6+D36*COSTOS!$C$7+E36*COSTOS!$C$8+F36*COSTOS!$C$9+G36*COSTOS!$C$10)))
L37: =IF(K37<>"",(IF(H37="","",H37-(C37*COSTOS!$C$6+D37*COSTOS!$C$7+E37*COSTOS!$C$8+F37*COSTOS!$C$9+G37*COSTOS!$C$10)))+K37,IF(H37="","",H37-(C37*COSTOS!$C$6+D37*COSTOS!$C$7+E37*COSTOS!$C$8+F37*COSTOS!$C$9+G37*COSTOS!$C$10)))
L38: =IF(K38<>"",(IF(H38="","",H38-(C38*COSTOS!$C$6+D38*COSTOS!$C$7+E38*COSTOS!$C$8+F38*COSTOS!$C$9+G38*COSTOS!$C$10)))+K38,IF(H38="","",H38-(C38*COSTOS!$C$6+D38*COSTOS!$C$7+E38*COSTOS!$C$8+F38*COSTOS!$C$9+G38*COSTOS!$C$10)))
L39: =IF(K39<>"",(IF(H39="","",H39-(C39*COSTOS!$C$6+D39*COSTOS!$C$7+E39*COSTOS!$C$8+F39*COSTOS!$C$9+G39*COSTOS!$C$10)))+K39,IF(H39="","",H39-(C39*COSTOS!$C$6+D39*COSTOS!$C$7+E39*COSTOS!$C$8+F39*COSTOS!$C$9+G39*COSTOS!$C$10)))
L40: =IF(K40<>"",(IF(H40="","",H40-(C40*COSTOS!$C$6+D40*COSTOS!$C$7+E40*COSTOS!$C$8+F40*COSTOS!$C$9+G40*COSTOS!$C$10)))+K40,IF(H40="","",H40-(C40*COSTOS!$C$6+D40*COSTOS!$C$7+E40*COSTOS!$C$8+F40*COSTOS!$C$9+G40*COSTOS!$C$10)))
L41: =IF(K41<>"",(IF(H41="","",H41-(C41*COSTOS!$C$6+D41*COSTOS!$C$7+E41*COSTOS!$C$8+F41*COSTOS!$C$9+G41*COSTOS!$C$10)))+K41,IF(H41="","",H41-(C41*COSTOS!$C$6+D41*COSTOS!$C$7+E41*COSTOS!$C$8+F41*COSTOS!$C$9+G41*COSTOS!$C$10)))
... L500: =IF(K500<>"",(IF(H500="","",H500-(C500*COSTOS!$C$6+D500*COSTOS!$C$7+E500*COSTOS!$C$8+F500*COSTOS!$C$9+G500*COSTOS!$C$10)))+K500,IF(H500="","",H500-(C500*COSTOS!$C$6+D500*COSTOS!$C$7+E500*COSTOS!$C$8+F500*COSTOS!$C$9+G500*COSTOS!$C$10)))
A501: TOTALES DEL MES | C501: =IFERROR(SUM(C5:C500),0) | D501: =IFERROR(SUM(D5:D500),0) | E501: =IFERROR(SUM(E5:E500),0) | F501: =IFERROR(SUM(F5:F500),0) | G501: =IFERROR(SUM(G5:G500),0)

Sheet Noviembre
A1: VENTAS — NOVIEMBRE 2026
A2: ⚠ El nombre del cliente debe ser EXACTAMENTE igual siempre · La ganancia se calcula con el costo vigente a la fecha
A4: FECHA | B4: CLIENTE / DIRECCIÓN | C4: 10 | D4: 15 | E4: 45 | F4: YERBA | G4: AGUA | H4: VALOR ($) | I4: EFECTIVO ($) | J4: TRANSFER ($) | K4: ENVASE ($) | L4: GANANCIA ($) | N4: RESUMEN NOVIEMBRE
L5: =IF(K5<>"",(IF(H5="","",H5-(C5*COSTOS!$C$6+D5*COSTOS!$C$7+E5*COSTOS!$C$8+F5*COSTOS!$C$9+G5*COSTOS!$C$10)))+K5,IF(H5="","",H5-(C5*COSTOS!$C$6+D5*COSTOS!$C$7+E5*COSTOS!$C$8+F5*COSTOS!$C$9+G5*COSTOS!$C$10))) | N5: TOTAL 10 | O5: =IFERROR(SUM(C5:C700),0)
L6: =IF(K6<>"",(IF(H6="","",H6-(C6*COSTOS!$C$6+D6*COSTOS!$C$7+E6*COSTOS!$C$8+F6*COSTOS!$C$9+G6*COSTOS!$C$10)))+K6,IF(H6="","",H6-(C6*COSTOS!$C$6+D6*COSTOS!$C$7+E6*COSTOS!$C$8+F6*COSTOS!$C$9+G6*COSTOS!$C$10))) | N6: TOTAL 15 | O6: =IFERROR(SUM(D5:D700),0)
L7: =IF(K7<>"",(IF(H7="","",H7-(C7*COSTOS!$C$6+D7*COSTOS!$C$7+E7*COSTOS!$C$8+F7*COSTOS!$C$9+G7*COSTOS!$C$10)))+K7,IF(H7="","",H7-(C7*COSTOS!$C$6+D7*COSTOS!$C$7+E7*COSTOS!$C$8+F7*COSTOS!$C$9+G7*COSTOS!$C$10))) | N7: TOTAL 45 | O7: =IFERROR(SUM(E5:E700),0)
L8: =IF(K8<>"",(IF(H8="","",H8-(C8*COSTOS!$C$6+D8*COSTOS!$C$7+E8*COSTOS!$C$8+F8*COSTOS!$C$9+G8*COSTOS!$C$10)))+K8,IF(H8="","",H8-(C8*COSTOS!$C$6+D8*COSTOS!$C$7+E8*COSTOS!$C$8+F8*COSTOS!$C$9+G8*COSTOS!$C$10))) | N8: TOTAL YERBA | O8: =IFERROR(SUM(F5:F700),0)
L9: =IF(K9<>"",(IF(H9="","",H9-(C9*COSTOS!$C$6+D9*COSTOS!$C$7+E9*COSTOS!$C$8+F9*COSTOS!$C$9+G9*COSTOS!$C$10)))+K9,IF(H9="","",H9-(C9*COSTOS!$C$6+D9*COSTOS!$C$7+E9*COSTOS!$C$8+F9*COSTOS!$C$9+G9*COSTOS!$C$10))) | N9: TOTAL AGUA | O9: =IFERROR(SUM(G5:G700),0)
L10: =IF(K10<>"",(IF(H10="","",H10-(C10*COSTOS!$C$6+D10*COSTOS!$C$7+E10*COSTOS!$C$8+F10*COSTOS!$C$9+G10*COSTOS!$C$10)))+K10,IF(H10="","",H10-(C10*COSTOS!$C$6+D10*COSTOS!$C$7+E10*COSTOS!$C$8+F10*COSTOS!$C$9+G10*COSTOS!$C$10)))
L11: =IF(K11<>"",(IF(H11="","",H11-(C11*COSTOS!$C$6+D11*COSTOS!$C$7+E11*COSTOS!$C$8+F11*COSTOS!$C$9+G11*COSTOS!$C$10)))+K11,IF(H11="","",H11-(C11*COSTOS!$C$6+D11*COSTOS!$C$7+E11*COSTOS!$C$8+F11*COSTOS!$C$9+G11*COSTOS!$C$10))) | N11: FACTURACIÓN | O11: =IFERROR(SUM(H5:H700),0)
L12: =IF(K12<>"",(IF(H12="","",H12-(C12*COSTOS!$C$6+D12*COSTOS!$C$7+E12*COSTOS!$C$8+F12*COSTOS!$C$9+G12*COSTOS!$C$10)))+K12,IF(H12="","",H12-(C12*COSTOS!$C$6+D12*COSTOS!$C$7+E12*COSTOS!$C$8+F12*COSTOS!$C$9+G12*COSTOS!$C$10))) | N12: GANANCIA | O12: =IFERROR(SUM(L5:L700),0)
L13: =IF(K13<>"",(IF(H13="","",H13-(C13*COSTOS!$C$6+D13*COSTOS!$C$7+E13*COSTOS!$C$8+F13*COSTOS!$C$9+G13*COSTOS!$C$10)))+K13,IF(H13="","",H13-(C13*COSTOS!$C$6+D13*COSTOS!$C$7+E13*COSTOS!$C$8+F13*COSTOS!$C$9+G13*COSTOS!$C$10))) | N13: % GANANCIA | O13: =IFERROR(SUM(L5:L700)/SUM(H5:H700),0)
L14: =IF(K14<>"",(IF(H14="","",H14-(C14*COSTOS!$C$6+D14*COSTOS!$C$7+E14*COSTOS!$C$8+F14*COSTOS!$C$9+G14*COSTOS!$C$10)))+K14,IF(H14="","",H14-(C14*COSTOS!$C$6+D14*COSTOS!$C$7+E14*COSTOS!$C$8+F14*COSTOS!$C$9+G14*COSTOS!$C$10)))
L15: =IF(K15<>"",(IF(H15="","",H15-(C15*COSTOS!$C$6+D15*COSTOS!$C$7+E15*COSTOS!$C$8+F15*COSTOS!$C$9+G15*COSTOS!$C$10)))+K15,IF(H15="","",H15-(C15*COSTOS!$C$6+D15*COSTOS!$C$7+E15*COSTOS!$C$8+F15*COSTOS!$C$9+G15*COSTOS!$C$10))) | N15: EFECTIVO | O15: =IFERROR(SUM(I5:I700),0)
L16: =IF(K16<>"",(IF(H16="","",H16-(C16*COSTOS!$C$6+D16*COSTOS!$C$7+E16*COSTOS!$C$8+F16*COSTOS!$C$9+G16*COSTOS!$C$10)))+K16,IF(H16="","",H16-(C16*COSTOS!$C$6+D16*COSTOS!$C$7+E16*COSTOS!$C$8+F16*COSTOS!$C$9+G16*COSTOS!$C$10))) | N16: TRANSFERENCIA | O16: =IFERROR(SUM(J5:J700),0)
L17: =IF(K17<>"",(IF(H17="","",H17-(C17*COSTOS!$C$6+D17*COSTOS!$C$7+E17*COSTOS!$C$8+F17*COSTOS!$C$9+G17*COSTOS!$C$10)))+K17,IF(H17="","",H17-(C17*COSTOS!$C$6+D17*COSTOS!$C$7+E17*COSTOS!$C$8+F17*COSTOS!$C$9+G17*COSTOS!$C$10)))
L18: =IF(K18<>"",(IF(H18="","",H18-(C18*COSTOS!$C$6+D18*COSTOS!$C$7+E18*COSTOS!$C$8+F18*COSTOS!$C$9+G18*COSTOS!$C$10)))+K18,IF(H18="","",H18-(C18*COSTOS!$C$6+D18*COSTOS!$C$7+E18*COSTOS!$C$8+F18*COSTOS!$C$9+G18*COSTOS!$C$10))) | N18: Nº VENTAS | O18: =IFERROR(COUNTA(B5:B700),0)
L19: =IF(K19<>"",(IF(H19="","",H19-(C19*COSTOS!$C$6+D19*COSTOS!$C$7+E19*COSTOS!$C$8+F19*COSTOS!$C$9+G19*COSTOS!$C$10)))+K19,IF(H19="","",H19-(C19*COSTOS!$C$6+D19*COSTOS!$C$7+E19*COSTOS!$C$8+F19*COSTOS!$C$9+G19*COSTOS!$C$10))) | N19: DÍAS DEL MES | O19: 30
L20: =IF(K20<>"",(IF(H20="","",H20-(C20*COSTOS!$C$6+D20*COSTOS!$C$7+E20*COSTOS!$C$8+F20*COSTOS!$C$9+G20*COSTOS!$C$10)))+K20,IF(H20="","",H20-(C20*COSTOS!$C$6+D20*COSTOS!$C$7+E20*COSTOS!$C$8+F20*COSTOS!$C$9+G20*COSTOS!$C$10)))
L21: =IF(K21<>"",(IF(H21="","",H21-(C21*COSTOS!$C$6+D21*COSTOS!$C$7+E21*COSTOS!$C$8+F21*COSTOS!$C$9+G21*COSTOS!$C$10)))+K21,IF(H21="","",H21-(C21*COSTOS!$C$6+D21*COSTOS!$C$7+E21*COSTOS!$C$8+F21*COSTOS!$C$9+G21*COSTOS!$C$10))) | N21: OBJETIVO ($)
L22: =IF(K22<>"",(IF(H22="","",H22-(C22*COSTOS!$C$6+D22*COSTOS!$C$7+E22*COSTOS!$C$8+F22*COSTOS!$C$9+G22*COSTOS!$C$10)))+K22,IF(H22="","",H22-(C22*COSTOS!$C$6+D22*COSTOS!$C$7+E22*COSTOS!$C$8+F22*COSTOS!$C$9+G22*COSTOS!$C$10))) | N22: DIFERENCIA | O22: =IFERROR(SUM(L5:L700)-N21,0)
L23: =IF(K23<>"",(IF(H23="","",H23-(C23*COSTOS!$C$6+D23*COSTOS!$C$7+E23*COSTOS!$C$8+F23*COSTOS!$C$9+G23*COSTOS!$C$10)))+K23,IF(H23="","",H23-(C23*COSTOS!$C$6+D23*COSTOS!$C$7+E23*COSTOS!$C$8+F23*COSTOS!$C$9+G23*COSTOS!$C$10)))
L24: =IF(K24<>"",(IF(H24="","",H24-(C24*COSTOS!$C$6+D24*COSTOS!$C$7+E24*COSTOS!$C$8+F24*COSTOS!$C$9+G24*COSTOS!$C$10)))+K24,IF(H24="","",H24-(C24*COSTOS!$C$6+D24*COSTOS!$C$7+E24*COSTOS!$C$8+F24*COSTOS!$C$9+G24*COSTOS!$C$10)))
L25: =IF(K25<>"",(IF(H25="","",H25-(C25*COSTOS!$C$6+D25*COSTOS!$C$7+E25*COSTOS!$C$8+F25*COSTOS!$C$9+G25*COSTOS!$C$10)))+K25,IF(H25="","",H25-(C25*COSTOS!$C$6+D25*COSTOS!$C$7+E25*COSTOS!$C$8+F25*COSTOS!$C$9+G25*COSTOS!$C$10)))
L26: =IF(K26<>"",(IF(H26="","",H26-(C26*COSTOS!$C$6+D26*COSTOS!$C$7+E26*COSTOS!$C$8+F26*COSTOS!$C$9+G26*COSTOS!$C$10)))+K26,IF(H26="","",H26-(C26*COSTOS!$C$6+D26*COSTOS!$C$7+E26*COSTOS!$C$8+F26*COSTOS!$C$9+G26*COSTOS!$C$10)))
L27: =IF(K27<>"",(IF(H27="","",H27-(C27*COSTOS!$C$6+D27*COSTOS!$C$7+E27*COSTOS!$C$8+F27*COSTOS!$C$9+G27*COSTOS!$C$10)))+K27,IF(H27="","",H27-(C27*COSTOS!$C$6+D27*COSTOS!$C$7+E27*COSTOS!$C$8+F27*COSTOS!$C$9+G27*COSTOS!$C$10)))
L28: =IF(K28<>"",(IF(H28="","",H28-(C28*COSTOS!$C$6+D28*COSTOS!$C$7+E28*COSTOS!$C$8+F28*COSTOS!$C$9+G28*COSTOS!$C$10)))+K28,IF(H28="","",H28-(C28*COSTOS!$C$6+D28*COSTOS!$C$7+E28*COSTOS!$C$8+F28*COSTOS!$C$9+G28*COSTOS!$C$10)))
L29: =IF(K29<>"",(IF(H29="","",H29-(C29*COSTOS!$C$6+D29*COSTOS!$C$7+E29*COSTOS!$C$8+F29*COSTOS!$C$9+G29*COSTOS!$C$10)))+K29,IF(H29="","",H29-(C29*COSTOS!$C$6+D29*COSTOS!$C$7+E29*COSTOS!$C$8+F29*COSTOS!$C$9+G29*COSTOS!$C$10))) | O29: =IFERROR(SUM(L5:L700)/COUNTA(B5:B700),0)
L30: =IF(K30<>"",(IF(H30="","",H30-(C30*COSTOS!$C$6+D30*COSTOS!$C$7+E30*COSTOS!$C$8+F30*COSTOS!$C$9+G30*COSTOS!$C$10)))+K30,IF(H30="","",H30-(C30*COSTOS!$C$6+D30*COSTOS!$C$7+E30*COSTOS!$C$8+F30*COSTOS!$C$9+G30*COSTOS!$C$10)))
L31: =IF(K31<>"",(IF(H31="","",H31-(C31*COSTOS!$C$6+D31*COSTOS!$C$7+E31*COSTOS!$C$8+F31*COSTOS!$C$9+G31*COSTOS!$C$10)))+K31,IF(H31="","",H31-(C31*COSTOS!$C$6+D31*COSTOS!$C$7+E31*COSTOS!$C$8+F31*COSTOS!$C$9+G31*COSTOS!$C$10)))
L32: =IF(K32<>"",(IF(H32="","",H32-(C32*COSTOS!$C$6+D32*COSTOS!$C$7+E32*COSTOS!$C$8+F32*COSTOS!$C$9+G32*COSTOS!$C$10)))+K32,IF(H32="","",H32-(C32*COSTOS!$C$6+D32*COSTOS!$C$7+E32*COSTOS!$C$8+F32*COSTOS!$C$9+G32*COSTOS!$C$10)))
L33: =IF(K33<>"",(IF(H33="","",H33-(C33*COSTOS!$C$6+D33*COSTOS!$C$7+E33*COSTOS!$C$8+F33*COSTOS!$C$9+G33*COSTOS!$C$10)))+K33,IF(H33="","",H33-(C33*COSTOS!$C$6+D33*COSTOS!$C$7+E33*COSTOS!$C$8+F33*COSTOS!$C$9+G33*COSTOS!$C$10)))
L34: =IF(K34<>"",(IF(H34="","",H34-(C34*COSTOS!$C$6+D34*COSTOS!$C$7+E34*COSTOS!$C$8+F34*COSTOS!$C$9+G34*COSTOS!$C$10)))+K34,IF(H34="","",H34-(C34*COSTOS!$C$6+D34*COSTOS!$C$7+E34*COSTOS!$C$8+F34*COSTOS!$C$9+G34*COSTOS!$C$10)))
L35: =IF(K35<>"",(IF(H35="","",H35-(C35*COSTOS!$C$6+D35*COSTOS!$C$7+E35*COSTOS!$C$8+F35*COSTOS!$C$9+G35*COSTOS!$C$10)))+K35,IF(H35="","",H35-(C35*COSTOS!$C$6+D35*COSTOS!$C$7+E35*COSTOS!$C$8+F35*COSTOS!$C$9+G35*COSTOS!$C$10)))
L36: =IF(K36<>"",(IF(H36="","",H36-(C36*COSTOS!$C$6+D36*COSTOS!$C$7+E36*COSTOS!$C$8+F36*COSTOS!$C$9+G36*COSTOS!$C$10)))+K36,IF(H36="","",H36-(C36*COSTOS!$C$6+D36*COSTOS!$C$7+E36*COSTOS!$C$8+F36*COSTOS!$C$9+G36*COSTOS!$C$10)))
L37: =IF(K37<>"",(IF(H37="","",H37-(C37*COSTOS!$C$6+D37*COSTOS!$C$7+E37*COSTOS!$C$8+F37*COSTOS!$C$9+G37*COSTOS!$C$10)))+K37,IF(H37="","",H37-(C37*COSTOS!$C$6+D37*COSTOS!$C$7+E37*COSTOS!$C$8+F37*COSTOS!$C$9+G37*COSTOS!$C$10)))
L38: =IF(K38<>"",(IF(H38="","",H38-(C38*COSTOS!$C$6+D38*COSTOS!$C$7+E38*COSTOS!$C$8+F38*COSTOS!$C$9+G38*COSTOS!$C$10)))+K38,IF(H38="","",H38-(C38*COSTOS!$C$6+D38*COSTOS!$C$7+E38*COSTOS!$C$8+F38*COSTOS!$C$9+G38*COSTOS!$C$10)))
L39: =IF(K39<>"",(IF(H39="","",H39-(C39*COSTOS!$C$6+D39*COSTOS!$C$7+E39*COSTOS!$C$8+F39*COSTOS!$C$9+G39*COSTOS!$C$10)))+K39,IF(H39="","",H39-(C39*COSTOS!$C$6+D39*COSTOS!$C$7+E39*COSTOS!$C$8+F39*COSTOS!$C$9+G39*COSTOS!$C$10)))
L40: =IF(K40<>"",(IF(H40="","",H40-(C40*COSTOS!$C$6+D40*COSTOS!$C$7+E40*COSTOS!$C$8+F40*COSTOS!$C$9+G40*COSTOS!$C$10)))+K40,IF(H40="","",H40-(C40*COSTOS!$C$6+D40*COSTOS!$C$7+E40*COSTOS!$C$8+F40*COSTOS!$C$9+G40*COSTOS!$C$10)))
L41: =IF(K41<>"",(IF(H41="","",H41-(C41*COSTOS!$C$6+D41*COSTOS!$C$7+E41*COSTOS!$C$8+F41*COSTOS!$C$9+G41*COSTOS!$C$10)))+K41,IF(H41="","",H41-(C41*COSTOS!$C$6+D41*COSTOS!$C$7+E41*COSTOS!$C$8+F41*COSTOS!$C$9+G41*COSTOS!$C$10)))
... L500: =IF(K500<>"",(IF(H500="","",H500-(C500*COSTOS!$C$6+D500*COSTOS!$C$7+E500*COSTOS!$C$8+F500*COSTOS!$C$9+G500*COSTOS!$C$10)))+K500,IF(H500="","",H500-(C500*COSTOS!$C$6+D500*COSTOS!$C$7+E500*COSTOS!$C$8+F500*COSTOS!$C$9+G500*COSTOS!$C$10)))
A501: TOTALES DEL MES | C501: =IFERROR(SUM(C5:C500),0) | D501: =IFERROR(SUM(D5:D500),0) | E501: =IFERROR(SUM(E5:E500),0) | F501: =IFERROR(SUM(F5:F500),0) | G501: =IFERROR(SUM(G5:G500),0)

Sheet Diciembre
A1: VENTAS — DICIEMBRE 2026
A2: ⚠ El nombre del cliente debe ser EXACTAMENTE igual siempre · La ganancia se calcula con el costo vigente a la fecha
A4: FECHA | B4: CLIENTE / DIRECCIÓN | C4: 10 | D4: 15 | E4: 45 | F4: YERBA | G4: AGUA | H4: VALOR ($) | I4: EFECTIVO ($) | J4: TRANSFER ($) | K4: ENVASE ($) | L4: GANANCIA ($) | N4: RESUMEN DICIEMBRE
L5: =IF(K5<>"",(IF(H5="","",H5-(C5*COSTOS!$C$6+D5*COSTOS!$C$7+E5*COSTOS!$C$8+F5*COSTOS!$C$9+G5*COSTOS!$C$10)))+K5,IF(H5="","",H5-(C5*COSTOS!$C$6+D5*COSTOS!$C$7+E5*COSTOS!$C$8+F5*COSTOS!$C$9+G5*COSTOS!$C$10))) | N5: TOTAL 10 | O5: =IFERROR(SUM(C5:C700),0)
L6: =IF(K6<>"",(IF(H6="","",H6-(C6*COSTOS!$C$6+D6*COSTOS!$C$7+E6*COSTOS!$C$8+F6*COSTOS!$C$9+G6*COSTOS!$C$10)))+K6,IF(H6="","",H6-(C6*COSTOS!$C$6+D6*COSTOS!$C$7+E6*COSTOS!$C$8+F6*COSTOS!$C$9+G6*COSTOS!$C$10))) | N6: TOTAL 15 | O6: =IFERROR(SUM(D5:D700),0)
L7: =IF(K7<>"",(IF(H7="","",H7-(C7*COSTOS!$C$6+D7*COSTOS!$C$7+E7*COSTOS!$C$8+F7*COSTOS!$C$9+G7*COSTOS!$C$10)))+K7,IF(H7="","",H7-(C7*COSTOS!$C$6+D7*COSTOS!$C$7+E7*COSTOS!$C$8+F7*COSTOS!$C$9+G7*COSTOS!$C$10))) | N7: TOTAL 45 | O7: =IFERROR(SUM(E5:E700),0)
L8: =IF(K8<>"",(IF(H8="","",H8-(C8*COSTOS!$C$6+D8*COSTOS!$C$7+E8*COSTOS!$C$8+F8*COSTOS!$C$9+G8*COSTOS!$C$10)))+K8,IF(H8="","",H8-(C8*COSTOS!$C$6+D8*COSTOS!$C$7+E8*COSTOS!$C$8+F8*COSTOS!$C$9+G8*COSTOS!$C$10))) | N8: TOTAL YERBA | O8: =IFERROR(SUM(F5:F700),0)
L9: =IF(K9<>"",(IF(H9="","",H9-(C9*COSTOS!$C$6+D9*COSTOS!$C$7+E9*COSTOS!$C$8+F9*COSTOS!$C$9+G9*COSTOS!$C$10)))+K9,IF(H9="","",H9-(C9*COSTOS!$C$6+D9*COSTOS!$C$7+E9*COSTOS!$C$8+F9*COSTOS!$C$9+G9*COSTOS!$C$10))) | N9: TOTAL AGUA | O9: =IFERROR(SUM(G5:G700),0)
L10: =IF(K10<>"",(IF(H10="","",H10-(C10*COSTOS!$C$6+D10*COSTOS!$C$7+E10*COSTOS!$C$8+F10*COSTOS!$C$9+G10*COSTOS!$C$10)))+K10,IF(H10="","",H10-(C10*COSTOS!$C$6+D10*COSTOS!$C$7+E10*COSTOS!$C$8+F10*COSTOS!$C$9+G10*COSTOS!$C$10)))
L11: =IF(K11<>"",(IF(H11="","",H11-(C11*COSTOS!$C$6+D11*COSTOS!$C$7+E11*COSTOS!$C$8+F11*COSTOS!$C$9+G11*COSTOS!$C$10)))+K11,IF(H11="","",H11-(C11*COSTOS!$C$6+D11*COSTOS!$C$7+E11*COSTOS!$C$8+F11*COSTOS!$C$9+G11*COSTOS!$C$10))) | N11: FACTURACIÓN | O11: =IFERROR(SUM(H5:H700),0)
L12: =IF(K12<>"",(IF(H12="","",H12-(C12*COSTOS!$C$6+D12*COSTOS!$C$7+E12*COSTOS!$C$8+F12*COSTOS!$C$9+G12*COSTOS!$C$10)))+K12,IF(H12="","",H12-(C12*COSTOS!$C$6+D12*COSTOS!$C$7+E12*COSTOS!$C$8+F12*COSTOS!$C$9+G12*COSTOS!$C$10))) | N12: GANANCIA | O12: =IFERROR(SUM(L5:L700),0)
L13: =IF(K13<>"",(IF(H13="","",H13-(C13*COSTOS!$C$6+D13*COSTOS!$C$7+E13*COSTOS!$C$8+F13*COSTOS!$C$9+G13*COSTOS!$C$10)))+K13,IF(H13="","",H13-(C13*COSTOS!$C$6+D13*COSTOS!$C$7+E13*COSTOS!$C$8+F13*COSTOS!$C$9+G13*COSTOS!$C$10))) | N13: % GANANCIA | O13: =IFERROR(SUM(L5:L700)/SUM(H5:H700),0)
L14: =IF(K14<>"",(IF(H14="","",H14-(C14*COSTOS!$C$6+D14*COSTOS!$C$7+E14*COSTOS!$C$8+F14*COSTOS!$C$9+G14*COSTOS!$C$10)))+K14,IF(H14="","",H14-(C14*COSTOS!$C$6+D14*COSTOS!$C$7+E14*COSTOS!$C$8+F14*COSTOS!$C$9+G14*COSTOS!$C$10)))
L15: =IF(K15<>"",(IF(H15="","",H15-(C15*COSTOS!$C$6+D15*COSTOS!$C$7+E15*COSTOS!$C$8+F15*COSTOS!$C$9+G15*COSTOS!$C$10)))+K15,IF(H15="","",H15-(C15*COSTOS!$C$6+D15*COSTOS!$C$7+E15*COSTOS!$C$8+F15*COSTOS!$C$9+G15*COSTOS!$C$10))) | N15: EFECTIVO | O15: =IFERROR(SUM(I5:I700),0)
L16: =IF(K16<>"",(IF(H16="","",H16-(C16*COSTOS!$C$6+D16*COSTOS!$C$7+E16*COSTOS!$C$8+F16*COSTOS!$C$9+G16*COSTOS!$C$10)))+K16,IF(H16="","",H16-(C16*COSTOS!$C$6+D16*COSTOS!$C$7+E16*COSTOS!$C$8+F16*COSTOS!$C$9+G16*COSTOS!$C$10))) | N16: TRANSFERENCIA | O16: =IFERROR(SUM(J5:J700),0)
L17: =IF(K17<>"",(IF(H17="","",H17-(C17*COSTOS!$C$6+D17*COSTOS!$C$7+E17*COSTOS!$C$8+F17*COSTOS!$C$9+G17*COSTOS!$C$10)))+K17,IF(H17="","",H17-(C17*COSTOS!$C$6+D17*COSTOS!$C$7+E17*COSTOS!$C$8+F17*COSTOS!$C$9+G17*COSTOS!$C$10)))
L18: =IF(K18<>"",(IF(H18="","",H18-(C18*COSTOS!$C$6+D18*COSTOS!$C$7+E18*COSTOS!$C$8+F18*COSTOS!$C$9+G18*COSTOS!$C$10)))+K18,IF(H18="","",H18-(C18*COSTOS!$C$6+D18*COSTOS!$C$7+E18*COSTOS!$C$8+F18*COSTOS!$C$9+G18*COSTOS!$C$10))) | N18: Nº VENTAS | O18: =IFERROR(COUNTA(B5:B700),0)
L19: =IF(K19<>"",(IF(H19="","",H19-(C19*COSTOS!$C$6+D19*COSTOS!$C$7+E19*COSTOS!$C$8+F19*COSTOS!$C$9+G19*COSTOS!$C$10)))+K19,IF(H19="","",H19-(C19*COSTOS!$C$6+D19*COSTOS!$C$7+E19*COSTOS!$C$8+F19*COSTOS!$C$9+G19*COSTOS!$C$10))) | N19: DÍAS DEL MES | O19: 31
L20: =IF(K20<>"",(IF(H20="","",H20-(C20*COSTOS!$C$6+D20*COSTOS!$C$7+E20*COSTOS!$C$8+F20*COSTOS!$C$9+G20*COSTOS!$C$10)))+K20,IF(H20="","",H20-(C20*COSTOS!$C$6+D20*COSTOS!$C$7+E20*COSTOS!$C$8+F20*COSTOS!$C$9+G20*COSTOS!$C$10)))
L21: =IF(K21<>"",(IF(H21="","",H21-(C21*COSTOS!$C$6+D21*COSTOS!$C$7+E21*COSTOS!$C$8+F21*COSTOS!$C$9+G21*COSTOS!$C$10)))+K21,IF(H21="","",H21-(C21*COSTOS!$C$6+D21*COSTOS!$C$7+E21*COSTOS!$C$8+F21*COSTOS!$C$9+G21*COSTOS!$C$10))) | N21: OBJETIVO ($)
L22: =IF(K22<>"",(IF(H22="","",H22-(C22*COSTOS!$C$6+D22*COSTOS!$C$7+E22*COSTOS!$C$8+F22*COSTOS!$C$9+G22*COSTOS!$C$10)))+K22,IF(H22="","",H22-(C22*COSTOS!$C$6+D22*COSTOS!$C$7+E22*COSTOS!$C$8+F22*COSTOS!$C$9+G22*COSTOS!$C$10))) | N22: DIFERENCIA | O22: =IFERROR(SUM(L5:L700)-N21,0)
L23: =IF(K23<>"",(IF(H23="","",H23-(C23*COSTOS!$C$6+D23*COSTOS!$C$7+E23*COSTOS!$C$8+F23*COSTOS!$C$9+G23*COSTOS!$C$10)))+K23,IF(H23="","",H23-(C23*COSTOS!$C$6+D23*COSTOS!$C$7+E23*COSTOS!$C$8+F23*COSTOS!$C$9+G23*COSTOS!$C$10)))
L24: =IF(K24<>"",(IF(H24="","",H24-(C24*COSTOS!$C$6+D24*COSTOS!$C$7+E24*COSTOS!$C$8+F24*COSTOS!$C$9+G24*COSTOS!$C$10)))+K24,IF(H24="","",H24-(C24*COSTOS!$C$6+D24*COSTOS!$C$7+E24*COSTOS!$C$8+F24*COSTOS!$C$9+G24*COSTOS!$C$10)))
L25: =IF(K25<>"",(IF(H25="","",H25-(C25*COSTOS!$C$6+D25*COSTOS!$C$7+E25*COSTOS!$C$8+F25*COSTOS!$C$9+G25*COSTOS!$C$10)))+K25,IF(H25="","",H25-(C25*COSTOS!$C$6+D25*COSTOS!$C$7+E25*COSTOS!$C$8+F25*COSTOS!$C$9+G25*COSTOS!$C$10)))
L26: =IF(K26<>"",(IF(H26="","",H26-(C26*COSTOS!$C$6+D26*COSTOS!$C$7+E26*COSTOS!$C$8+F26*COSTOS!$C$9+G26*COSTOS!$C$10)))+K26,IF(H26="","",H26-(C26*COSTOS!$C$6+D26*COSTOS!$C$7+E26*COSTOS!$C$8+F26*COSTOS!$C$9+G26*COSTOS!$C$10)))
L27: =IF(K27<>"",(IF(H27="","",H27-(C27*COSTOS!$C$6+D27*COSTOS!$C$7+E27*COSTOS!$C$8+F27*COSTOS!$C$9+G27*COSTOS!$C$10)))+K27,IF(H27="","",H27-(C27*COSTOS!$C$6+D27*COSTOS!$C$7+E27*COSTOS!$C$8+F27*COSTOS!$C$9+G27*COSTOS!$C$10)))
L28: =IF(K28<>"",(IF(H28="","",H28-(C28*COSTOS!$C$6+D28*COSTOS!$C$7+E28*COSTOS!$C$8+F28*COSTOS!$C$9+G28*COSTOS!$C$10)))+K28,IF(H28="","",H28-(C28*COSTOS!$C$6+D28*COSTOS!$C$7+E28*COSTOS!$C$8+F28*COSTOS!$C$9+G28*COSTOS!$C$10)))
L29: =IF(K29<>"",(IF(H29="","",H29-(C29*COSTOS!$C$6+D29*COSTOS!$C$7+E29*COSTOS!$C$8+F29*COSTOS!$C$9+G29*COSTOS!$C$10)))+K29,IF(H29="","",H29-(C29*COSTOS!$C$6+D29*COSTOS!$C$7+E29*COSTOS!$C$8+F29*COSTOS!$C$9+G29*COSTOS!$C$10))) | O29: =IFERROR(SUM(L5:L700)/COUNTA(B5:B700),0)
L30: =IF(K30<>"",(IF(H30="","",H30-(C30*COSTOS!$C$6+D30*COSTOS!$C$7+E30*COSTOS!$C$8+F30*COSTOS!$C$9+G30*COSTOS!$C$10)))+K30,IF(H30="","",H30-(C30*COSTOS!$C$6+D30*COSTOS!$C$7+E30*COSTOS!$C$8+F30*COSTOS!$C$9+G30*COSTOS!$C$10)))
L31: =IF(K31<>"",(IF(H31="","",H31-(C31*COSTOS!$C$6+D31*COSTOS!$C$7+E31*COSTOS!$C$8+F31*COSTOS!$C$9+G31*COSTOS!$C$10)))+K31,IF(H31="","",H31-(C31*COSTOS!$C$6+D31*COSTOS!$C$7+E31*COSTOS!$C$8+F31*COSTOS!$C$9+G31*COSTOS!$C$10)))
L32: =IF(K32<>"",(IF(H32="","",H32-(C32*COSTOS!$C$6+D32*COSTOS!$C$7+E32*COSTOS!$C$8+F32*COSTOS!$C$9+G32*COSTOS!$C$10)))+K32,IF(H32="","",H32-(C32*COSTOS!$C$6+D32*COSTOS!$C$7+E32*COSTOS!$C$8+F32*COSTOS!$C$9+G32*COSTOS!$C$10)))
L33: =IF(K33<>"",(IF(H33="","",H33-(C33*COSTOS!$C$6+D33*COSTOS!$C$7+E33*COSTOS!$C$8+F33*COSTOS!$C$9+G33*COSTOS!$C$10)))+K33,IF(H33="","",H33-(C33*COSTOS!$C$6+D33*COSTOS!$C$7+E33*COSTOS!$C$8+F33*COSTOS!$C$9+G33*COSTOS!$C$10)))
L34: =IF(K34<>"",(IF(H34="","",H34-(C34*COSTOS!$C$6+D34*COSTOS!$C$7+E34*COSTOS!$C$8+F34*COSTOS!$C$9+G34*COSTOS!$C$10)))+K34,IF(H34="","",H34-(C34*COSTOS!$C$6+D34*COSTOS!$C$7+E34*COSTOS!$C$8+F34*COSTOS!$C$9+G34*COSTOS!$C$10)))
L35: =IF(K35<>"",(IF(H35="","",H35-(C35*COSTOS!$C$6+D35*COSTOS!$C$7+E35*COSTOS!$C$8+F35*COSTOS!$C$9+G35*COSTOS!$C$10)))+K35,IF(H35="","",H35-(C35*COSTOS!$C$6+D35*COSTOS!$C$7+E35*COSTOS!$C$8+F35*COSTOS!$C$9+G35*COSTOS!$C$10)))
L36: =IF(K36<>"",(IF(H36="","",H36-(C36*COSTOS!$C$6+D36*COSTOS!$C$7+E36*COSTOS!$C$8+F36*COSTOS!$C$9+G36*COSTOS!$C$10)))+K36,IF(H36="","",H36-(C36*COSTOS!$C$6+D36*COSTOS!$C$7+E36*COSTOS!$C$8+F36*COSTOS!$C$9+G36*COSTOS!$C$10)))
L37: =IF(K37<>"",(IF(H37="","",H37-(C37*COSTOS!$C$6+D37*COSTOS!$C$7+E37*COSTOS!$C$8+F37*COSTOS!$C$9+G37*COSTOS!$C$10)))+K37,IF(H37="","",H37-(C37*COSTOS!$C$6+D37*COSTOS!$C$7+E37*COSTOS!$C$8+F37*COSTOS!$C$9+G37*COSTOS!$C$10)))
L38: =IF(K38<>"",(IF(H38="","",H38-(C38*COSTOS!$C$6+D38*COSTOS!$C$7+E38*COSTOS!$C$8+F38*COSTOS!$C$9+G38*COSTOS!$C$10)))+K38,IF(H38="","",H38-(C38*COSTOS!$C$6+D38*COSTOS!$C$7+E38*COSTOS!$C$8+F38*COSTOS!$C$9+G38*COSTOS!$C$10)))
L39: =IF(K39<>"",(IF(H39="","",H39-(C39*COSTOS!$C$6+D39*COSTOS!$C$7+E39*COSTOS!$C$8+F39*COSTOS!$C$9+G39*COSTOS!$C$10)))+K39,IF(H39="","",H39-(C39*COSTOS!$C$6+D39*COSTOS!$C$7+E39*COSTOS!$C$8+F39*COSTOS!$C$9+G39*COSTOS!$C$10)))
L40: =IF(K40<>"",(IF(H40="","",H40-(C40*COSTOS!$C$6+D40*COSTOS!$C$7+E40*COSTOS!$C$8+F40*COSTOS!$C$9+G40*COSTOS!$C$10)))+K40,IF(H40="","",H40-(C40*COSTOS!$C$6+D40*COSTOS!$C$7+E40*COSTOS!$C$8+F40*COSTOS!$C$9+G40*COSTOS!$C$10)))
L41: =IF(K41<>"",(IF(H41="","",H41-(C41*COSTOS!$C$6+D41*COSTOS!$C$7+E41*COSTOS!$C$8+F41*COSTOS!$C$9+G41*COSTOS!$C$10)))+K41,IF(H41="","",H41-(C41*COSTOS!$C$6+D41*COSTOS!$C$7+E41*COSTOS!$C$8+F41*COSTOS!$C$9+G41*COSTOS!$C$10)))
... L500: =IF(K500<>"",(IF(H500="","",H500-(C500*COSTOS!$C$6+D500*COSTOS!$C$7+E500*COSTOS!$C$8+F500*COSTOS!$C$9+G500*COSTOS!$C$10)))+K500,IF(H500="","",H500-(C500*COSTOS!$C$6+D500*COSTOS!$C$7+E500*COSTOS!$C$8+F500*COSTOS!$C$9+G500*COSTOS!$C$10)))
A501: TOTALES DEL MES | C501: =IFERROR(SUM(C5:C500),0) | D501: =IFERROR(SUM(D5:D500),0) | E501: =IFERROR(SUM(E5:E500),0) | F501: =IFERROR(SUM(F5:F500),0) | G501: =IFERROR(SUM(G5:G500),0)

Sheet GASTOS
A1: GASTOS Y GASOIL 2026 — Registro mensual de egresos
A3: ENERO 2026 | O3: INVERSIÓN ENVASES
A4: FECHA | B4: DESCRIPCIÓN | C4: MONTO ($) | D4: PAGADO | F4: FECHA | G4: MONTO ($) | H4: LITROS | J4: TOTAL MES ($) | O4: FECHA | P4: DESCRIPCIÓN | Q4: CANT. | R4: COSTO UNIT. ($) | S4: TOTAL ($)
O5: 46143 | P5: Cilindro 45kg | Q5: 2 | R5: 60000 | S5: =Q5*R5
A15: TOTAL ENERO | C15: =IFERROR(SUM(C5:C14),0) | G15: =IFERROR(SUM(G5:G14),0) | H15: =IFERROR(SUM(H5:H14),0) | J15: =IFERROR(C15+G15,0)
A17: FEBRERO 2026
A18: FECHA | B18: DESCRIPCIÓN | C18: MONTO ($) | D18: PAGADO | F18: FECHA | G18: MONTO ($) | H18: LITROS | J18: TOTAL MES ($)
A29: TOTAL FEBRERO | C29: =IFERROR(SUM(C19:C28),0) | G29: =IFERROR(SUM(G19:G28),0) | H29: =IFERROR(SUM(H19:H28),0) | J29: =IFERROR(C29+G29,0)
A31: MARZO 2026
A32: FECHA | B32: DESCRIPCIÓN | C32: MONTO ($) | D32: PAGADO | F32: FECHA | G32: MONTO ($) | H32: LITROS | J32: TOTAL MES ($)
A43: TOTAL MARZO | C43: =IFERROR(SUM(C33:C42),0) | G43: =IFERROR(SUM(G33:G42),0) | H43: =IFERROR(SUM(H33:H42),0) | J43: =IFERROR(C43+G43,0)
A45: ABRIL 2026
A46: FECHA | B46: DESCRIPCIÓN | C46: MONTO ($) | D46: PAGADO | F46: FECHA | G46: MONTO ($) | H46: LITROS | J46: TOTAL MES ($)
A57: TOTAL ABRIL | C57: =IFERROR(SUM(C47:C56),0) | G57: =IFERROR(SUM(G47:G56),0) | H57: =IFERROR(SUM(H47:H56),0) | J57: =IFERROR(C57+G57,0)
A59: MAYO 2026
A60: FECHA | B60: DESCRIPCIÓN | C60: MONTO ($) | D60: PAGADO | F60: FECHA | G60: MONTO ($) | H60: LITROS | J60: TOTAL MES ($)
A71: TOTAL MAYO | C71: =IFERROR(SUM(C61:C70),0) | G71: =IFERROR(SUM(G61:G70),0) | H71: =IFERROR(SUM(H61:H70),0) | J71: =IFERROR(C71+G71,0)
A73: JUNIO 2026
A74: FECHA | B74: DESCRIPCIÓN | C74: MONTO ($) | D74: PAGADO | F74: FECHA | G74: MONTO ($) | H74: LITROS | J74: TOTAL MES ($)
A85: TOTAL JUNIO | C85: =IFERROR(SUM(C75:C84),0) | G85: =IFERROR(SUM(G75:G84),0) | H85: =IFERROR(SUM(H75:H84),0) | J85: =IFERROR(C85+G85,0)
A87: JULIO 2026
A88: FECHA | B88: DESCRIPCIÓN | C88: MONTO ($) | D88: PAGADO | F88: FECHA | G88: MONTO ($) | H88: LITROS | J88: TOTAL MES ($)
A99: TOTAL JULIO | C99: =IFERROR(SUM(C89:C98),0) | G99: =IFERROR(SUM(G89:G98),0) | H99: =IFERROR(SUM(H89:H98),0) | J99: =IFERROR(C99+G99,0)
A101: AGOSTO 2026
A102: FECHA | B102: DESCRIPCIÓN | C102: MONTO ($) | D102: PAGADO | F102: FECHA | G102: MONTO ($) | H102: LITROS | J102: TOTAL MES ($)
A113: TOTAL AGOSTO | C113: =IFERROR(SUM(C103:C112),0) | G113: =IFERROR(SUM(G103:G112),0) | H113: =IFERROR(SUM(H103:H112),0) | J113: =IFERROR(C113+G113,0)
A115: SEPTIEMBRE 2026
A116: FECHA | B116: DESCRIPCIÓN | C116: MONTO ($) | D116: PAGADO | F116: FECHA | G116: MONTO ($) | H116: LITROS | J116: TOTAL MES ($)
A127: TOTAL SEPTIEMBRE | C127: =IFERROR(SUM(C117:C126),0) | G127: =IFERROR(SUM(G117:G126),0) | H127: =IFERROR(SUM(H117:H126),0) | J127: =IFERROR(C127+G127,0)
A129: OCTUBRE 2026
A130: FECHA | B130: DESCRIPCIÓN | C130: MONTO ($) | D130: PAGADO | F130: FECHA | G130: MONTO ($) | H130: LITROS | J130: TOTAL MES ($)
A141: TOTAL OCTUBRE | C141: =IFERROR(SUM(C131:C140),0) | G141: =IFERROR(SUM(G131:G140),0) | H141: =IFERROR(SUM(H131:H140),0) | J141: =IFERROR(C141+G141,0)
A143: NOVIEMBRE 2026
A144: FECHA | B144: DESCRIPCIÓN | C144: MONTO ($) | D144: PAGADO | F144: FECHA | G144: MONTO ($) | H144: LITROS | J144: TOTAL MES ($)
A155: TOTAL NOVIEMBRE | C155: =IFERROR(SUM(C145:C154),0) | G155: =IFERROR(SUM(G145:G154),0) | H155: =IFERROR(SUM(H145:H154),0) | J155: =IFERROR(C155+G155,0)
A157: DICIEMBRE 2026
A158: FECHA | B158: DESCRIPCIÓN | C158: MONTO ($) | D158: PAGADO | F158: FECHA | G158: MONTO ($) | H158: LITROS | J158: TOTAL MES ($)
A169: TOTAL DICIEMBRE | C169: =IFERROR(SUM(C159:C168),0) | G169: =IFERROR(SUM(G159:G168),0) | H169: =IFERROR(SUM(H159:H168),0) | J169: =IFERROR(C169+G169,0)
A200: 2026-06-01 | B200: Personal/Varios | C200: Gasto diario | D200: 5600
A201: 2026-06-01 | B201: Personal/Varios | C201: Gasto diario | D201: 24000
A202: 2026-06-02 | B202: Personal/Varios | C202: Gasto diario | D202: 20000
A203: 2026-06-02 | B203: Combustible | C203: Gasoil | D203: 77000
A204: 2026-06-02 | B204: Salud | C204: Psicologa Paz y Vitto | D204: 80000
A205: 2026-06-02 | B205: Personal/Varios | C205: Gasto diario | D205: 6000
A206: 2026-06-03 | B206: Combustible | C206: Gasoil | D206: 86000
A207: 2026-06-04 | B207: Combustible | C207: Gasoil | D207: 100000
A208: 2026-06-04 | B208: Personal/Varios | C208: Gasto Sandra marca particular | D208: 20000
A209: 2026-06-05 | B209: Personal/Varios | C209: Gasto diario | D209: 3000
A210: 2026-06-06 | B210: Combustible | C210: Gasoil | D210: 100000
A211: 2026-06-06 | B211: Personal/Varios | C211: Pantalon personal | D211: 55000
... A218: 2026-06-08 | B218: Personal/Varios | C218: Gasto Sandra | D218: 20000

Sheet LISTAS
A1: LISTAS DE REFERENCIA — No modificar
A2: CLIENTES | B2: PRODUCTOS
A3: 1 DE MAYO 1605 | B3: Garrafa 10
A4: 1 DE MAYO 1959 BARSANTA | B4: Garrafa 15
A5: 1 DE MAYO 8361 | B5: Garrafa 45
A6: 12 DE INFANTERIA 2148 | B6: Yerba 500gr
A7: 20 DE JUNIO Y 9 DE JULIO | B7: Bidón
A8: 25 DE MAYO 2617
A9: 25 DE MAYO 3771
A10: 25 DE MAYO 8347
A11: 4 DE ENERO 1342
A12: 4 DE ENERO 3526
A13: 4 DE ENERO 6625
A14: 7 JEFES 4525
A15: 9 DE JULIO 1144
A16: 9 DE JULIO 1144 BAR
A17: 9 DE JULIO 2109
A18: 9 DE JULIO 2366
A19: 9 DE JULIO 6543
... A676: ZAVALLA 8455

Sheet RANKING
A1: 🏆 RANKING ANUAL DE CLIENTES 2026
A2: 🔍 Para buscar un cliente: usá la flecha ▼ de la columna CLIENTE en la tabla de abajo → destildá "Seleccionar todo" → tildá el cliente que querés.
A4: 📊 RANKING ANUAL — ordenado por facturación total
A5: # | B5: Cliente | C5: Facturado ($) | D5: Ganancia ($) | E5: Margen % | F5: Pedidos | G5: 10 | H5: 15 | I5: 45 | J5: Yerba | K5: Agua | L5: Última compra
A6: 🥇 | B6: OTNIEL | C6: 2968700 | D6: 1110860 | E6: 0.3742 | F6: 48 | G6: 8 | H6: 29 | I6: 20 | J6: 32 | K6: 40 | L6: 31/05/2026
A7: 🥈 | B7: FILOMENA | C7: 2464500 | D7: 902700 | E7: 0.3663 | F7: 68 | G7: 118 | L7: 30/05/2026
A8: 🥉 | B8: LUCHO | C8: 2381800 | D8: 562680 | E8: 0.2362 | F8: 73 | G8: 107 | H8: 18 | L8: 29/05/2026
A9: 4 | B9: AZCUENAGA 5023 | C9: 2318500 | D9: 496200 | E9: 0.214 | F9: 30 | G9: 123 | H9: 12 | K9: 10 | L9: 14/05/2026
A10: 5 | B10: CAREN | C10: 2219000 | D10: 671000 | E10: 0.3024 | F10: 29 | I10: 29 | L10: 30/05/2026
A11: 6 | B11: EXE | C11: 2101000 | D11: 631000 | E11: 0.3003 | F11: 26 | G11: 2 | I11: 27 | L11: 27/05/2026
A12: 7 | B12: SABOREAR | C12: 1869500 | D12: 625750 | E12: 0.3347 | F12: 44 | G12: 34 | H12: 11 | I12: 11 | L12: 30/05/2026
A13: 8 | B13: TROPPO | C13: 1858000 | D13: 763600 | E13: 0.411 | F13: 15 | G13: 52 | L13: 30/05/2026
A14: 9 | B14: BRASERIA | C14: 1534000 | D14: 468200 | E14: 0.3052 | F14: 19 | G14: 1 | I14: 19 | L14: 29/05/2026
A15: 10 | B15: PANA VIEYTES 4500 | C15: 1498000 | D15: 390500 | E15: 0.2607 | F15: 20 | G15: 1 | I15: 20 | L15: 28/05/2026
A16: 11 | B16: PANA GENESIO | C16: 1307500 | D16: 386000 | E16: 0.2952 | F16: 20 | G16: 5 | I16: 17 | L16: 27/05/2026
A17: 12 | B17: PANA ALBERTI | C17: 1289000 | D17: 391750 | E17: 0.3039 | F17: 18 | G17: 3 | H17: 2 | I17: 15 | L17: 28/05/2026
A18: 13 | B18: SANDRA | C18: 1119500 | D18: 286810 | E18: 0.2562 | F18: 41 | G18: 50 | H18: 8 | J18: 2 | K18: 11 | L18: 30/05/2026
A19: 14 | B19: DANA | C19: 1034000 | D19: 208800 | E19: 0.2019 | F19: 16 | G19: 48 | H19: 4 | L19: 28/05/2026
A20: 15 | B20: ROTI AGUADO | C20: 958000 | D20: 308500 | E20: 0.322 | F20: 14 | G20: 5 | H20: 13 | I20: 6 | L20: 28/05/2026
A21: 16 | B21: 9 DE JULIO 1144 | C21: 945000 | D21: 316000 | E21: 0.3344 | F21: 6 | I21: 11 | L21: 25/05/2026
A22: 17 | B22: PAULO | C22: 900000 | D22: 186650 | E22: 0.2074 | F22: 22 | G22: 49 | H22: 3 | L22: 30/05/2026
A23: 18 | B23: PANA GORRITI 4600 | C23: 869000 | D23: 264000 | E23: 0.3038 | F23: 11 | I23: 11 | L23: 25/05/2026
A24: 19 | B24: DOMINGO SILVA 4217 | C24: 765500 | D24: 175950 | E24: 0.2298 | F24: 14 | G24: 33 | H24: 7 | L24: 25/05/2026
A25: 20 | B25: ROTI SAN LORENZO | C25: 758500 | D25: 279750 | E25: 0.3688 | F25: 9 | G25: 12 | H25: 10 | I25: 2 | L25: 21/05/2026
A26: 21 | B26: ROTI VIEYTES | C26: 745000 | D26: 192700 | E26: 0.2587 | F26: 14 | G26: 1 | H26: 26 | L26: 30/05/2026
A27: 22 | B27: SANTA BAR 1 MAYO 1959 | C27: 629000 | D27: 186000 | E27: 0.2957 | F27: 7 | G27: 1 | I27: 7 | L27: 23/05/2026
A28: 23 | B28: COGORNO 5520 | C28: 606500 | D28: 139400 | E28: 0.2298 | F28: 7 | G28: 35 | L28: 22/05/2026
A29: 24 | B29: PANA BERUTI 6400 | C29: 576000 | D29: 133000 | E29: 0.2309 | F29: 7 | I29: 8 | L29: 19/05/2026
A30: 25 | B30: PANA VIEYTES 3800 | C30: 571000 | D30: 170200 | E30: 0.2981 | F30: 7 | G30: 1 | I30: 7 | L30: 22/05/2026
A31: 26 | B31: MARTINEZ 3221 | C31: 469000 | D31: 174000 | E31: 0.371 | F31: 4 | G31: 5 | I31: 4 | L31: 27/05/2026
A32: 27 | B32: LOBOS | C32: 457000 | D32: 159600 | E32: 0.3492 | F32: 4 | G32: 5 | H32: 2 | I32: 3 | L32: 29/05/2026
A33: 28 | B33: NACHO | C33: 449000 | D33: 144500 | E33: 0.3218 | F33: 18 | G33: 14 | H33: 7 | L33: 02/04/2026
A34: 29 | B34: VIANDAS JORGE | C34: 423000 | D34: 132300 | E34: 0.3128 | F34: 19 | G34: 19 | L34: 30/05/2026
A35: 30 | B35: ASCUÉNAGA 5023 | C35: 408500 | D35: 88200 | E35: 0.2159 | F35: 4 | G35: 16 | H35: 3 | L35: 29/05/2026
A36: 31 | B36: CHICLANA 7325 | C36: 405500 | D36: 84200 | E36: 0.2076 | F36: 17 | G36: 23 | L36: 28/05/2026
A37: 32 | B37: LOS PRIMOS | C37: 404000 | D37: 167000 | E37: 0.4134 | F37: 6 | G37: 12 | H37: 2 | L37: 31/05/2026
A38: 33 | B38: GENERAL PAZ 7826 | C38: 387000 | D38: 146000 | E38: 0.3773 | F38: 7 | G38: 6 | I38: 3 | L38: 14/05/2026
A39: 34 | B39: SAVEDRA 10125 | C39: 383000 | D39: 141300 | E39: 0.3689 | F39: 4 | H39: 1 | I39: 4 | L39: 15/05/2026
A40: 35 | B40: ROTI VIEYTES | C40: 355000 | D40: 85000 | E40: 0.2394 | F40: 6 | H40: 14 | L40: 17/04/2026
A41: 36 | B41: RIO NEGRO 6558 | C41: 347000 | D41: 253000 | E41: 0.7291 | F41: 2 | I41: 2 | L41: 13/02/2026
A42: 37 | B42: GOLD BURGER | C42: 347000 | D42: 141600 | E42: 0.4081 | F42: 3 | G42: 13 | L42: 23/05/2026
A43: 38 | B43: D SILVA 4217 | C43: 345500 | D43: 74750 | E43: 0.2164 | F43: 7 | G43: 20 | H43: 1 | L43: 11/04/2026
A44: 39 | B44: MARIO | C44: 335500 | D44: 69300 | E44: 0.2066 | F44: 6 | G44: 14 | H44: 2 | L44: 30/05/2026
A45: 40 | B45: BERUTI 4075 | C45: 334000 | D45: 116000 | E45: 0.3473 | F45: 2 | I45: 4 | L45: 04/05/2026
A46: 41 | B46: NAMUNCURA 4436 | C46: 326000 | D46: 110000 | E46: 0.3374 | F46: 4 | I46: 4 | L46: 05/05/2026
A47: 42 | B47: GOLD BURGUER | C47: 322000 | D47: 134000 | E47: 0.4161 | F47: 2 | I47: 4 | J47: 6 | L47: 09/02/2026
A48: 43 | B48: GOLD BURGUER | C48: 322000 | D48: 134000 | E48: 0.4161 | F48: 2 | I48: 4 | J48: 22 | L48: 20/02/2026
A49: 44 | B49: PANA BERUTI 3850 | C49: 317000 | D49: 77000 | E49: 0.2429 | F49: 3 | G49: 4 | I49: 3 | L49: 25/04/2026
A50: 45 | B50: LOLI | C50: 313000 | D50: 120400 | E50: 0.3847 | F50: 6 | G50: 3 | H50: 1 | I50: 1 | J50: 2 | L50: 27/05/2026
A51: 46 | B51: BRASERIA | C51: 303000 | D51: 100000 | E51: 0.33 | F51: 4 | I51: 4 | L51: 04/04/2026
A52: 47 | B52: PANA VIEYTES GISELA | C52: 290800 | D52: 106500 | E52: 0.3662 | F52: 14 | G52: 13 | L52: 28/05/2026
A53: 48 | B53: ALSINA 9251 | C53: 278000 | D53: 106500 | E53: 0.3831 | F53: 3 | G53: 1 | I53: 3 | L53: 30/05/2026
A54: 49 | B54: GABOTO 8168 | C54: 266000 | D54: 84000 | E54: 0.3158 | F54: 3 | I54: 3 | L54: 28/05/2026
A55: 50 | B55: LAVAISE 3786 | C55: 263500 | D55: 114200 | E55: 0.4334 | F55: 6 | G55: 7 | H55: 3 | L55: 27/05/2026
A56: 51 | B56: GASTON AMARAL | C56: 263000 | D56: 89400 | E56: 0.3399 | F56: 3 | I56: 3 | L56: 14/05/2026
A57: 52 | B57: TACUARI 5717 | C57: 255000 | D57: 110900 | E57: 0.4349 | F57: 10 | G57: 11 | L57: 16/05/2026
A58: 53 | B58: NOGALES 2412 | C58: 255000 | D58: 97000 | E58: 0.3804 | F58: 3 | I58: 3 | L58: 09/05/2026
A59: 54 | B59: ESMERALDA 2376 | C59: 246000 | D59: 77000 | E59: 0.313 | F59: 3 | I59: 3 | J59: 20 | L59: 18/05/2026
A60: 55 | B60: PORKIS | C60: 241500 | D60: 78600 | E60: 0.3255 | F60: 7 | G60: 7 | I60: 1 | L60: 24/05/2026
A61: 56 | B61: GOLD COSTA ESTE | C61: 231000 | D61: 90000 | E61: 0.3896 | F61: 1 | I61: 3 | L61: 06/01/2026
A62: 57 | B62: SANTA CRUZ 3051 | C62: 231000 | D62: 51000 | E62: 0.2208 | F62: 3 | I62: 3 | L62: 03/05/2026
A63: 58 | B63: PEDRO CEBALLOS 8134 | C63: 229000 | D63: 48800 | E63: 0.2131 | F63: 5 | G63: 13 | L63: 18/05/2026
A64: 59 | B64: MARIELA | C64: 219000 | D64: 53000 | E64: 0.242 | F64: 1 | I64: 2 | K64: 5 | L64: 25/03/2026
A65: 60 | B65: PANA GENESIO | C65: 207000 | D65: 66000 | E65: 0.3188 | F65: 3 | I65: 3 | L65: 27/02/2026
A66: 61 | B66: LO DE NICO | C66: 205000 | D66: 47000 | E66: 0.2293 | F66: 3 | G66: 10 | L66: 28/05/2026
A67: 62 | B67: ALBERTI 4930 | C67: 201000 | D67: 87900 | E67: 0.4373 | F67: 5 | I67: 2 | L67: 29/04/2026
A68: 63 | B68: LAVADERO | C68: 200000 | D68: 45800 | E68: 0.229 | F68: 9 | G68: 8 | H68: 3 | L68: 20/05/2026
A69: 64 | B69: GABOTO 7320 | C69: 196000 | D69: 59000 | E69: 0.301 | F69: 2 | G69: 1 | I69: 2 | L69: 16/05/2026
A70: 65 | B70: COSTA ESTE 1980 | C70: 196000 | D70: 85400 | E70: 0.4357 | F70: 2 | G70: 7 | L70: 23/05/2026
A71: 66 | B71: LARGUIA 6924 | C71: 194500 | D71: 78100 | E71: 0.4015 | F71: 7 | G71: 8 | L71: 27/05/2026
A72: 67 | B72: PAVÓN 3435 | C72: 194500 | D72: 61400 | E72: 0.3157 | F72: 3 | H72: 3 | I72: 1 | L72: 31/05/2026
A73: 68 | B73: PUBLICO 2527 | C73: 188000 | D73: 76050 | E73: 0.4045 | F73: 4 | G73: 3 | H73: 3 | L73: 28/05/2026
A74: 69 | B74: FREY AROCA 9560 ESCUELA | C74: 187900 | D74: 67900 | E74: 0.3614 | F74: 1 | I74: 2 | L74: 24/04/2026
A75: 70 | B75: BAIGORRIA 9351 | C75: 185000 | D75: 65000 | E75: 0.3514 | F75: 2 | I75: 2 | L75: 06/05/2026
A76: 71 | B76: FLORENCIO FERNANDEZ 6196 | C76: 185000 | D76: 35000 | E76: 0.1892 | F76: 1 | G76: 10 | L76: 02/05/2026
A77: 72 | B77: VIEYTES 4361 | C77: 180000 | D77: 71000 | E77: 0.3944 | F77: 4 | G77: 7 | L77: 28/05/2026
A78: 73 | B78: REMEDIO DE ESCALADA | C78: 180000 | D78: 60000 | E78: 0.3333 | F78: 1 | I78: 2 | L78: 02/05/2026
A79: 74 | B79: AZCUENAGA 6551 | C79: 179500 | D79: 35400 | E79: 0.1972 | F79: 3 | G79: 8 | H79: 1 | L79: 23/05/2026
A80: 75 | B80: DUSO 7678 | C80: 178500 | D80: 36750 | E80: 0.2059 | F80: 1 | G80: 9 | H80: 1 | L80: 22/03/2026
A81: 76 | B81: GRAL PAZ 7826 | C81: 178000 | D81: 69500 | E81: 0.3904 | F81: 2 | G81: 1 | I81: 2 | L81: 14/03/2026
A82: 77 | B82: ANGEL | C82: 175000 | D82: 33250 | E82: 0.19 | F82: 7 | G82: 7 | H82: 2 | L82: 29/04/2026
A83: 78 | B83: MARCE DUSO | C83: 174000 | D83: 43300 | E83: 0.2489 | F83: 2 | G83: 3 | H83: 1 | I83: 1 | L83: 22/05/2026
A84: 79 | B84: PANA GORRITI 6500 | C84: 173000 | D84: 51000 | E84: 0.2948 | F84: 2 | I84: 2 | L84: 15/05/2026
A85: 80 | B85: TERE | C85: 172000 | D85: 52000 | E85: 0.3023 | F85: 1 | I85: 2 | L85: 02/04/2026
A86: 81 | B86: ARENALES 10625 | C86: 172000 | D86: 31000 | E86: 0.1802 | F86: 3 | G86: 5 | I86: 1 | L86: 23/05/2026
A87: 82 | B87: LARGUIA 7186 | C87: 171000 | D87: 49000 | E87: 0.2865 | F87: 2 | I87: 2 | L87: 16/05/2026
A88: 83 | B88: HUERGO 3961 | C88: 170000 | D88: 46000 | E88: 0.2706 | F88: 1 | I88: 2 | L88: 22/05/2026
A89: 84 | B89: ROTI SAN LORENZO | C89: 168000 | D89: 66750 | E89: 0.3973 | F89: 2 | G89: 3 | H89: 3 | L89: 15/04/2026
A90: 85 | B90: MARCIAL CANDIOTI 8968 | C90: 168000 | D90: 59000 | E90: 0.3512 | F90: 2 | I90: 2 | L90: 09/05/2026
A91: 86 | B91: RIVADAVIA 8280 | C91: 168000 | D91: 61000 | E91: 0.3631 | F91: 2 | I91: 2 | L91: 01/05/2026
A92: 87 | B92: PIEDRABUENA 4506 | C92: 168000 | D92: 59000 | E92: 0.3512 | F92: 2 | I92: 2 | L92: 01/05/2026
A93: 88 | B93: GOROSTIAGA 4659 | C93: 168000 | D93: 57000 | E93: 0.3393 | F93: 2 | I93: 2 | L93: 15/05/2026
A94: 89 | B94: DAMIANOVICH 6212 | C94: 167000 | D94: 58000 | E94: 0.3473 | F94: 2 | I94: 2 | L94: 14/05/2026
A95: 90 | B95: ALSINA 7980 | C95: 167000 | D95: 63700 | E95: 0.3814 | F95: 4 | G95: 3 | I95: 1 | L95: 09/05/2026
A96: 91 | B96: PUBLICO 8821 | C96: 166000 | D96: 57000 | E96: 0.3434 | F96: 2 | I96: 2 | L96: 13/05/2026
A97: 92 | B97: J D SOLIS 10529 | C97: 166000 | D97: 68000 | E97: 0.4096 | F97: 1 | I97: 2 | L97: 14/03/2026
A98: 93 | B98: ALBERTI 5570 | C98: 166000 | D98: 46000 | E98: 0.2771 | F98: 1 | I98: 2 | L98: 01/04/2026
A99: 94 | B99: MONTIEL 9165 | C99: 163000 | D99: 54000 | E99: 0.3313 | F99: 2 | I99: 2 | L99: 17/05/2026
A100: 95 | B100: ÁNGEL | C100: 161500 | D100: 28400 | E100: 0.1759 | F100: 5 | G100: 1 | H100: 5 | L100: 14/05/2026
A101: 96 | B101: ALSINA 7981 | C101: 161000 | D101: 54000 | E101: 0.3354 | F101: 2 | I101: 2 | L101: 02/05/2026
...
